Workbook

Sheet Financial>

Sheet Ratio Analysis
B2: ="Ratio Analysis - "&'Data Sheet'!B1 -> Ratio Analysis - INFOSYS LTD
B3: Years | C3: ='[1]Data Sheet'!B16 -> 42460 | D3: ='[1]Data Sheet'!C16 -> 42825 | E3: ='[1]Data Sheet'!D16 -> 43190 | F3: ='[1]Data Sheet'!E16 -> 43555 | G3: ='[1]Data Sheet'!F16 -> 43921 | H3: ='[1]Data Sheet'!G16 -> 44286 | I3: ='[1]Data Sheet'!H16 -> 44651 | J3: ='[1]Data Sheet'!I16 -> 45016 | ... L3: ='[1]Data Sheet'!K16 -> 45747 | M3: Trend | N3: Mean | O3: Median
B5: Sales Growth | D5: =IFERROR('Historical FS'!D7,0) -> 0.09677936 | E5: =IFERROR('Historical FS'!E7,0) -> 0.029758776 | F5: =IFERROR('Historical FS'!F7,0) -> 0.1723292 | G5: =IFERROR('Historical FS'!G7,0) -> 0.098167523 | H5: =IFERROR('Historical FS'!H7,0) -> 0.10662951 | I5: =IFERROR('Historical FS'!I7,0) -> 0.21069552 | J5: =IFERROR('Historical FS'!J7,0) -> 0.20655864 | K5: =IFERROR('Historical FS'!K7,0) -> 0.047033734 | L5: =IFERROR('Historical FS'!L7,0) -> 0.060649444 | N5: =IFERROR(AVERAGE(D5:L5),0) -> 0.11428908 | O5: =IFERROR(MEDIAN(D5:L5),0) -> 0.098167523
B6: EBITDA Growth | D6: =IFERROR('Historical FS'!D18/'Historical FS'!C18-1,0) -> 0.089290942 | E6: =IFERROR('Historical FS'!E18/'Historical FS'!D18-1,0) -> 0.01171791 | F6: =IFERROR('Historical FS'!F18/'Historical FS'!E18-1,0) -> 0.071618319 | G6: =IFERROR('Historical FS'!G18/'Historical FS'!F18-1,0) -> 0.10396629 | H6: =IFERROR('Historical FS'!H18/'Historical FS'!G18-1,0) -> 0.25248125 | I6: =IFERROR('Historical FS'!I18/'Historical FS'!H18-1,0) -> 0.12915486 | J6: =IFERROR('Historical FS'!J18/'Historical FS'!I18-1,0) -> 0.11555683 | K6: =IFERROR('Historical FS'!K18/'Historical FS'!J18-1,0) -> 0.03686308 | L6: =IFERROR('Historical FS'!L18/'Historical FS'!K18-1,0) -> 0.077172272 | N6: =IFERROR(AVERAGE(D6:L6),0) -> 0.098646861 | O6: =IFERROR(MEDIAN(D6:L6),0) -> 0.089290942
B7: EBIT Growth | D7: =IFERROR('Historical FS'!D27/'Historical FS'!C27-1,0) -> 0.082010243 | E7: =IFERROR('Historical FS'!E27/'Historical FS'!D27-1,0) -> 0.0034317496 | F7: =IFERROR('Historical FS'!F27/'Historical FS'!E27-1,0) -> 0.070758889 | G7: =IFERROR('Historical FS'!G27/'Historical FS'!F27-1,0) -> 0.057547222 | H7: =IFERROR('Historical FS'!H27/'Historical FS'!G27-1,0) -> 0.27197459 | I7: =IFERROR('Historical FS'!I27/'Historical FS'!H27-1,0) -> 0.13869898 | J7: =IFERROR('Historical FS'!J27/'Historical FS'!I27-1,0) -> 0.10088082 | K7: =IFERROR('Historical FS'!K27/'Historical FS'!J27-1,0) -> 0.021423206 | L7: =IFERROR('Historical FS'!L27/'Historical FS'!K27-1,0) -> 0.087316558 | N7: =IFERROR(AVERAGE(D7:L7),0) -> 0.092671362 | O7: =IFERROR(MEDIAN(D7:L7),0) -> 0.082010243
B8: Net Profit Growth | D8: =IFERROR('Historical FS'!D33/'Historical FS'!C33-1,0) -> 0.090076189 | E8: =IFERROR('Historical FS'!E33/'Historical FS'!D33-1,0) -> 0.125188 | F8: =IFERROR('Historical FS'!F33/'Historical FS'!E33-1,0) -> -0.014939456 | G8: =IFERROR('Historical FS'!G33/'Historical FS'!F33-1,0) -> 0.10440613 | H8: =IFERROR('Historical FS'!H33/'Historical FS'!G33-1,0) -> 0.24472391 | I8: =IFERROR('Historical FS'!I33/'Historical FS'!H33-1,0) -> 0.15265358 | J8: =IFERROR('Historical FS'!J33/'Historical FS'!I33-1,0) -> 0.078383961 | K8: =IFERROR('Historical FS'!K33/'Historical FS'!J33-1,0) -> 0.0060727799 | L8: =IFERROR('Historical FS'!L33/'Historical FS'!K33-1,0) -> 0.074894368 | N8: =IFERROR(AVERAGE(D8:L8),0) -> 0.095717718 | O8: =IFERROR(MEDIAN(D8:L8),0) -> 0.090076189
B9: Dividend Growth | D9: =IFERROR('Historical FS'!D41/'Historical FS'!C41-1,0) -> 0.06185567 | E9: =IFERROR('Historical FS'!E41/'Historical FS'!D41-1,0) -> 0.68963897 | F9: =IFERROR('Historical FS'!F41/'Historical FS'!E41-1,0) -> -0.02583858 | G9: =IFERROR('Historical FS'!G41/'Historical FS'!F41-1,0) -> -0.17390646 | H9: =IFERROR('Historical FS'!H41/'Historical FS'!G41-1,0) -> 0.54369512 | I9: =IFERROR('Historical FS'!I41/'Historical FS'!H41-1,0) -> 0.14865158 | J9: =IFERROR('Historical FS'!J41/'Historical FS'!I41-1,0) -> 0.096761529 | K9: =IFERROR('Historical FS'!K41/'Historical FS'!J41-1,0) -> 0.35349861 | L9: =IFERROR('Historical FS'!L41/'Historical FS'!K41-1,0) -> -0.064855345 | N9: =IFERROR(AVERAGE(D9:L9),0) -> 0.18105568 | O9: =IFERROR(MEDIAN(D9:L9),0) -> 0.096761529
B11: Gross Margin | C11: =IFERROR('Historical FS'!C13,0) -> 0.35151583 | D11: =IFERROR('Historical FS'!D13,0) -> 0.34862158 | E11: =IFERROR('Historical FS'!E13,0) -> 0.34212019 | F11: =IFERROR('Historical FS'!F13,0) -> 0.32934986 | G11: =IFERROR('Historical FS'!G13,0) -> 0.31479993 | H11: =IFERROR('Historical FS'!H13,0) -> 0.31831754 | I11: =IFERROR('Historical FS'!I13,0) -> 0.30271043 | J11: =IFERROR('Historical FS'!J13,0) -> 0.28539794 | ... L11: =IFERROR('Historical FS'!L13,0) -> 0.28471072 | N11: =IFERROR(AVERAGE(C11:L11),0) -> 0.31615292 | O11: =IFERROR(MEDIAN(C11:L11),0) -> 0.31655873
B12: EBITDA Margin | C12: =IFERROR('Historical FS'!C19,0) -> 0.2735222 | D12: =IFERROR('Historical FS'!D19,0) -> 0.27165469 | E12: =IFERROR('Historical FS'!E19,0) -> 0.26689544 | F12: =IFERROR('Historical FS'!F19,0) -> 0.24396734 | G12: =IFERROR('Historical FS'!G19,0) -> 0.24525559 | H12: =IFERROR('Historical FS'!H19,0) -> 0.27757982 | I12: =IFERROR('Historical FS'!I19,0) -> 0.25888475 | J12: =IFERROR('Historical FS'!J19,0) -> 0.23935898 | ... L12: =IFERROR('Historical FS'!L19,0) -> 0.24072642 | N12: =IFERROR(AVERAGE(C12:L12),0) -> 0.25548792 | O12: =IFERROR(MEDIAN(C12:L12),0) -> 0.25207017
B13: EBIT Margin | C13: =IFERROR(('Historical FS'!C18-'Historical FS'!C24)/'Historical FS'!C6,0) -> 0.25015615 | D13: =IFERROR(('Historical FS'!D18-'Historical FS'!D24)/'Historical FS'!D6,0) -> 0.24678757 | E13: =IFERROR(('Historical FS'!E18-'Historical FS'!E24)/'Historical FS'!E6,0) -> 0.24047815 | F13: =IFERROR(('Historical FS'!F18-'Historical FS'!F24)/'Historical FS'!F6,0) -> 0.21964318 | G13: =IFERROR(('Historical FS'!G18-'Historical FS'!G24)/'Historical FS'!G6,0) -> 0.2133912 | H13: =IFERROR(('Historical FS'!H18-'Historical FS'!H24)/'Historical FS'!H6,0) -> 0.2450633 | I13: =IFERROR(('Historical FS'!I18-'Historical FS'!I24)/'Historical FS'!I6,0) -> 0.23030886 | J13: =IFERROR(('Historical FS'!J18-'Historical FS'!J24)/'Historical FS'!J6,0) -> 0.21057186 | ... L13: =IFERROR(('Historical FS'!L18-'Historical FS'!L24)/'Historical FS'!L6,0) -> 0.21120314 | N13: =IFERROR(AVERAGE(C13:L13),0) -> 0.22741955 | O13: =IFERROR(MEDIAN(C13:L13),0) -> 0.22497602
B14: EBT Margin | C14: =IFERROR('Historical FS'!C28,0) -> 0.25015615 | D14: =IFERROR('Historical FS'!D28,0) -> 0.24678757 | E14: =IFERROR('Historical FS'!E28,0) -> 0.24047815 | F14: =IFERROR('Historical FS'!F28,0) -> 0.21964318 | G14: =IFERROR('Historical FS'!G28,0) -> 0.21151876 | H14: =IFERROR('Historical FS'!H28,0) -> 0.24312246 | I14: =IFERROR('Historical FS'!I28,0) -> 0.22866468 | J14: =IFERROR('Historical FS'!J28,0) -> 0.20863682 | ... L14: =IFERROR('Historical FS'!L28,0) -> 0.20865084 | N14: =IFERROR(AVERAGE(C14:L14),0) -> 0.22611922 | O14: =IFERROR(MEDIAN(C14:L14),0) -> 0.22415393
B15: Net profit Margin | C15: =IFERROR('Historical FS'!C34,0) -> 0.16606076 | D15: =IFERROR('Historical FS'!D34,0) -> 0.16504585 | E15: =IFERROR('Historical FS'!E34,0) -> 0.18034089 | F15: =IFERROR('Historical FS'!F34,0) -> 0.15153311 | G15: =IFERROR('Historical FS'!G34,0) -> 0.15239396 | H15: =IFERROR('Historical FS'!H34,0) -> 0.17141094 | I15: =IFERROR('Historical FS'!I34,0) -> 0.16319333 | J15: =IFERROR('Historical FS'!J34,0) -> 0.14585704 | ... L15: =IFERROR('Historical FS'!L34,0) -> 0.14203325 | N15: =IFERROR(AVERAGE(C15:L15),0) -> 0.15780201 | O15: =IFERROR(MEDIAN(C15:L15),0) -> 0.15779365
B17: SalesExpenses%Sales | C17: =IFERROR('Historical FS'!C16,0) -> 0.077993626 | D17: =IFERROR('Historical FS'!D16,0) -> 0.076966883 | E17: =IFERROR('Historical FS'!E16,0) -> 0.075224753 | F17: =IFERROR('Historical FS'!F16,0) -> 0.085382522 | G17: =IFERROR('Historical FS'!G16,0) -> 0.069544338 | H17: =IFERROR('Historical FS'!H16,0) -> 0.040737718 | I17: =IFERROR('Historical FS'!I16,0) -> 0.043825684 | J17: =IFERROR('Historical FS'!J16,0) -> 0.04603896 | ... L17: =IFERROR('Historical FS'!L16,0) -> 0.043984294 | N17: =IFERROR(AVERAGE(C17:L17),0) -> 0.060665004 | O17: =IFERROR(MEDIAN(C17:L17),0) -> 0.058247799
B18: Depreciation%Sales | C18: =IFERROR('Historical FS'!C25,0) -> 0.023366058 | D18: =IFERROR('Historical FS'!D25,0) -> 0.024867122 | E18: =IFERROR('Historical FS'!E25,0) -> 0.026417288 | F18: =IFERROR('Historical FS'!F25,0) -> 0.024324161 | G18: =IFERROR('Historical FS'!G25,0) -> 0.031864392 | H18: =IFERROR('Historical FS'!H25,0) -> 0.032516522 | I18: =IFERROR('Historical FS'!I25,0) -> 0.028575891 | J18: =IFERROR('Historical FS'!J25,0) -> 0.028787125 | ... L18: =IFERROR('Historical FS'!L25,0) -> 0.029523284 | N18: =IFERROR(AVERAGE(C18:L18),0) -> 0.02806837 | O18: =IFERROR(MEDIAN(C18:L18),0) -> 0.028681508
B19: OperatingIncome%Sales | C19: =IFERROR('Ratio Analysis'!C13,0) -> 0.25015615 | D19: =IFERROR('Ratio Analysis'!D13,0) -> 0.24678757 | E19: =IFERROR('Ratio Analysis'!E13,0) -> 0.24047815 | F19: =IFERROR('Ratio Analysis'!F13,0) -> 0.21964318 | G19: =IFERROR('Ratio Analysis'!G13,0) -> 0.2133912 | H19: =IFERROR('Ratio Analysis'!H13,0) -> 0.2450633 | I19: =IFERROR('Ratio Analysis'!I13,0) -> 0.23030886 | J19: =IFERROR('Ratio Analysis'!J13,0) -> 0.21057186 | ... L19: =IFERROR('Ratio Analysis'!L13,0) -> 0.21120314 | N19: =IFERROR(AVERAGE(C19:L19),0) -> 0.22741955 | O19: =IFERROR(MEDIAN(C19:L19),0) -> 0.22497602
B21: Return on Capital Employed | C21: =IFERROR(('Historical FS'!C18-'Historical FS'!C24)/SUM('Historical FS'!C47:C49),0) -> 0.25298005 | D21: =IFERROR(('Historical FS'!D18-'Historical FS'!D24)/SUM('Historical FS'!D47:D49),0) -> 0.24500594 | E21: =IFERROR(('Historical FS'!E18-'Historical FS'!E24)/SUM('Historical FS'!E47:E49),0) -> 0.26121713 | F21: =IFERROR(('Historical FS'!F18-'Historical FS'!F24)/SUM('Historical FS'!F47:F49),0) -> 0.27959291 | G21: =IFERROR(('Historical FS'!G18-'Historical FS'!G24)/SUM('Historical FS'!G47:G49),0) -> 0.27644365 | H21: =IFERROR(('Historical FS'!H18-'Historical FS'!H24)/SUM('Historical FS'!H47:H49),0) -> 0.30145943 | I21: =IFERROR(('Historical FS'!I18-'Historical FS'!I24)/SUM('Historical FS'!I47:I49),0) -> 0.34661734 | J21: =IFERROR(('Historical FS'!J18-'Historical FS'!J24)/SUM('Historical FS'!J47:J49),0) -> 0.3692089 | ... L21: =IFERROR(('Historical FS'!L18-'Historical FS'!L24)/SUM('Historical FS'!L47:L49),0) -> 0.33085684 | N21: =IFERROR(AVERAGE(C21:L21),0) -> 0.29924519 | O21: =IFERROR(MEDIAN(C21:L21),0) -> 0.29052617
B22: Retain Earnings% | C22: =IFERROR('Historical FS'!C44,0) -> 0 | D22: =IFERROR('Historical FS'!D44,0) -> 0 | E22: =IFERROR('Historical FS'!E44,0) -> 0 | F22: =IFERROR('Historical FS'!F44,0) -> 0 | G22: =IFERROR('Historical FS'!G44,0) -> 0 | H22: =IFERROR('Historical FS'!H44,0) -> 0 | I22: =IFERROR('Historical FS'!I44,0) -> 0 | J22: =IFERROR('Historical FS'!J44,0) -> 0 | ... L22: =IFERROR('Historical FS'!L44,0) -> 0 | N22: =IFERROR(AVERAGE(C22:L22),0) -> 0 | O22: =IFERROR(MEDIAN(C22:L22),0) -> 0
B23: Return on Equity% | C23: =IFERROR('Historical FS'!C33/SUM('Historical FS'!C47:C48),0) -> 0.16793535 | D23: =IFERROR('Historical FS'!D33/SUM('Historical FS'!D47:D48),0) -> 0.16385434 | E23: =IFERROR('Historical FS'!E33/SUM('Historical FS'!E47:E48),0) -> 0.1958936 | F23: =IFERROR('Historical FS'!F33/SUM('Historical FS'!F47:F48),0) -> 0.19289278 | G23: =IFERROR('Historical FS'!G33/SUM('Historical FS'!G47:G48),0) -> 0.21139801 | H23: =IFERROR('Historical FS'!H33/SUM('Historical FS'!H47:H48),0) -> 0.22556352 | I23: =IFERROR('Historical FS'!I33/SUM('Historical FS'!I47:I48),0) -> 0.26345056 | J23: =IFERROR('Historical FS'!J33/SUM('Historical FS'!J47:J48),0) -> 0.28388611 | ... L23: =IFERROR('Historical FS'!L33/SUM('Historical FS'!L47:L48),0) -> 0.24160387 | N23: =IFERROR(AVERAGE(C23:L23),0) -> 0.21908946 | O23: =IFERROR(MEDIAN(C23:L23),0) -> 0.21848076
B24: Self Sustained Growth Rate | C24: =IFERROR(C22*C23,0) -> 0 | D24: =IFERROR(D22*D23,0) -> 0 | E24: =IFERROR(E22*E23,0) -> 0 | F24: =IFERROR(F22*F23,0) -> 0 | G24: =IFERROR(G22*G23,0) -> 0 | H24: =IFERROR(H22*H23,0) -> 0 | I24: =IFERROR(I22*I23,0) -> 0 | J24: =IFERROR(J22*J23,0) -> 0 | ... L24: =IFERROR(L22*L23,0) -> 0 | N24: =IFERROR(AVERAGE(C24:L24),0) -> 0 | O24: =IFERROR(MEDIAN(C24:L24),0) -> 0
B25: Interest Coverage Ratio | C25: =IFERROR(('Historical FS'!C18-'Historical FS'!C24)/'Historical FS'!C21,0) -> 0 | D25: =IFERROR(('Historical FS'!D18-'Historical FS'!D24)/'Historical FS'!D21,0) -> 0 | E25: =IFERROR(('Historical FS'!E18-'Historical FS'!E24)/'Historical FS'!E21,0) -> 0 | F25: =IFERROR(('Historical FS'!F18-'Historical FS'!F24)/'Historical FS'!F21,0) -> 0 | G25: =IFERROR(('Historical FS'!G18-'Historical FS'!G24)/'Historical FS'!G21,0) -> 113.96471 | H25: =IFERROR(('Historical FS'!H18-'Historical FS'!H24)/'Historical FS'!H21,0) -> 126.26667 | I25: =IFERROR(('Historical FS'!I18-'Historical FS'!I24)/'Historical FS'!I21,0) -> 140.075 | J25: =IFERROR(('Historical FS'!J18-'Historical FS'!J24)/'Historical FS'!J21,0) -> 108.82042 | ... L25: =IFERROR(('Historical FS'!L18-'Historical FS'!L24)/'Historical FS'!L21,0) -> 82.75 | N25: =IFERROR(AVERAGE(C25:L25),0) -> 63.94236 | O25: =IFERROR(MEDIAN(C25:L25),0) -> 75.148404
B27: Debtor Turnover Ratio | C27: =IFERROR('Historical FS'!C6/'Historical FS'!C59,0) -> 5.5111209 | D27: =IFERROR('Historical FS'!D6/'Historical FS'!D59,0) -> 5.557864 | E27: =IFERROR('Historical FS'!E6/'Historical FS'!E59,0) -> 5.3661543 | F27: =IFERROR('Historical FS'!F6/'Historical FS'!F59,0) -> 5.5759763 | G27: =IFERROR('Historical FS'!G6/'Historical FS'!G59,0) -> 4.9110726 | H27: =IFERROR('Historical FS'!H6/'Historical FS'!H59,0) -> 5.207422 | I27: =IFERROR('Historical FS'!I6/'Historical FS'!I59,0) -> 5.3591065 | J27: =IFERROR('Historical FS'!J6/'Historical FS'!J59,0) -> 5.7727738 | ... L27: =IFERROR('Historical FS'!L6/'Historical FS'!L59,0) -> 5.2310803 | N27: =IFERROR(AVERAGE(C27:L27),0) -> 5.3582161 | O27: =IFERROR(MEDIAN(C27:L27),0) -> 5.3626304
B28: Creditor Turnover Ratio | C28: =IFERROR('Historical FS'!C6/'Historical FS'!C50,0) -> 4.6758275 | D28: =IFERROR('Historical FS'!D6/'Historical FS'!D50,0) -> 4.8343922 | E28: =IFERROR('Historical FS'!E6/'Historical FS'!E50,0) -> 4.8885346 | F28: =IFERROR('Historical FS'!F6/'Historical FS'!F50,0) -> 4.3244586 | G28: =IFERROR('Historical FS'!G6/'Historical FS'!G50,0) -> 4.1806419 | H28: =IFERROR('Historical FS'!H6/'Historical FS'!H50,0) -> 3.8889878 | I28: =IFERROR('Historical FS'!I6/'Historical FS'!I50,0) -> 3.3878568 | J28: =IFERROR('Historical FS'!J6/'Historical FS'!J50,0) -> 3.5893128 | ... L28: =IFERROR('Historical FS'!L6/'Historical FS'!L50,0) -> 3.7254857 | N28: =IFERROR(AVERAGE(C28:L28),0) -> 4.1254089 | O28: =IFERROR(MEDIAN(C28:L28),0) -> 4.0348149
B29: Inventory Turnover | C29: =IFERROR('Historical FS'!C6/'Historical FS'!C60,0) -> 0 | D29: =IFERROR('Historical FS'!D6/'Historical FS'!D60,0) -> 0 | E29: =IFERROR('Historical FS'!E6/'Historical FS'!E60,0) -> 0 | F29: =IFERROR('Historical FS'!F6/'Historical FS'!F60,0) -> 0 | G29: =IFERROR('Historical FS'!G6/'Historical FS'!G60,0) -> 0 | H29: =IFERROR('Historical FS'!H6/'Historical FS'!H60,0) -> 0 | I29: =IFERROR('Historical FS'!I6/'Historical FS'!I60,0) -> 0 | J29: =IFERROR('Historical FS'!J6/'Historical FS'!J60,0) -> 0 | ... L29: =IFERROR('Historical FS'!L6/'Historical FS'!L60,0) -> 0 | N29: =IFERROR(AVERAGE(C29:L29),0) -> 0 | O29: =IFERROR(MEDIAN(C29:L29),0) -> 0
B30: Fixed Asset Turnover | C30: =IFERROR('Historical FS'!C6/'Historical FS'!C53,0) -> 4.6646496 | D30: =IFERROR('Historical FS'!D6/'Historical FS'!D53,0) -> 4.8299598 | E30: =IFERROR('Historical FS'!E6/'Historical FS'!E53,0) -> 5.6085573 | F30: =IFERROR('Historical FS'!F6/'Historical FS'!F53,0) -> 5.2625716 | G30: =IFERROR('Historical FS'!G6/'Historical FS'!G53,0) -> 3.8165118 | H30: =IFERROR('Historical FS'!H6/'Historical FS'!H53,0) -> 3.939306 | I30: =IFERROR('Historical FS'!I6/'Historical FS'!I53,0) -> 4.7147674 | J30: =IFERROR('Historical FS'!J6/'Historical FS'!J53,0) -> 5.0219675 | ... L30: =IFERROR('Historical FS'!L6/'Historical FS'!L53,0) -> 5.2643648 | N30: =IFERROR(AVERAGE(C30:L30),0) -> 4.8685975 | O30: =IFERROR(MEDIAN(C30:L30),0) -> 4.9259636
B31: Capital Turnover Ratio | C31: =IFERROR('Historical FS'!C6/SUM('Historical FS'!C47:C48),0) -> 1.0112885 | D31: =IFERROR('Historical FS'!D6/SUM('Historical FS'!D47:D48),0) -> 0.99278073 | E31: =IFERROR('Historical FS'!E6/SUM('Historical FS'!E47:E48),0) -> 1.0862406 | F31: =IFERROR('Historical FS'!F6/SUM('Historical FS'!F47:F48),0) -> 1.2729414 | G31: =IFERROR('Historical FS'!G6/SUM('Historical FS'!G47:G48),0) -> 1.3871811 | H31: =IFERROR('Historical FS'!H6/SUM('Historical FS'!H47:H48),0) -> 1.3159225 | I31: =IFERROR('Historical FS'!I6/SUM('Historical FS'!I47:I48),0) -> 1.6143464 | J31: =IFERROR('Historical FS'!J6/SUM('Historical FS'!J47:J48),0) -> 1.9463312 | ... L31: =IFERROR('Historical FS'!L6/SUM('Historical FS'!L47:L48),0) -> 1.7010374 | N31: =IFERROR(AVERAGE(C31:L31),0) -> 1.4072021 | O31: =IFERROR(MEDIAN(C31:L31),0) -> 1.3515518
B34: Debtor Days | C34: =IFERROR(365/C27,0) -> 66.229721 | D34: =IFERROR(365/D27,0) -> 65.672712 | E34: =IFERROR(365/E27,0) -> 68.018916 | F34: =IFERROR(365/F27,0) -> 65.459389 | G34: =IFERROR(365/G27,0) -> 74.321849 | H34: =IFERROR(365/H27,0) -> 70.092265 | I34: =IFERROR(365/I27,0) -> 68.108368 | J34: =IFERROR(365/J27,0) -> 63.227837 | ... L34: =IFERROR(365/L27,0) -> 69.775262 | N34: =IFERROR(AVERAGE(C34:L34),0) -> 68.262133 | O34: =IFERROR(MEDIAN(C34:L34),0) -> 68.063642
B35: Payable Days | C35: =IFERROR(365/C28,0) -> 78.06105 | D35: =IFERROR(365/D28,0) -> 75.500701 | E35: =IFERROR(365/E28,0) -> 74.664502 | F35: =IFERROR(365/F28,0) -> 84.403629 | G35: =IFERROR(365/G28,0) -> 87.307167 | H35: =IFERROR(365/H28,0) -> 93.854756 | I35: =IFERROR(365/I28,0) -> 107.73773 | J35: =IFERROR(365/J28,0) -> 101.69078 | ... L35: =IFERROR(365/L28,0) -> 97.973802 | N35: =IFERROR(AVERAGE(C35:L35),0) -> 89.830496 | O35: =IFERROR(MEDIAN(C35:L35),0) -> 90.580961
B36: Inventory Days | C36: =IFERROR(365/C29,0) -> 0 | D36: =IFERROR(365/D29,0) -> 0 | E36: =IFERROR(365/E29,0) -> 0 | F36: =IFERROR(365/F29,0) -> 0 | G36: =IFERROR(365/G29,0) -> 0 | H36: =IFERROR(365/H29,0) -> 0 | I36: =IFERROR(365/I29,0) -> 0 | J36: =IFERROR(365/J29,0) -> 0 | ... L36: =IFERROR(365/L29,0) -> 0 | N36: =IFERROR(AVERAGE(C36:L36),0) -> 0 | O36: =IFERROR(MEDIAN(C36:L36),0) -> 0
B37: Cash Conversion Cycle (in Days) | C37: =IFERROR(SUM(C34+C36)-C35,0) -> -11.831329 | D37: =IFERROR(SUM(D34+D36)-D35,0) -> -9.827989 | E37: =IFERROR(SUM(E34+E36)-E35,0) -> -6.6455858 | F37: =IFERROR(SUM(F34+F36)-F35,0) -> -18.944239 | G37: =IFERROR(SUM(G34+G36)-G35,0) -> -12.985318 | H37: =IFERROR(SUM(H34+H36)-H35,0) -> -23.762491 | I37: =IFERROR(SUM(I34+I36)-I35,0) -> -39.62936 | J37: =IFERROR(SUM(J34+J36)-J35,0) -> -38.462938 | ... L37: =IFERROR(SUM(L34+L36)-L35,0) -> -28.19854 | N37: =IFERROR(AVERAGE(C37:L37),0) -> -21.568364 | O37: =IFERROR(MEDIAN(C37:L37),0) -> -21.353365
B39: CFO/ Sales | C39: =IFERROR('Historical FS'!C80/'Historical FS'!C6,0) -> 0.12943419 | D39: =IFERROR('Historical FS'!D80/'Historical FS'!D6,0) -> 0.13689329 | E39: =IFERROR('Historical FS'!E80/'Historical FS'!E6,0) -> 0.18862199 | F39: =IFERROR('Historical FS'!F80/'Historical FS'!F6,0) -> 0.17403084 | G39: =IFERROR('Historical FS'!G80/'Historical FS'!G6,0) -> 0.16120541 | H39: =IFERROR('Historical FS'!H80/'Historical FS'!H6,0) -> 0.2387929 | I39: =IFERROR('Historical FS'!I80/'Historical FS'!I6,0) -> 0.18464991 | J39: =IFERROR('Historical FS'!J80/'Historical FS'!J6,0) -> 0.1098544 | ... L39: =IFERROR('Historical FS'!L80/'Historical FS'!L6,0) -> 0.2171851 | N39: =IFERROR(AVERAGE(C39:L39),0) -> 0.167165 | O39: =IFERROR(MEDIAN(C39:L39),0) -> 0.16761812
B40: CFO/Total Assets | C40: =IFERROR('Historical FS'!C80/'Historical FS'!C64,0) -> 0.10761938 | D40: =IFERROR('Historical FS'!D80/'Historical FS'!D64,0) -> 0.11275076 | E40: =IFERROR('Historical FS'!E80/'Historical FS'!E64,0) -> 0.16763916 | F40: =IFERROR('Historical FS'!F80/'Historical FS'!F64,0) -> 0.17115124 | G40: =IFERROR('Historical FS'!G80/'Historical FS'!G64,0) -> 0.15943355 | H40: =IFERROR('Historical FS'!H80/'Historical FS'!H64,0) -> 0.22315856 | I40: =IFERROR('Historical FS'!I80/'Historical FS'!I64,0) -> 0.19242005 | J40: =IFERROR('Historical FS'!J80/'Historical FS'!J64,0) -> 0.12940223 | ... L40: =IFERROR('Historical FS'!L80/'Historical FS'!L64,0) -> 0.23951419 | N40: =IFERROR(AVERAGE(C40:L40),0) -> 0.16496238 | O40: =IFERROR(MEDIAN(C40:L40),0) -> 0.16353636
B41: CFO/Total Debt | C41: =IFERROR('Historical FS'!C80/'Historical FS'!C49,0) -> 0 | D41: =IFERROR('Historical FS'!D80/'Historical FS'!D49,0) -> 0 | E41: =IFERROR('Historical FS'!E80/'Historical FS'!E49,0) -> 0 | F41: =IFERROR('Historical FS'!F80/'Historical FS'!F49,0) -> 0 | G41: =IFERROR('Historical FS'!G80/'Historical FS'!G49,0) -> 3.1590762 | H41: =IFERROR('Historical FS'!H80/'Historical FS'!H49,0) -> 4.5055399 | I41: =IFERROR('Historical FS'!I80/'Historical FS'!I49,0) -> 4.1032152 | J41: =IFERROR('Historical FS'!J80/'Historical FS'!J49,0) -> 1.9427642 | ... L41: =IFERROR('Historical FS'!L80/'Historical FS'!L49,0) -> 4.3027835 | N41: =IFERROR(AVERAGE(C41:L41),0) -> 2.0421323 | O41: =IFERROR(MEDIAN(C41:L41),0) -> 2.1753539

Sheet Forecasting
B2: ='Data Sheet'!$B$1&" - "&'Data Sheet'!A17&" Forecasting" -> INFOSYS LTD - Sales Forecasting | G2: ='Data Sheet'!$B$1&" - "&'Data Sheet'!A30&" Forecasting" -> INFOSYS LTD - Net profit Forecasting | L2: ='Data Sheet'!$B$1&" - "&'Historical FS'!B38&" Forecasting" -> INFOSYS LTD - Earning per Share Forecasting | Q2: ='Data Sheet'!$B$1&" - "&'Historical FS'!B18&" Forecasting" -> INFOSYS LTD - EBITDA Forecasting
B3: Year Weight | C3: Year | D3: Sales | E3: Sales Growth | G3: Year Weight | H3: Year | I3: Net Profit | J3: Net Profit Growth | L3: Year Weight | M3: Year | N3: Earning per Share | O3: Earning per Share Growth | Q3: Year Weight | R3: Year | S3: EBITDA | T3: EBITDA Growth
B4: 1 | C4: ='Data Sheet'!$B$16 -> 42460 | D4: {=TRANSPOSE('Data Sheet'!B17:K17)} -> 62441 | G4: 1 | H4: ='Data Sheet'!$B$16 -> 42460 | I4: {=TRANSPOSE('Data Sheet'!B30:K30)} -> 13489 | L4: 1 | M4: ='Data Sheet'!$B$16 -> 42460 | N4: {=TRANSPOSE('Historical FS'!C38:L38)} -> 0.044304176 | Q4: 1 | R4: ='Data Sheet'!$B$16 -> 42460 | S4: {=TRANSPOSE('Historical FS'!C18:L18)} -> 17079
B5: =B4+1 -> 2 | C5: =C4+365 -> 42825 | D5: 68484 | E5: =D5/D4-1 -> 0.09677936 | G5: =G4+1 -> 2 | H5: =H4+365 -> 42825 | I5: 14353 | J5: =I5/I4-1 -> 0.064052191 | L5: =L4+1 -> 2 | M5: =M4+365 -> 42825 | N5: 0.040643192 | O5: =N5/N4-1 -> -0.082632929 | Q5: =Q4+1 -> 2 | R5: =R4+365 -> 42825 | S5: 18604 | T5: =S5/S4-1 -> 0.089290942
B6: =B5+1 -> 3 | C6: =C5+365 -> 43190 | D6: 70522 | E6: =D6/D5-1 -> 0.029758776 | G6: =G5+1 -> 3 | H6: =H5+365 -> 43190 | I6: 16029 | J6: =I6/I5-1 -> 0.11677001 | L6: =L5+1 -> 3 | M6: =M5+365 -> 43190 | N6: 0.034346595 | O6: =N6/N5-1 -> -0.15492377 | Q6: =Q5+1 -> 3 | R6: =R5+365 -> 43190 | S6: 18822 | T6: =S6/S5-1 -> 0.01171791
B7: =B6+1 -> 4 | C7: =C6+365 -> 43555 | D7: 82675 | E7: =D7/D6-1 -> 0.1723292 | G7: =G6+1 -> 4 | H7: =H6+365 -> 43555 | I7: 15404 | J7: =I7/I6-1 -> -0.038991827 | L7: =L6+1 -> 4 | M7: =M6+365 -> 43555 | N7: 0.034873084 | O7: =N7/N6-1 -> 0.015328708 | Q7: =Q6+1 -> 4 | R7: =R6+365 -> 43555 | S7: 20170 | T7: =S7/S6-1 -> 0.071618319
B8: =B7+1 -> 5 | C8: =C7+365 -> 43920 | D8: 90791 | E8: =D8/D7-1 -> 0.098167523 | G8: =G7+1 -> 5 | H8: =H7+365 -> 43920 | I8: 16594 | J8: =I8/I7-1 -> 0.077252662 | L8: =L7+1 -> 5 | M8: =M7+365 -> 43920 | N8: 0.030782018 | O8: =N8/N7-1 -> -0.11731301 | Q8: =Q7+1 -> 5 | R8: =R7+365 -> 43920 | S8: 22267 | T8: =S8/S7-1 -> 0.10396629
B9: =B8+1 -> 6 | C9: =C8+365 -> 44285 | D9: 100472 | E9: =D9/D8-1 -> 0.10662951 | G9: =G8+1 -> 6 | H9: =H8+365 -> 44285 | I9: 19351 | J9: =I9/I8-1 -> 0.16614439 | L9: =L8+1 -> 6 | M9: =M8+365 -> 44285 | N9: 0.024739868 | O9: =N9/N8-1 -> -0.19628831 | Q9: =Q8+1 -> 6 | R9: =R8+365 -> 44285 | S9: 27889 | T9: =S9/S8-1 -> 0.25248125
B10: =B9+1 -> 7 | C10: =C9+365 -> 44650 | D10: 121641 | E10: =D10/D9-1 -> 0.21069552 | G10: =G9+1 -> 7 | H10: =H9+365 -> 44650 | I10: 22110 | J10: =I10/I9-1 -> 0.14257661 | L10: =L9+1 -> 7 | M10: =M9+365 -> 44650 | N10: 0.021191376 | O10: =N10/N9-1 -> -0.14343213 | Q10: =Q9+1 -> 7 | R10: =R9+365 -> 44650 | S10: 31491 | T10: =S10/S9-1 -> 0.12915486
B11: =B10+1 -> 8 | C11: =C10+365 -> 45015 | D11: 146767 | E11: =D11/D10-1 -> 0.20655864 | G11: =G10+1 -> 8 | H11: =H10+365 -> 45015 | I11: 24095 | J11: =I11/I10-1 -> 0.089778381 | L11: =L10+1 -> 8 | M11: =M10+365 -> 45015 | N11: 0.019379642 | O11: =N11/N10-1 -> -0.08549391 | Q11: =Q10+1 -> 8 | R11: =R10+365 -> 45015 | S11: 35130 | T11: =S11/S10-1 -> 0.11555683
B12: =B11+1 -> 9 | C12: =C11+365 -> 45380 | D12: 153670 | E12: =D12/D11-1 -> 0.047033734 | G12: =G11+1 -> 9 | H12: =H11+365 -> 45380 | I12: 26233 | J12: =I12/I11-1 -> 0.088732102 | L12: =L11+1 -> 9 | M12: =M11+365 -> 45380 | N12: 0.019273344 | O12: =N12/N11-1 -> -0.0054850664 | Q12: =Q11+1 -> 9 | R12: =R11+365 -> 45380 | S12: 36425 | T12: =S12/S11-1 -> 0.03686308
B13: =B12+1 -> 10 | C13: =C12+365 -> 45745 | D13: 162990 | E13: =D13/D12-1 -> 0.060649444 | G13: =G12+1 -> 10 | H13: =H12+365 -> 45745 | I13: 26713 | J13: =I13/I12-1 -> 0.018297564 | L13: =L12+1 -> 10 | M13: =M12+365 -> 45745 | N13: 0.017940821 | O13: =N13/N12-1 -> -0.069138124 | Q13: =Q12+1 -> 10 | R13: =R12+365 -> 45745 | S13: 39236 | T13: =S13/S12-1 -> 0.077172272
B14: =B13+1 -> 11 | C14: =C13+365 -> 46110 | D14: =FORECAST(B14,$D$4:$D$13,$B$4:$B$13) -> 173013.53 | E14: =D14/D13-1 -> 0.061497842 | G14: =G13+1 -> 11 | H14: =H13+365 -> 46110 | I14: =FORECAST(G14,$I$4:$I$13,$G$4:$G$13) -> 28283.133 | J14: =I14/I13-1 -> 0.058777873 | L14: =L13+1 -> 11 | M14: =M13+365 -> 46110 | N14: =FORECAST(L14,$N$4:$N$13,$L$4:$L$13) -> 0.011788039 | O14: =N14/N13-1 -> -0.34294874 | Q14: =Q13+1 -> 11 | R14: =R13+365 -> 46110 | S14: =FORECAST(Q14,$S$4:$S$13,$Q$4:$Q$13) -> 41554.133 | T14: =S14/S13-1 -> 0.059081796
B15: =B14+1 -> 12 | C15: =C14+365 -> 46475 | D15: =FORECAST(B15,$D$4:$D$13,$B$4:$B$13) -> 185189.58 | E15: =D15/D14-1 -> 0.070376243 | G15: =G14+1 -> 12 | H15: =H14+365 -> 46475 | I15: =FORECAST(G15,$I$4:$I$13,$G$4:$G$13) -> 29891.503 | J15: =I15/I14-1 -> 0.056866744 | L15: =L14+1 -> 12 | M15: =M14+365 -> 46475 | N15: =FORECAST(L15,$N$4:$N$13,$L$4:$L$13) -> 0.0087045166 | O15: =N15/N14-1 -> -0.2615806 | Q15: =Q14+1 -> 12 | R15: =R14+365 -> 46475 | S15: =FORECAST(Q15,$S$4:$S$13,$Q$4:$Q$13) -> 44252.83 | T15: =S15/S14-1 -> 0.064944128
B16: =B15+1 -> 13 | C16: =C15+365 -> 46840 | D16: =FORECAST(B16,$D$4:$D$13,$B$4:$B$13) -> 197365.62 | E16: =D16/D15-1 -> 0.06574907 | G16: =G15+1 -> 13 | H16: =H15+365 -> 46840 | I16: =FORECAST(G16,$I$4:$I$13,$G$4:$G$13) -> 31499.873 | J16: =I16/I15-1 -> 0.053806919 | L16: =L15+1 -> 13 | M16: =M15+365 -> 46840 | N16: =FORECAST(L16,$N$4:$N$13,$L$4:$L$13) -> 0.0056209943 | O16: =N16/N15-1 -> -0.35424394 | Q16: =Q15+1 -> 13 | R16: =R15+365 -> 46840 | S16: =FORECAST(Q16,$S$4:$S$13,$Q$4:$Q$13) -> 46951.527 | T16: =S16/S15-1 -> 0.060983602
B17: =B16+1 -> 14 | C17: =C16+365 -> 47205 | D17: =FORECAST(B17,$D$4:$D$13,$B$4:$B$13) -> 209541.66 | E17: =D17/D16-1 -> 0.061692824 | G17: =G16+1 -> 14 | H17: =H16+365 -> 47205 | I17: =FORECAST(G17,$I$4:$I$13,$G$4:$G$13) -> 33108.242 | J17: =I17/I16-1 -> 0.051059562 | L17: =L16+1 -> 14 | M17: =M16+365 -> 47205 | N17: =FORECAST(L17,$N$4:$N$13,$L$4:$L$13) -> 0.0025374721 | O17: =N17/N16-1 -> -0.54857239 | Q17: =Q16+1 -> 14 | R17: =R16+365 -> 47205 | S17: =FORECAST(Q17,$S$4:$S$13,$Q$4:$Q$13) -> 49650.224 | T17: =S17/S16-1 -> 0.057478364
B18: =B17+1 -> 15 | C18: =C17+365 -> 47570 | D18: =FORECAST(B18,$D$4:$D$13,$B$4:$B$13) -> 221717.7 | E18: =D18/D17-1 -> 0.058107979 | G18: =G17+1 -> 15 | H18: =H17+365 -> 47570 | I18: =FORECAST(G18,$I$4:$I$13,$G$4:$G$13) -> 34716.612 | J18: =I18/I17-1 -> 0.048579133 | L18: =L17+1 -> 15 | M18: =M17+365 -> 47570 | N18: =FORECAST(L18,$N$4:$N$13,$L$4:$L$13) -> -0.00054605024 | O18: =N18/N17-1 -> -1.2151946 | Q18: =Q17+1 -> 15 | R18: =R17+365 -> 47570 | S18: =FORECAST(Q18,$S$4:$S$13,$Q$4:$Q$13) -> 52348.921 | T18: =S18/S17-1 -> 0.054354175

Sheet Intrinsic Growth
A2: # | B2: Calculating of ROIC | D2: ='[1]Raw FS'!J2 -> 44256 | E2: ='[1]Raw FS'!K2 -> 44621 | F2: ='[1]Raw FS'!L2 -> 44986 | G2: ='[1]Raw FS'!M2 -> 45352 | H2: ='[1]Raw FS'!N2 -> 45717
B4: Current Assets
B5: ='Raw FS'!B34 -> Trade receivables | D5: ='Raw FS'!J34 -> 19294 | E5: ='Raw FS'!K34 -> 22698 | F5: ='Raw FS'!L34 -> 25424 | G5: ='Raw FS'!M34 -> 30193 | H5: ='Raw FS'!N34 -> 31158
B6: ='Raw FS'!B36 -> Loans n Advances | D6: ='Raw FS'!J36 -> 1460 | E6: ='Raw FS'!K36 -> 2491 | F6: ='Raw FS'!L36 -> 3242 | G6: ='Raw FS'!M36 -> 10330 | H6: ='Raw FS'!N36 -> 6717
B7: ='Raw FS'!B37 -> Other asset items | D7: ='Raw FS'!J37 -> 21411 | E7: ='Raw FS'!K37 -> 27528 | F7: ='Raw FS'!L37 -> 34766 | G7: ='Raw FS'!M37 -> 29513 | H7: ='Raw FS'!N37 -> 30149
B8: Total Current Assets | D8: =SUM(D5:D7) -> 42165 | E8: =SUM(E5:E7) -> 52717 | F8: =SUM(F5:F7) -> 63432 | G8: =SUM(G5:G7) -> 70036 | H8: =SUM(H5:H7) -> 68024
B10: Current Liabilities
B11: ='Raw FS'!B10 -> Trade Payables | D11: ='Raw FS'!J10 -> 2645 | E11: ='Raw FS'!K10 -> 4134 | F11: ='Raw FS'!L10 -> 3865 | G11: ='Raw FS'!M10 -> 3956 | H11: ='Raw FS'!N10 -> 4164
B12: ='Raw FS'!B11 -> Advance from Customers | D12: ='Raw FS'!J11 -> 0 | E12: ='Raw FS'!K11 -> 0 | F12: ='Raw FS'!L11 -> 0 | G12: ='Raw FS'!M11 -> 0 | H12: ='Raw FS'!N11 -> 0
B13: ='Raw FS'!B12 -> Other liability items | D13: ='Raw FS'!J12 -> 22759 | E13: ='Raw FS'!K12 -> 31385 | F13: ='Raw FS'!L12 -> 36637 | G13: ='Raw FS'!M12 -> 36584 | H13: ='Raw FS'!N12 -> 39201
B14: Total Current Assets | D14: =SUM(D11:D13) -> 25404 | E14: =SUM(E11:E13) -> 35519 | F14: =SUM(F11:F13) -> 40502 | G14: =SUM(G11:G13) -> 40540 | H14: =SUM(H11:H13) -> 43365
A16: # | B16: Net Working Capital | D16: =D8-D14 -> 16761 | E16: =E8-E14 -> 17198 | F16: =F8-F14 -> 22930 | G16: =G8-G14 -> 29496 | H16: =H8-H14 -> 24659
B18: Non Current Assets
B19: ='Raw FS'!B16 -> Land | D19: ='Raw FS'!J16 -> 2036 | E19: ='Raw FS'!K16 -> 2065 | F19: ='Raw FS'!L16 -> 2054 | G19: ='Raw FS'!M16 -> 2037 | H19: ='Raw FS'!N16 -> 2079
B20: ='Raw FS'!B17 -> Building | D20: ='Raw FS'!J17 -> 16328 | E20: ='Raw FS'!K17 -> 16761 | F20: ='Raw FS'!L17 -> 16903 | G20: ='Raw FS'!M17 -> 16515 | H20: ='Raw FS'!N17 -> 16376
B21: ='Raw FS'!B18 -> Plant Machinery | D21: ='Raw FS'!J18 -> 3296 | E21: ='Raw FS'!K18 -> 3210 | F21: ='Raw FS'!L18 -> 3302 | G21: ='Raw FS'!M18 -> 3428 | H21: ='Raw FS'!N18 -> 3461
B22: ='Raw FS'!B19 -> Equipments | D22: ='Raw FS'!J19 -> 1371 | E22: ='Raw FS'!K19 -> 1427 | F22: ='Raw FS'!L19 -> 1482 | G22: ='Raw FS'!M19 -> 1528 | H22: ='Raw FS'!N19 -> 1628
B23: ='Raw FS'!B20 -> Computers | D23: ='Raw FS'!J20 -> 8650 | E23: ='Raw FS'!K20 -> 9936 | F23: ='Raw FS'!L20 -> 11898 | G23: ='Raw FS'!M20 -> 12353 | H23: ='Raw FS'!N20 -> 12925
B24: ='Raw FS'!B21 -> Furniture n fittings | D24: ='Raw FS'!J21 -> 2149 | E24: ='Raw FS'!K21 -> 2279 | F24: ='Raw FS'!L21 -> 2303 | G24: ='Raw FS'!M21 -> 2326 | H24: ='Raw FS'!N21 -> 2340
B25: ='Raw FS'!B22 -> Vehicles | D25: ='Raw FS'!J22 -> 74 | E25: ='Raw FS'!K22 -> 71 | F25: ='Raw FS'!L22 -> 60 | G25: ='Raw FS'!M22 -> 62 | H25: ='Raw FS'!N22 -> 72
B26: ='Raw FS'!B23 -> Intangible Assets | D26: ='Raw FS'!J23 -> 6372 | E26: ='Raw FS'!K23 -> 6495 | F26: ='Raw FS'!L23 -> 7594 | G26: ='Raw FS'!M23 -> 7653 | H26: ='Raw FS'!N23 -> 10626
B27: ='Raw FS'!B24 -> Other fixed assets | D27: ='Raw FS'!J24 -> 2730 | E27: ='Raw FS'!K24 -> 2766 | F27: ='Raw FS'!L24 -> 3281 | G27: ='Raw FS'!M24 -> 3294 | H27: ='Raw FS'!N24 -> 5184
B28: ='Raw FS'!B25 -> Gross Block | D28: =SUM(D19:D27) -> 43006 | E28: =SUM(E19:E27) -> 45010 | F28: =SUM(F19:F27) -> 48877 | G28: =SUM(G19:G27) -> 49196 | H28: =SUM(H19:H27) -> 54691
B30: ='Raw FS'!B26 -> Accumulated Depreciation | D30: =-'Raw FS'!J26 -> -17501 | E30: =-'Raw FS'!K26 -> -19210 | F30: =-'Raw FS'!L26 -> -19652 | G30: =-'Raw FS'!M26 -> -21574 | H30: =-'Raw FS'!N26 -> -23730
A31: # | B31: Net Non Current Assets | D31: =SUM(D28:D30) -> 25505 | E31: =SUM(E28:E30) -> 25800 | F31: =SUM(F28:F30) -> 29225 | G31: =SUM(G28:G30) -> 27622 | H31: =SUM(H28:H30) -> 30961
A33: # | B33: Invested Capital | D33: =D31+D16 -> 42266 | E33: =E31+E16 -> 42998 | F33: =F31+F16 -> 52155 | G33: =G31+G16 -> 57118 | H33: =H31+H16 -> 55620
B34: EBIT | D34: =('Historical FS'!H27+'Historical FS'!H21) -> 24622 | E34: =('Historical FS'!I27+'Historical FS'!I21) -> 28015 | F34: =('Historical FS'!J27+'Historical FS'!J21) -> 30905 | G34: =('Historical FS'!K27+'Historical FS'!K21) -> 31747 | H34: =('Historical FS'!L27+'Historical FS'!L21) -> 34424
B36: ROIC | D36: =D34/D33 -> 0.58254862 | E36: =E34/E33 -> 0.65154193 | F36: =F34/F33 -> 0.59256064 | G36: =G34/G33 -> 0.55581428 | H36: =H34/H33 -> 0.61891406
B38: Calculating of Renivestement Rate | D38: =D2 -> 44256 | E38: =E2 -> 44621 | F38: =F2 -> 44986 | G38: =G2 -> 45352 | H38: =H2 -> 45717
B40: Net Capex | D40: =-SUM('Raw FS'!J51:J52) -> 2107 | E40: =-SUM('Raw FS'!K51:K52) -> 2161 | F40: =-SUM('Raw FS'!L51:L52) -> 2579 | G40: =-SUM('Raw FS'!M51:M52) -> 2201 | H40: =-SUM('Raw FS'!N51:N52) -> 2237
B41: Change in Working Capital | E41: =E16-D16 -> 437 | F41: =F16-E16 -> 5732 | G41: =G16-F16 -> 6566 | H41: =H16-G16 -> -4837
B43: EBIT | D43: =D34 -> 24622 | E43: =E34 -> 28015 | F43: =F34 -> 30905 | G43: =G34 -> 31747 | H43: =H34 -> 34424
B44: Marginal Tax Rate | D44: 0.27 | E44: 0.27 | F44: 0.27 | G44: 0.27 | H44: 0.27
B45: EBIT(1-T) | D45: =D43*(1-D44) -> 17974.06 | E45: =E43*(1-E44) -> 20450.95 | F45: =F43*(1-F44) -> 22560.65 | G45: =G43*(1-G44) -> 23175.31 | H45: =H43*(1-H44) -> 25129.52
B47: Reinvestment | E47: =SUM(E40:E41) -> 2598 | F47: =SUM(F40:F41) -> 8311 | G47: =SUM(G40:G41) -> 8767 | H47: =SUM(H40:H41) -> -2600
B49: Reinvestment Rate | E49: =E47/E45 -> 0.12703566 | F49: =F47/F45 -> 0.36838478 | G49: =G47/G45 -> 0.37829052 | H49: =H47/H45 -> -0.10346397
G51: 4 Years Average | H51: =AVERAGE(E49:H49) -> 0.19256175
G52: 4 Years Median | H52: =MEDIAN(E49:H49) -> 0.24771022
B54: Calculating of Growth Rate | D54: =D2 -> 44256 | E54: =E2 -> 44621 | F54: =F2 -> 44986 | G54: =G2 -> 45352 | H54: =H2 -> 45717
B56: Reinvestment Rate | E56: =E49 -> 0.12703566 | F56: =F49 -> 0.36838478 | G56: =G49 -> 0.37829052 | H56: =H49 -> -0.10346397
B57: ROIC | E57: =E36 -> 0.65154193 | F57: =F36 -> 0.59256064 | G57: =G36 -> 0.55581428 | H57: =H36 -> 0.61891406
B59: Intrinsic Growth | E59: =E56*E57 -> 0.082769062 | F59: =F56*F57 -> 0.21829032 | G59: =G56*G57 -> 0.21025927 | H59: =H56*H57 -> -0.064035308
G61: 4 Years Average | H61: =AVERAGE(E59:H59) -> 0.11182084
G62: 4 Years Median | H62: =MEDIAN(E59:H59) -> 0.14651417

Sheet DCF
B2: Calculation of PV of FCFF | D2: ='Intrinsic Growth'!H2 -> 45717 | E2: =D2+366 -> 46083 | F2: =E2+366 -> 46449 | G2: =F2+366 -> 46815 | H2: =G2+366 -> 47181 | I2: =H2+366 -> 47547
B4: EBIT | D4: ='Data Sheet'!K33-'Data Sheet'!K26 -> 37987 | E4: =D4*(1+$C$14) -> 41063.947 | F4: =E4*(1+$C$14) -> 44390.127 | G4: =F4*(1+$C$14) -> 47985.727 | H4: =G4*(1+$C$14) -> 51872.571 | I4: =H4*(1+$C$14) -> 56074.249
B5: Tax Rate | D5: 0.29 | E5: =D5 -> 0.29 | F5: =E5 -> 0.29 | G5: =F5 -> 0.29 | H5: =G5 -> 0.29 | I5: =H5 -> 0.29
B6: EBIT(1-T) | D6: =D4*(1-D5) -> 26970.77 | E6: =E4*(1-E5) -> 29155.402 | F6: =F4*(1-F5) -> 31516.99 | G6: =G4*(1-G5) -> 34069.866 | H6: =H4*(1-H5) -> 36829.525 | I6: =I4*(1-I5) -> 39812.717
B7: less: Reinvestment Rate | D7: ='Intrinsic Growth'!H52 -> 0.24771022 | E7: =D7+(($I$7-$D$7)/4) -> 0.30978266 | F7: =E7+(($I$7-$D$7)/4) -> 0.37185511 | G7: =F7+(($I$7-$D$7)/4) -> 0.43392755 | H7: =G7+(($I$7-$D$7)/4) -> 0.496 | I7: 0.496
B8: Free Cash Flow to Firm (FCFF) | D8: =D6*(1-D7) -> 20289.835 | E8: =E6*(1-E7) -> 20123.564 | F8: =F6*(1-F7) -> 19797.236 | G8: =G6*(1-G7) -> 19286.012 | H8: =H6*(1-H7) -> 18562.081 | I8: =I6*(1-I7) -> 20065.609
B9: Mid Year Convention | E9: 0.5 | F9: =E9+1 -> 1.5 | G9: =F9+1 -> 2.5 | H9: =G9+1 -> 3.5 | I9: =H9+1 -> 4.5
B10: Discount Factor | E10: =1/(1+$C$16)^E9 -> 0.96247977 | F10: =1/(1+$C$16)^F9 -> 0.8916098 | G10: =1/(1+$C$16)^G9 -> 0.82595817 | H10: =1/(1+$C$16)^H9 -> 0.76514065 | I10: =1/(1+$C$16)^I9 -> 0.70880129
B12: PV of FCFF | E12: =E8*E10 -> 19368.523 | F12: =F8*F10 -> 17651.41 | G12: =G8*G10 -> 15929.44 | H12: =H8*H10 -> 14202.603 | I12: =I8*I10 -> 14222.53 | N12: .
B14: Expected Growth | C14: 0.081
B15: Terminal Growth | C15: 0.068
B16: WACC | C16: =WACC!K37 -> 0.079485413
B18: Calculation of Terminal Value | F18: Sensitivity Analysis
F19: =C37 -> 3457.1004 | G19: 0.03 | H19: 0.06 | I19: 0.0795 | J19: 0.09
B20: FCFF (n+1) | C20: =I8*(1+C14) -> 21690.924 | F20: 0.04 | G20: -3465.8494 | H20: 2085.3311 | I20: 1171.8457 | J20: 975.095
B21: WACC | C21: =C16 -> 0.079485413 | F21: 0.05 | G21: -1615.4559 | H21: 3935.7246 | I21: 1489.4417 | J21: 1160.1344
B22: Terminal Growth Rate | C22: =C15 -> 0.068 | F22: 0.068 | G22: -738.95373 | H22: -4391.0462 | I22: 3453.0133 | J22: 1917.1135
F23: 0.07 | G23: -690.25917 | H23: -3465.8494 | I23: 4130.5029 | J23: 2085.3311
B24: Terminal Value | C24: =C20/(C21-C22) -> 1888562.8 | F24: 0.08 | G24: -505.21981 | H24: -1615.4559 | I24: -73780.803 | J24: 3935.7246
B26: Calculation of Equity Value per Share
B28: PV of FCFF | C28: =SUM(E12:I12) -> 81374.505
B29: PV of Terminal Value | C29: =C24*I10 -> 1338615.7
B30: Value of Operating Assets | C30: =SUM(C28:C29) -> 1419990.2
B32: Add : Cash | C32: ='Data Sheet'!K69 -> 24455
B33: Less: Debt | C33: =SUM('Raw FS'!N7) -> 8227
B34: Value of Equity | C34: =C30+C32-C33 -> 1436218.2
B35: No of Share | C35: ='Data Sheet'!B6 -> 415.44013
B37: Equity Value per Share | C37: =C34/C35 -> 3457.1004
B39: Share Price | C39: 1639
B40: Discount/ Premium | C40: =C39/C37-1 -> -0.52590326

Sheet Comps Val
B2: Amount in Crores
B3: Comparable Company Valuation
D5: Market Data | J5: Financials | N5: Valuation
B6: Company | C6: Ticker | D6: Share Price | E6: Share Outstanding | F6: Equity Value | G6: Net Debt | H6: Enterprise Value | J6: Revenue | K6: EBITDA | L6: Net Income | N6: EV/ Revenue | O6: EV/ EBITDA | P6: P/E
B8: ='RV Data'!C4 -> Infosys | C8: INFY | D8: ='RV Data'!D4 -> 1638.7 | E8: ='RV Data'!E4 -> 405.47 | F8: =D8*E8 -> 664443.69 | G8: ='RV Data'!I4 -> -15700 | H8: =F8+G8 -> 648743.69 | J8: ='RV Data'!K4 -> 169458 | K8: ='RV Data'!L4 -> 44059.08 | L8: ='RV Data'!M4 -> 28159 | N8: =$H8/J8 -> 3.828345 | O8: =$H8/K8 -> 14.724404 | P8: =F8/L8 -> 23.596139
B9: ='RV Data'!C3 -> TCS | C9: TCS.NS | D9: ='RV Data'!D3 -> 3282 | E9: ='RV Data'!E3 -> 361.81 | F9: =D9*E9 -> 1187460.4 | G9: ='RV Data'!I3 -> -4531 | H9: =F9+G9 -> 1182929.4 | J9: ='RV Data'!K3 -> 257688 | K9: ='RV Data'!L3 -> 74729.52 | L9: ='RV Data'!M3 -> 49687 | N9: =$H9/J9 -> 4.5905491 | O9: =$H9/K9 -> 15.82948 | P9: =F9/L9 -> 23.898815
B10: ='RV Data'!C5 -> HCL Technologies | C10: HCLTECH.NS | D10: ='RV Data'!D5 -> 1642.4 | E10: ='RV Data'!E5 -> 271.37 | F10: =D10*E10 -> 445698.09 | G10: ='RV Data'!I5 -> -14509 | H10: =F10+G10 -> 431189.09 | J10: ='RV Data'!K5 -> 122427 | K10: ='RV Data'!L5 -> 28158.21 | L10: ='RV Data'!M5 -> 16983 | N10: =$H10/J10 -> 3.5220098 | O10: =$H10/K10 -> 15.313086 | P10: =F10/L10 -> 26.243778
B11: ='RV Data'!C6 -> Wipro | C11: WIT | D11: ='RV Data'!D6 -> 264.45 | E11: ='RV Data'!E6 -> 1048.67 | F11: =D11*E11 -> 277320.78 | G11: ='RV Data'!I6 -> 3966.3 | H11: =F11+G11 -> 281287.08 | J11: ='RV Data'!K6 -> 89654.9 | K11: ='RV Data'!L6 -> 22413.725 | L11: ='RV Data'!M6 -> 13553.7 | N11: =$H11/J11 -> 3.1374424 | O11: =$H11/K11 -> 12.549769 | P11: =F11/L11 -> 20.460891
B12: ='RV Data'!C7 -> LTIMindtree | C12: LTIM.NS | D12: ='RV Data'!D7 -> 6197.5 | E12: ='RV Data'!E7 -> 29.65 | F12: =D12*E12 -> 183755.88 | G12: ='RV Data'!I7 -> -1205.6 | H12: =F12+G12 -> 182550.27 | J12: ='RV Data'!K7 -> 39667.5 | K12: ='RV Data'!L7 -> 7933.5 | L12: ='RV Data'!M7 -> 4851.1 | N12: =$H12/J12 -> 4.6020111 | O12: =$H12/K12 -> 23.010055 | P12: =F12/L12 -> 37.879218
B13: ='RV Data'!C8 -> Tech Mahindra | C13: TECHM.BO | D13: ='RV Data'!D8 -> 1612.5 | E13: ='RV Data'!E8 -> 97.97 | F13: =D13*E13 -> 157976.62 | G13: ='RV Data'!I8 -> -2587.8 | H13: =F13+G13 -> 155388.83 | J13: ='RV Data'!K8 -> 54015.7 | K13: ='RV Data'!L8 -> 8102.355 | L13: ='RV Data'!M8 -> 4461.2 | N13: =$H13/J13 -> 2.8767344 | O13: =$H13/K13 -> 19.17823 | P13: =F13/L13 -> 35.41124
B14: ='RV Data'!C9 -> Persistent Systems | C14: PERSISTENT.NS | D14: ='RV Data'!D9 -> 6358 | E14: ='RV Data'!E9 -> 15.78 | F14: =D14*E14 -> 100329.24 | G14: ='RV Data'!I9 -> -621.53 | H14: =F14+G14 -> 99707.71 | J14: ='RV Data'!K9 -> 13218.7 | K14: ='RV Data'!L9 -> 2643.74 | L14: ='RV Data'!M9 -> 1665.16 | N14: =$H14/J14 -> 7.5429286 | O14: =$H14/K14 -> 37.714643 | P14: =F14/L14 -> 60.252012
B15: ='RV Data'!C10 -> Oracle Fin.Serv. | C15: OFSS.BO | D15: ='RV Data'!D10 -> 7823.5 | E15: ='RV Data'!E10 -> 8.7 | F15: =D15*E15 -> 68064.45 | G15: ='RV Data'!I10 -> -5917.4 | H15: =F15+G15 -> 62147.05 | J15: ='RV Data'!K10 -> 7072.5 | K15: ='RV Data'!L10 -> 3394.8 | L15: ='RV Data'!M10 -> 2373.2 | N15: =$H15/J15 -> 8.7871403 | O15: =$H15/K15 -> 18.306542 | P15: =F15/L15 -> 28.680453
B16: ='RV Data'!C11 -> Coforge | C16: COFORGE.NS | D16: ='RV Data'!D11 -> 1845.4 | E16: ='RV Data'!E11 -> 33.5 | F16: =D16*E16 -> 61820.9 | G16: ='RV Data'!I11 -> 88.3 | H16: =F16+G16 -> 61909.2 | J16: ='RV Data'!K11 -> 14342.3 | K16: ='RV Data'!L11 -> 2438.191 | L16: ='RV Data'!M11 -> 1345 | N16: =$H16/J16 -> 4.3165462 | O16: =$H16/K16 -> 25.391448 | P16: =F16/L16 -> 45.963494
B17: ='RV Data'!C12 -> Mphasis | C17: MPHASIS.NS | D17: ='RV Data'!D12 -> 2890.2 | E17: ='RV Data'!E12 -> 19.06 | F17: =D17*E17 -> 55087.212 | G17: ='RV Data'!I12 -> 366.45 | H17: =F17+G17 -> 55453.662 | J17: ='RV Data'!K12 -> 14905.78 | K17: ='RV Data'!L12 -> 3130.2138 | L17: ='RV Data'!M12 -> 1785.07 | N17: =$H17/J17 -> 3.7202791 | O17: =$H17/K17 -> 17.715615 | P17: =F17/L17 -> 30.859973
B19: High | N19: =MAX(N8:N17) -> 8.7871403 | O19: =MAX(O8:O17) -> 37.714643 | P19: =MAX(P8:P17) -> 60.252012
B20: 75th Percentile | N20: =QUARTILE(N8:N17,3) -> 4.5991456 | O20: =QUARTILE(O8:O17,3) -> 22.052099 | P20: =QUARTILE(P8:P17,3) -> 37.262224
B21: Average | N21: =AVERAGE(N8:N17) -> 4.6923986 | O21: =AVERAGE(O8:O17) -> 19.973327 | P21: =AVERAGE(P8:P17) -> 33.324601
B22: Median | N22: =MEDIAN(N8:N17) -> 4.0724456 | O22: =MEDIAN(O8:O17) -> 18.011079 | P22: =MEDIAN(P8:P17) -> 29.770213
B23: 25th percentile | N23: =QUARTILE(N8:N17,1) -> 3.5715771 | O23: =QUARTILE(O8:O17,1) -> 15.442184 | P23: =QUARTILE(P8:P17,1) -> 24.485056
B24: Low | N24: =MIN(N8:N17) -> 2.8767344 | O24: =MIN(O8:O17) -> 12.549769 | P24: =MIN(P8:P17) -> 20.460891
B26: Infosys Comparable Valuation | N26: EV/ Revenue | O26: EV/ EBITDA | P26: P/E
B28: Implied Enterprize Value | N28: =N$22*J8 -> 690108.48 | O28: =O$22*K8 -> 793551.55 | P28: =P30+P29 -> 822599.42
B29: Net Debt | N29: =$G$8 -> -15700 | O29: =$G$8 -> -15700 | P29: =$G$8 -> -15700
B30: Implied Market Value | N30: =N28-N29 -> 705808.48 | O30: =O28-O29 -> 809251.55 | P30: =P22*L8 -> 838299.42
B31: Share Outstanding | N31: =$E$8 -> 405.47 | O31: =$E$8 -> 405.47 | P31: =$E$8 -> 405.47
B33: Implied value Per Share | N33: =N30/N31 -> 1740.7169 | O33: =O30/O31 -> 1995.8358 | P33: =P30/P31 -> 2067.4758
N35: =IF(N33>$D$8,"Undervalued", "Overvalued") -> Undervalued | O35: =IF(O33>$D$8,"Undervalued", "Overvalued") -> Undervalued | P35: =IF(P33>$D$8,"Undervalued", "Overvalued") -> Undervalued

Sheet Football Field
L3: Football Field Analysis - Data
N4: OpenLow | O4: Low | P4: OpenHigh | Q4: High
L5: Comps | N5: 1740.7169 | O5: 1740.7169 | P5: 2067.4758 | Q5: 2067.4758
L6: DCF Bear | N6: 975.095 | O6: 975.095 | P6: 3935.7246 | Q6: 3935.7246
L7: DCF Base | N7: 1171.85 | O7: 1171.85 | P7: -73780.803 | Q7: -73780.803
L8: DCF Bull | N8: -3465.8494 | O8: -3465.8494 | P8: -505.21981 | Q8: -505.21981
L9: 52w H/L | N9: 1307 | O9: 1307 | P9: 1982.8 | Q9: 1982.8

Sheet RV Data
B2: S.No. | C2: Name | D2: CMP Rs. | E2: No. Eq. Shares Cr. | F2: Market Capitalization | G2: Debt Rs.Cr. | H2: Cash End Rs.Cr. | I2: Net Debt | J2: EV | K2: Sales Rs.Cr. | L2: EBITDA | M2: NP 12M Rs.Cr.
B3: 1 | C3: TCS | D3: 3282 | E3: 361.81 | F3: =D3*E3 -> 1187460.4 | G3: 10932 | H3: 15463 | I3: =G3-H3 -> -4531 | J3: =F3+G3-H3 -> 1182929.4 | K3: 257688 | L3: 74729.52 | M3: 49687
B4: 2 | C4: Infosys | D4: 1638.7 | E4: 405.47 | F4: =D4*E4 -> 664443.69 | G4: 8755 | H4: 24455 | I4: =G4-H4 -> -15700 | J4: =F4+G4-H4 -> 648743.69 | K4: 169458 | L4: 44059.08 | M4: 28159
B5: 3 | C5: HCL Technologies | D5: 1642.4 | E5: 271.37 | F5: =D5*E5 -> 445698.09 | G5: 6780 | H5: 21289 | I5: =G5-H5 -> -14509 | J5: =F5+G5-H5 -> 431189.09 | K5: 122427 | L5: 28158.21 | M5: 16983
B6: 4 | C6: Wipro | D6: 264.45 | E6: 1048.67 | F6: =D6*E6 -> 277320.78 | G6: 16163.7 | H6: 12197.4 | I6: =G6-H6 -> 3966.3 | J6: =F6+G6-H6 -> 281287.08 | K6: 89654.9 | L6: 22413.725 | M6: 13553.7
B7: 5 | C7: LTIMindtree | D7: 6197.5 | E7: 29.65 | F7: =D7*E7 -> 183755.88 | G7: 2382.6 | H7: 3588.2 | I7: =G7-H7 -> -1205.6 | J7: =F7+G7-H7 -> 182550.27 | K7: 39667.5 | L7: 7933.5 | M7: 4851.1
B8: 6 | C8: Tech Mahindra | D8: 1612.5 | E8: 97.97 | F8: =D8*E8 -> 157976.62 | G8: 1954.4 | H8: 4542.2 | I8: =G8-H8 -> -2587.8 | J8: =F8+G8-H8 -> 155388.82 | K8: 54015.7 | L8: 8102.355 | M8: 4461.2
B9: 7 | C9: Persistent Systems | D9: 6358 | E9: 15.78 | F9: =D9*E9 -> 100329.24 | G9: 403.94 | H9: 1025.47 | I9: =G9-H9 -> -621.53 | J9: =F9+G9-H9 -> 99707.71 | K9: 13218.7 | L9: 2643.74 | M9: 1665.16
B10: 8 | C10: Oracle Fin.Serv. | D10: 7823.5 | E10: 8.7 | F10: =D10*E10 -> 68064.45 | G10: 34 | H10: 5951.4 | I10: =G10-H10 -> -5917.4 | J10: =F10+G10-H10 -> 62147.05 | K10: 7072.5 | L10: 3394.8 | M10: 2373.2
B11: 9 | C11: Coforge | D11: 1845.4 | E11: 33.5 | F11: =D11*E11 -> 61820.9 | G11: 971.5 | H11: 883.2 | I11: =G11-H11 -> 88.3 | J11: =F11+G11-H11 -> 61909.2 | K11: 14342.3 | L11: 2438.191 | M11: 1345
B12: 10 | C12: Mphasis | D12: 2890.2 | E12: 19.06 | F12: =D12*E12 -> 55087.212 | G12: 1979.03 | H12: 1612.58 | I12: =G12-H12 -> 366.45 | J12: =F12+G12-H12 -> 55453.662 | K12: 14905.78 | L12: 3130.2138 | M12: 1785.07

Sheet Historical FS
B2: ="Hiscorical financial Statement - "&'Data Sheet'!B1 -> Hiscorical financial Statement - INFOSYS LTD
B3: Years | C3: ='Data Sheet'!B16 -> 42460 | D3: ='Data Sheet'!C16 -> 42825 | E3: ='Data Sheet'!D16 -> 43190 | F3: ='Data Sheet'!E16 -> 43555 | G3: ='Data Sheet'!F16 -> 43921 | H3: ='Data Sheet'!G16 -> 44286 | I3: ='Data Sheet'!H16 -> 44651 | J3: ='Data Sheet'!I16 -> 45016 | ... L3: ='Data Sheet'!K16 -> 45747 | M3: LTM
A5: # | B5: Income Statement
B6: Sales | C6: =IFERROR('Data Sheet'!B17,0) -> 62441 | D6: =IFERROR('Data Sheet'!C17,0) -> 68484 | E6: =IFERROR('Data Sheet'!D17,0) -> 70522 | F6: =IFERROR('Data Sheet'!E17,0) -> 82675 | G6: =IFERROR('Data Sheet'!F17,0) -> 90791 | H6: =IFERROR('Data Sheet'!G17,0) -> 100472 | I6: =IFERROR('Data Sheet'!H17,0) -> 121641 | J6: =IFERROR('Data Sheet'!I17,0) -> 146767 | ... L6: =IFERROR('Data Sheet'!K17,0) -> 162990 | M6: =IFERROR(SUM('Data Sheet'!H42:K42),0) -> 169458
B7: Sales Growth | C7: 0 | D7: =D6/C6-1 -> 0.09677936 | E7: =E6/D6-1 -> 0.029758776 | F7: =F6/E6-1 -> 0.1723292 | G7: =G6/F6-1 -> 0.098167523 | H7: =H6/G6-1 -> 0.10662951 | I7: =I6/H6-1 -> 0.21069552 | J7: =J6/I6-1 -> 0.20655864 | K7: =K6/J6-1 -> 0.047033734 | ... M7: =M6/L6-1 -> 0.039683416
B9: COGS | C9: =IFERROR(SUM('Data Sheet'!B18,'Data Sheet'!B20:B22)-1*'Data Sheet'!B19,0) -> 40492 | D9: =IFERROR(SUM('Data Sheet'!C18,'Data Sheet'!C20:C22)-1*'Data Sheet'!C19,0) -> 44609 | E9: =IFERROR(SUM('Data Sheet'!D18,'Data Sheet'!D20:D22)-1*'Data Sheet'!D19,0) -> 46395 | F9: =IFERROR(SUM('Data Sheet'!E18,'Data Sheet'!E20:E22)-1*'Data Sheet'!E19,0) -> 55446 | G9: =IFERROR(SUM('Data Sheet'!F18,'Data Sheet'!F20:F22)-1*'Data Sheet'!F19,0) -> 62210 | H9: =IFERROR(SUM('Data Sheet'!G18,'Data Sheet'!G20:G22)-1*'Data Sheet'!G19,0) -> 68490 | I9: =IFERROR(SUM('Data Sheet'!H18,'Data Sheet'!H20:H22)-1*'Data Sheet'!H19,0) -> 84819 | J9: =IFERROR(SUM('Data Sheet'!I18,'Data Sheet'!I20:I22)-1*'Data Sheet'!I19,0) -> 104880 | ... L9: =IFERROR(SUM('Data Sheet'!K18,'Data Sheet'!K20:K22)-1*'Data Sheet'!K19,0) -> 116585 | M9: =IFERROR(SUM('Data Sheet'!H43:K43),0) -> 128991
B10: COGS % Sales | C10: =C9/C6 -> 0.64848417 | D10: =D9/D6 -> 0.65137842 | E10: =E9/E6 -> 0.65787981 | F10: =F9/F6 -> 0.67065014 | G10: =G9/G6 -> 0.68520007 | H10: =H9/H6 -> 0.68168246 | I10: =I9/I6 -> 0.69728957 | J10: =J9/J6 -> 0.71460206 | ... M10: =M9/M6 -> 0.76119746
B12: Gross Profit | C12: =C6-C9 -> 21949 | D12: =D6-D9 -> 23875 | E12: =E6-E9 -> 24127 | F12: =F6-F9 -> 27229 | G12: =G6-G9 -> 28581 | H12: =H6-H9 -> 31982 | I12: =I6-I9 -> 36822 | J12: =J6-J9 -> 41887 | ... M12: =M6-M9 -> 40467
B13: Gross Margin | C13: =C12/C6 -> 0.35151583 | D13: =D12/D6 -> 0.34862158 | E13: =E12/E6 -> 0.34212019 | F13: =F12/F6 -> 0.32934986 | G13: =G12/G6 -> 0.31479993 | H13: =H12/H6 -> 0.31831754 | I13: =I12/I6 -> 0.30271043 | J13: =J12/J6 -> 0.28539794 | ... M13: =M12/M6 -> 0.23880254
B15: Selling and General Expenses | C15: =IFERROR(SUM('Data Sheet'!B23:B24),0) -> 4870 | D15: =IFERROR(SUM('Data Sheet'!C23:C24),0) -> 5271 | E15: =IFERROR(SUM('Data Sheet'!D23:D24),0) -> 5305 | F15: =IFERROR(SUM('Data Sheet'!E23:E24),0) -> 7059 | G15: =IFERROR(SUM('Data Sheet'!F23:F24),0) -> 6314 | H15: =IFERROR(SUM('Data Sheet'!G23:G24),0) -> 4093 | I15: =IFERROR(SUM('Data Sheet'!H23:H24),0) -> 5331 | J15: =IFERROR(SUM('Data Sheet'!I23:I24),0) -> 6757 | ... L15: =IFERROR(SUM('Data Sheet'!K23:K24),0) -> 7169 | M15: 0
B16: S&G Exp % Sales | C16: =C15/C6 -> 0.077993626 | D16: =D15/D6 -> 0.076966883 | E16: =E15/E6 -> 0.075224753 | F16: =F15/F6 -> 0.085382522 | G16: =G15/G6 -> 0.069544338 | H16: =H15/H6 -> 0.040737718 | I16: =I15/I6 -> 0.043825684 | J16: =J15/J6 -> 0.04603896 | ... M16: =M15/M6 -> 0
B18: EBITDA | C18: =C12-C15 -> 17079 | D18: =D12-D15 -> 18604 | E18: =E12-E15 -> 18822 | F18: =F12-F15 -> 20170 | G18: =G12-G15 -> 22267 | H18: =H12-H15 -> 27889 | I18: =I12-I15 -> 31491 | J18: =J12-J15 -> 35130 | ... L18: =L12-L15 -> 39236 | M18: 0
B19: EBITDA Margin | C19: =C18/C6 -> 0.2735222 | D19: =D18/D6 -> 0.27165469 | E19: =E18/E6 -> 0.26689544 | F19: =F18/F6 -> 0.24396734 | G19: =G18/G6 -> 0.24525559 | H19: =H18/H6 -> 0.27757982 | I19: =I18/I6 -> 0.25888475 | J19: =J18/J6 -> 0.23935898 | ... M19: =M18/M6 -> 0
B21: Interest | C21: =IFERROR('Data Sheet'!B27,0) -> 0 | D21: =IFERROR('Data Sheet'!C27,0) -> 0 | E21: =IFERROR('Data Sheet'!D27,0) -> 0 | F21: =IFERROR('Data Sheet'!E27,0) -> 0 | G21: =IFERROR('Data Sheet'!F27,0) -> 170 | H21: =IFERROR('Data Sheet'!G27,0) -> 195 | I21: =IFERROR('Data Sheet'!H27,0) -> 200 | J21: =IFERROR('Data Sheet'!I27,0) -> 284 | ... L21: =IFERROR('Data Sheet'!K27,0) -> 416 | M21: =IFERROR(SUM('Data Sheet'!H46:K46),0) -> 414
B22: Interest % Sales | C22: =C21/C6 -> 0 | D22: =D21/D6 -> 0 | E22: =E21/E6 -> 0 | F22: =F21/F6 -> 0 | G22: =G21/G6 -> 0.0018724323 | H22: =H21/H6 -> 0.0019408392 | I22: =I21/I6 -> 0.0016441825 | J22: =J21/J6 -> 0.0019350399 | ... M22: =M21/M6 -> 0.0024430832
B24: Depreciation | C24: =IFERROR('Data Sheet'!B26,0) -> 1459 | D24: =IFERROR('Data Sheet'!C26,0) -> 1703 | E24: =IFERROR('Data Sheet'!D26,0) -> 1863 | F24: =IFERROR('Data Sheet'!E26,0) -> 2011 | G24: =IFERROR('Data Sheet'!F26,0) -> 2893 | H24: =IFERROR('Data Sheet'!G26,0) -> 3267 | I24: =IFERROR('Data Sheet'!H26,0) -> 3476 | J24: =IFERROR('Data Sheet'!I26,0) -> 4225 | ... L24: =IFERROR('Data Sheet'!K26,0) -> 4812 | M24: =IFERROR(SUM('Data Sheet'!H45:K45),0) -> 4824
B25: Depreciation % Sales | C25: =C24/C6 -> 0.023366058 | D25: =D24/D6 -> 0.024867122 | E25: =E24/E6 -> 0.026417288 | F25: =F24/F6 -> 0.024324161 | G25: =G24/G6 -> 0.031864392 | H25: =H24/H6 -> 0.032516522 | I25: =I24/I6 -> 0.028575891 | J25: =J24/J6 -> 0.028787125 | ... M25: =M24/M6 -> 0.028467231
B27: Earning Before Tax | C27: =IFERROR(C18-SUM(C21,C24),0) -> 15620 | D27: =IFERROR(D18-SUM(D21,D24),0) -> 16901 | E27: =IFERROR(E18-SUM(E21,E24),0) -> 16959 | F27: =IFERROR(F18-SUM(F21,F24),0) -> 18159 | G27: =IFERROR(G18-SUM(G21,G24),0) -> 19204 | H27: =IFERROR(H18-SUM(H21,H24),0) -> 24427 | I27: =IFERROR(I18-SUM(I21,I24),0) -> 27815 | J27: =IFERROR(J18-SUM(J21,J24),0) -> 30621 | ... M27: =IFERROR(M18-SUM(M21,M24),0) -> -5238
B28: EBT % Sales | C28: =C27/C6 -> 0.25015615 | D28: =D27/D6 -> 0.24678757 | E28: =E27/E6 -> 0.24047815 | F28: =F27/F6 -> 0.21964318 | G28: =G27/G6 -> 0.21151876 | H28: =H27/H6 -> 0.24312246 | I28: =I27/I6 -> 0.22866468 | J28: =J27/J6 -> 0.20863682 | ... M28: =M27/M6 -> -0.030910314
B30: Tax | C30: =IFERROR('Data Sheet'!B29,0) -> 5251 | D30: =IFERROR('Data Sheet'!C29,0) -> 5598 | E30: =IFERROR('Data Sheet'!D29,0) -> 4241 | F30: =IFERROR('Data Sheet'!E29,0) -> 5631 | G30: =IFERROR('Data Sheet'!F29,0) -> 5368 | H30: =IFERROR('Data Sheet'!G29,0) -> 7205 | I30: =IFERROR('Data Sheet'!H29,0) -> 7964 | J30: =IFERROR('Data Sheet'!I29,0) -> 9214 | ... L30: =IFERROR('Data Sheet'!K29,0) -> 10858 | M30: =IFERROR(SUM('Data Sheet'!H48:K48),0) -> 11143
B31: Effective Tax Rate | C31: =C30/C27 -> 0.33617157 | D31: =D30/D27 -> 0.331223 | E31: =E30/E27 -> 0.25007371 | F31: =F30/F27 -> 0.31009417 | G31: =G30/G27 -> 0.2795251 | H31: =H30/H27 -> 0.29496049 | I31: =I30/I27 -> 0.28632033 | J31: =J30/J27 -> 0.30090461 | ... M31: =M30/M27 -> -2.1273387
B33: Net Profit | C33: =IFERROR(C27-C30,0) -> 10369 | D33: =IFERROR(D27-D30,0) -> 11303 | E33: =IFERROR(E27-E30,0) -> 12718 | F33: =IFERROR(F27-F30,0) -> 12528 | G33: =IFERROR(G27-G30,0) -> 13836 | H33: =IFERROR(H27-H30,0) -> 17222 | I33: =IFERROR(I27-I30,0) -> 19851 | J33: =IFERROR(J27-J30,0) -> 21407 | ... L33: =IFERROR(L27-L30,0) -> 23150 | M33: =IFERROR(SUM('Data Sheet'!H49:K49),0) -> 28124
B34: Net Margin | C34: =C33/C6 -> 0.16606076 | D34: =D33/D6 -> 0.16504585 | E34: =E33/E6 -> 0.18034089 | F34: =F33/F6 -> 0.15153311 | G34: =G33/G6 -> 0.15239396 | H34: =H33/H6 -> 0.17141094 | I34: =I33/I6 -> 0.16319333 | J34: =J33/J6 -> 0.14585704 | ... M34: =M33/M6 -> 0.16596443
B36: No of Equity Share | C36: =IFERROR('Data Sheet'!B93,0) -> 459.39 | D36: =IFERROR('Data Sheet'!C93,0) -> 459.39 | E36: =IFERROR('Data Sheet'!D93,0) -> 436.82 | F36: =IFERROR('Data Sheet'!E93,0) -> 436.89 | G36: =IFERROR('Data Sheet'!F93,0) -> 425.9 | H36: =IFERROR('Data Sheet'!G93,0) -> 426.07 | I36: =IFERROR('Data Sheet'!H93,0) -> 420.67 | J36: =IFERROR('Data Sheet'!I93,0) -> 414.86 | ... L36: =IFERROR('Data Sheet'!K93,0) -> 415.33
B38: Earning per Share | C38: =IFERROR(C36/C33,0) -> 0.044304176 | D38: =IFERROR(D36/D33,0) -> 0.040643192 | E38: =IFERROR(E36/E33,0) -> 0.034346595 | F38: =IFERROR(F36/F33,0) -> 0.034873084 | G38: =IFERROR(G36/G33,0) -> 0.030782018 | H38: =IFERROR(H36/H33,0) -> 0.024739868 | I38: =IFERROR(I36/I33,0) -> 0.021191376 | J38: =IFERROR(J36/J33,0) -> 0.019379642 | ... L38: =IFERROR(L36/L33,0) -> 0.017940821
B39: EPS Growth % | C39: 0 | D39: =IFERROR(D38/C38-1,0) -> -0.082632929 | E39: =IFERROR(E38/D38-1,0) -> -0.15492377 | F39: =IFERROR(F38/E38-1,0) -> 0.015328708 | G39: =IFERROR(G38/F38-1,0) -> -0.11731301 | H39: =IFERROR(H38/G38-1,0) -> -0.19628831 | I39: =IFERROR(I38/H38-1,0) -> -0.14343213 | J39: =IFERROR(J38/I38-1,0) -> -0.08549391 | K39: =IFERROR(K38/J38-1,0) -> -0.0054850664 | L39: =IFERROR(L38/K38-1,0) -> -0.069138124
B41: Dividend per Share | C41: =IFERROR('Data Sheet'!B31/'Historical FS'!C36,0) -> 12.077755 | D41: =IFERROR('Data Sheet'!C31/'Historical FS'!D36,0) -> 12.824833 | E41: =IFERROR('Data Sheet'!D31/'Historical FS'!E36,0) -> 21.669337 | F41: =IFERROR('Data Sheet'!E31/'Historical FS'!F36,0) -> 21.109433 | G41: =IFERROR('Data Sheet'!F31/'Historical FS'!G36,0) -> 17.438366 | H41: =IFERROR('Data Sheet'!G31/'Historical FS'!H36,0) -> 26.91952 | I41: =IFERROR('Data Sheet'!H31/'Historical FS'!I36,0) -> 30.92115 | J41: =IFERROR('Data Sheet'!I31/'Historical FS'!J36,0) -> 33.913127 | ... L41: =IFERROR('Data Sheet'!K31/'Historical FS'!L36,0) -> 42.924422
B42: Dividend Payout Ratio | C42: =IFERROR(C41/C38,0) -> 272.60986 | D42: =IFERROR(D41/D38,0) -> 315.54689 | E42: =IFERROR(E41/E38,0) -> 630.90205 | F42: =IFERROR(F41/F38,0) -> 605.32164 | G42: =IFERROR(G41/G38,0) -> 566.51146 | H42: =IFERROR(H41/H38,0) -> 1088.1028 | I42: =IFERROR(I41/I38,0) -> 1459.1384 | J42: =IFERROR(J41/J38,0) -> 1749.9357 | ... L42: =IFERROR(L41/L38,0) -> 2392.5562
B44: Retained Earnings | C44: =IFERROR(IF(C38>C41,1-C42,0),0) -> 0 | D44: =IFERROR(IF(D38>D41,1-D42,0),0) -> 0 | E44: =IFERROR(IF(E38>E41,1-E42,0),0) -> 0 | F44: =IFERROR(IF(F38>F41,1-F42,0),0) -> 0 | G44: =IFERROR(IF(G38>G41,1-G42,0),0) -> 0 | H44: =IFERROR(IF(H38>H41,1-H42,0),0) -> 0 | I44: =IFERROR(IF(I38>I41,1-I42,0),0) -> 0 | J44: =IFERROR(IF(J38>J41,1-J42,0),0) -> 0 | ... L44: =IFERROR(IF(L38>L41,1-L42,0),0) -> 0
A46: # | B46: Balance Sheet
B47: Equity Share Capital | C47: =IFERROR('Data Sheet'!B57,0) -> 1144 | D47: =IFERROR('Data Sheet'!C57,0) -> 1144 | E47: =IFERROR('Data Sheet'!D57,0) -> 1088 | F47: =IFERROR('Data Sheet'!E57,0) -> 2170 | G47: =IFERROR('Data Sheet'!F57,0) -> 2122 | H47: =IFERROR('Data Sheet'!G57,0) -> 2124 | I47: =IFERROR('Data Sheet'!H57,0) -> 2098 | J47: =IFERROR('Data Sheet'!I57,0) -> 2069 | ... L47: =IFERROR('Data Sheet'!K57,0) -> 2073
B48: Reserves | C48: =IFERROR('Data Sheet'!B58,0) -> 60600 | D48: =IFERROR('Data Sheet'!C58,0) -> 67838 | E48: =IFERROR('Data Sheet'!D58,0) -> 63835 | F48: =IFERROR('Data Sheet'!E58,0) -> 62778 | G48: =IFERROR('Data Sheet'!F58,0) -> 63328 | H48: =IFERROR('Data Sheet'!G58,0) -> 74227 | I48: =IFERROR('Data Sheet'!H58,0) -> 73252 | J48: =IFERROR('Data Sheet'!I58,0) -> 73338 | ... L48: =IFERROR('Data Sheet'!K58,0) -> 93745
B49: Borrowings | C49: =IFERROR('Data Sheet'!B59,0) -> 0 | D49: =IFERROR('Data Sheet'!C59,0) -> 0 | E49: =IFERROR('Data Sheet'!D59,0) -> 0 | F49: =IFERROR('Data Sheet'!E59,0) -> 0 | G49: =IFERROR('Data Sheet'!F59,0) -> 4633 | H49: =IFERROR('Data Sheet'!G59,0) -> 5325 | I49: =IFERROR('Data Sheet'!H59,0) -> 5474 | J49: =IFERROR('Data Sheet'!I59,0) -> 8299 | ... L49: =IFERROR('Data Sheet'!K59,0) -> 8227
B50: Other Liabilities | C50: =IFERROR('Data Sheet'!B60,0) -> 13354 | D50: =IFERROR('Data Sheet'!C60,0) -> 14166 | E50: =IFERROR('Data Sheet'!D60,0) -> 14426 | F50: =IFERROR('Data Sheet'!E60,0) -> 19118 | G50: =IFERROR('Data Sheet'!F60,0) -> 21717 | H50: =IFERROR('Data Sheet'!G60,0) -> 25835 | I50: =IFERROR('Data Sheet'!H60,0) -> 35905 | J50: =IFERROR('Data Sheet'!I60,0) -> 40890 | ... L50: =IFERROR('Data Sheet'!K60,0) -> 43750
B51: Total Liabilities | C51: =IFERROR('Data Sheet'!B61,0) -> 75098 | D51: =IFERROR('Data Sheet'!C61,0) -> 83148 | E51: =IFERROR('Data Sheet'!D61,0) -> 79349 | F51: =IFERROR('Data Sheet'!E61,0) -> 84066 | G51: =IFERROR('Data Sheet'!F61,0) -> 91800 | H51: =IFERROR('Data Sheet'!G61,0) -> 107511 | I51: =IFERROR('Data Sheet'!H61,0) -> 116729 | J51: =IFERROR('Data Sheet'!I61,0) -> 124596 | ... L51: =IFERROR('Data Sheet'!K61,0) -> 147795
B53: Fixed Assets Net Block | C53: =IFERROR('Data Sheet'!B62,0) -> 13386 | D53: =IFERROR('Data Sheet'!C62,0) -> 14179 | E53: =IFERROR('Data Sheet'!D62,0) -> 12574 | F53: =IFERROR('Data Sheet'!E62,0) -> 15710 | G53: =IFERROR('Data Sheet'!F62,0) -> 23789 | H53: =IFERROR('Data Sheet'!G62,0) -> 25505 | I53: =IFERROR('Data Sheet'!H62,0) -> 25800 | J53: =IFERROR('Data Sheet'!I62,0) -> 29225 | ... L53: =IFERROR('Data Sheet'!K62,0) -> 30961
B54: Capital Work in Progress | C54: =IFERROR('Data Sheet'!B63,0) -> 960 | D54: =IFERROR('Data Sheet'!C63,0) -> 1365 | E54: =IFERROR('Data Sheet'!D63,0) -> 1606 | F54: =IFERROR('Data Sheet'!E63,0) -> 1388 | G54: =IFERROR('Data Sheet'!F63,0) -> 954 | H54: =IFERROR('Data Sheet'!G63,0) -> 922 | I54: =IFERROR('Data Sheet'!H63,0) -> 416 | J54: =IFERROR('Data Sheet'!I63,0) -> 288 | ... L54: =IFERROR('Data Sheet'!K63,0) -> 814
B55: Investments | C55: =IFERROR('Data Sheet'!B64,0) -> 1892 | D55: =IFERROR('Data Sheet'!C64,0) -> 16423 | E55: =IFERROR('Data Sheet'!D64,0) -> 12163 | F55: =IFERROR('Data Sheet'!E64,0) -> 11261 | G55: =IFERROR('Data Sheet'!F64,0) -> 8792 | H55: =IFERROR('Data Sheet'!G64,0) -> 14205 | I55: =IFERROR('Data Sheet'!H64,0) -> 20324 | J55: =IFERROR('Data Sheet'!I64,0) -> 19478 | ... L55: =IFERROR('Data Sheet'!K64,0) -> 23541
B56: Other Assets | C56: =IFERROR('Data Sheet'!B65-SUM('Data Sheet'!B67:B69),0) -> 14833 | D56: =IFERROR('Data Sheet'!C65-SUM('Data Sheet'!C67:C69),0) -> 16234 | E56: =IFERROR('Data Sheet'!D65-SUM('Data Sheet'!D67:D69),0) -> 20046 | F56: =IFERROR('Data Sheet'!E65-SUM('Data Sheet'!E67:E69),0) -> 21312 | G56: =IFERROR('Data Sheet'!F65-SUM('Data Sheet'!F67:F69),0) -> 21129 | H56: =IFERROR('Data Sheet'!G65-SUM('Data Sheet'!G67:G69),0) -> 22871 | I56: =IFERROR('Data Sheet'!H65-SUM('Data Sheet'!H67:H69),0) -> 30019 | J56: =IFERROR('Data Sheet'!I65-SUM('Data Sheet'!I67:I69),0) -> 38008 | ... L56: =IFERROR('Data Sheet'!K65-SUM('Data Sheet'!K67:K69),0) -> 36866
B57: Total Non Current Assets | C57: =SUM(C53:C56) -> 31071 | D57: =SUM(D53:D56) -> 48201 | E57: =SUM(E53:E56) -> 46389 | F57: =SUM(F53:F56) -> 49671 | G57: =SUM(G53:G56) -> 54664 | H57: =SUM(H53:H56) -> 63503 | I57: =SUM(I53:I56) -> 76559 | J57: =SUM(J53:J56) -> 86999 | ... L57: =SUM(L53:L56) -> 92182
B59: Receivables | C59: =IFERROR('Data Sheet'!B67,0) -> 11330 | D59: =IFERROR('Data Sheet'!C67,0) -> 12322 | E59: =IFERROR('Data Sheet'!D67,0) -> 13142 | F59: =IFERROR('Data Sheet'!E67,0) -> 14827 | G59: =IFERROR('Data Sheet'!F67,0) -> 18487 | H59: =IFERROR('Data Sheet'!G67,0) -> 19294 | I59: =IFERROR('Data Sheet'!H67,0) -> 22698 | J59: =IFERROR('Data Sheet'!I67,0) -> 25424 | ... L59: =IFERROR('Data Sheet'!K67,0) -> 31158
B60: Inventory | C60: =IFERROR('Data Sheet'!B68,0) -> 0 | D60: =IFERROR('Data Sheet'!C68,0) -> 0 | E60: =IFERROR('Data Sheet'!D68,0) -> 0 | F60: =IFERROR('Data Sheet'!E68,0) -> 0 | G60: =IFERROR('Data Sheet'!F68,0) -> 0 | H60: =IFERROR('Data Sheet'!G68,0) -> 0 | I60: =IFERROR('Data Sheet'!H68,0) -> 0 | J60: =IFERROR('Data Sheet'!I68,0) -> 0 | ... L60: =IFERROR('Data Sheet'!K68,0) -> 0
B61: Cash & Bank | C61: =IFERROR('Data Sheet'!B69,0) -> 32697 | D61: =IFERROR('Data Sheet'!C69,0) -> 22625 | E61: =IFERROR('Data Sheet'!D69,0) -> 19818 | F61: =IFERROR('Data Sheet'!E69,0) -> 19568 | G61: =IFERROR('Data Sheet'!F69,0) -> 18649 | H61: =IFERROR('Data Sheet'!G69,0) -> 24714 | I61: =IFERROR('Data Sheet'!H69,0) -> 17472 | J61: =IFERROR('Data Sheet'!I69,0) -> 12173 | ... L61: =IFERROR('Data Sheet'!K69,0) -> 24455
B62: Total Current Assets | C62: =SUM(C59:C61) -> 44027 | D62: =SUM(D59:D61) -> 34947 | E62: =SUM(E59:E61) -> 32960 | F62: =SUM(F59:F61) -> 34395 | G62: =SUM(G59:G61) -> 37136 | H62: =SUM(H59:H61) -> 44008 | I62: =SUM(I59:I61) -> 40170 | J62: =SUM(J59:J61) -> 37597 | ... L62: =SUM(L59:L61) -> 55613
B64: Total Assets | C64: =C57+C62 -> 75098 | D64: =D57+D62 -> 83148 | E64: =E57+E62 -> 79349 | F64: =F57+F62 -> 84066 | G64: =G57+G62 -> 91800 | H64: =H57+H62 -> 107511 | I64: =I57+I62 -> 116729 | J64: =J57+J62 -> 124596 | ... L64: =L57+L62 -> 147795
B66: Check | C66: =C64=C51 -> TRUE | D66: =D64=D51 -> TRUE | E66: =E64=E51 -> TRUE | F66: =F64=F51 -> TRUE | G66: =G64=G51 -> TRUE | H66: =H64=H51 -> TRUE | I66: =I64=I51 -> TRUE | J66: =J64=J51 -> TRUE | ... L66: =L64=L51 -> TRUE
A68: # | B68: Cash Flow Statement
B69: Operating Activity
B70: Profit from operations | C70: =IFERROR('Cash Flow Data'!E4,0) -> 17839 | D70: =IFERROR('Cash Flow Data'!F4,0) -> 19340 | E70: =IFERROR('Cash Flow Data'!G4,0) -> 19963 | F70: =IFERROR('Cash Flow Data'!H4,0) -> 22126 | G70: =IFERROR('Cash Flow Data'!I4,0) -> 23920 | H70: =IFERROR('Cash Flow Data'!J4,0) -> 28845 | I70: =IFERROR('Cash Flow Data'!K4,0) -> 32921 | J70: =IFERROR('Cash Flow Data'!L4,0) -> 37605 | ... L70: =IFERROR('Cash Flow Data'!N4,0) -> 41591
B71: Receivables | C71: =IFERROR('Cash Flow Data'!E5,0) -> -1654 | D71: =IFERROR('Cash Flow Data'!F5,0) -> -1743 | E71: =IFERROR('Cash Flow Data'!G5,0) -> -1523 | F71: =IFERROR('Cash Flow Data'!H5,0) -> -2881 | G71: =IFERROR('Cash Flow Data'!I5,0) -> -3861 | H71: =IFERROR('Cash Flow Data'!J5,0) -> -1835 | I71: =IFERROR('Cash Flow Data'!K5,0) -> -7937 | J71: =IFERROR('Cash Flow Data'!L5,0) -> -7076 | ... L71: =IFERROR('Cash Flow Data'!N5,0) -> -1769
B72: Inventory | C72: 0 | D72: 0 | E72: 0 | F72: 0 | G72: 0 | H72: 0 | I72: 0 | J72: 0 | K72: 0 | L72: 0
B73: Payables | C73: =IFERROR('Cash Flow Data'!E6,0) -> 242 | D73: =IFERROR('Cash Flow Data'!F6,0) -> -19 | E73: =IFERROR('Cash Flow Data'!G6,0) -> 328 | F73: =IFERROR('Cash Flow Data'!H6,0) -> 916 | G73: =IFERROR('Cash Flow Data'!I6,0) -> -373 | H73: =IFERROR('Cash Flow Data'!J6,0) -> -245 | I73: =IFERROR('Cash Flow Data'!K6,0) -> 1489 | J73: =IFERROR('Cash Flow Data'!L6,0) -> -279 | ... L73: =IFERROR('Cash Flow Data'!N6,0) -> 176
B74: Loans Advances | C74: =IFERROR('Cash Flow Data'!E7,0) -> -1134 | D74: =IFERROR('Cash Flow Data'!F7,0) -> 0 | E74: =IFERROR('Cash Flow Data'!G7,0) -> 0 | F74: =IFERROR('Cash Flow Data'!H7,0) -> 0 | G74: =IFERROR('Cash Flow Data'!I7,0) -> 0 | H74: =IFERROR('Cash Flow Data'!J7,0) -> -534 | I74: =IFERROR('Cash Flow Data'!K7,0) -> -1914 | J74: =IFERROR('Cash Flow Data'!L7,0) -> -3108 | ... L74: =IFERROR('Cash Flow Data'!N7,0) -> -1024
B75: Operating investments | C75: 0 | D75: 0 | E75: 0 | F75: 0 | G75: 0 | H75: 0 | I75: 0 | J75: 0 | K75: 0 | L75: 0
B76: Operating Deposits | C76: 0 | D76: 0 | E76: 0 | F76: 0 | G76: 0 | H76: 0 | I76: 0 | J76: 0 | K76: 0 | L76: 0
B77: Other WC items | C77: =IFERROR('Cash Flow Data'!E8,0) -> 600 | D77: =IFERROR('Cash Flow Data'!F8,0) -> -394 | E77: =IFERROR('Cash Flow Data'!G8,0) -> 1279 | F77: =IFERROR('Cash Flow Data'!H8,0) -> 1512 | G77: =IFERROR('Cash Flow Data'!I8,0) -> 1867 | H77: =IFERROR('Cash Flow Data'!J8,0) -> 3382 | I77: =IFERROR('Cash Flow Data'!K8,0) -> 6938 | J77: =IFERROR('Cash Flow Data'!L8,0) -> 4119 | ... L77: =IFERROR('Cash Flow Data'!N8,0) -> 2322
B78: Working capital changes | C78: =IFERROR('Cash Flow Data'!E9,0) -> -1946 | D78: =IFERROR('Cash Flow Data'!F9,0) -> -2156 | E78: =IFERROR('Cash Flow Data'!G9,0) -> 84 | F78: =IFERROR('Cash Flow Data'!H9,0) -> -453 | G78: =IFERROR('Cash Flow Data'!I9,0) -> -2367 | H78: =IFERROR('Cash Flow Data'!J9,0) -> 768 | I78: =IFERROR('Cash Flow Data'!K9,0) -> -1424 | J78: =IFERROR('Cash Flow Data'!L9,0) -> -6344 | ... L78: =IFERROR('Cash Flow Data'!N9,0) -> -295
B79: Direct taxes | C79: =IFERROR('Cash Flow Data'!E10,0) -> -5865 | D79: =IFERROR('Cash Flow Data'!F10,0) -> -5653 | E79: =IFERROR('Cash Flow Data'!G10,0) -> -6829 | F79: =IFERROR('Cash Flow Data'!H10,0) -> -6832 | G79: =IFERROR('Cash Flow Data'!I10,0) -> -4550 | H79: =IFERROR('Cash Flow Data'!J10,0) -> -6389 | I79: =IFERROR('Cash Flow Data'!K10,0) -> -7612 | J79: =IFERROR('Cash Flow Data'!L10,0) -> -8794 | ... L79: =IFERROR('Cash Flow Data'!N10,0) -> -5602
B80: Cash from Operating Activity | C80: =SUM(C70:C79) -> 8082 | D80: =SUM(D70:D79) -> 9375 | E80: =SUM(E70:E79) -> 13302 | F80: =SUM(F70:F79) -> 14388 | G80: =SUM(G70:G79) -> 14636 | H80: =SUM(H70:H79) -> 23992 | I80: =SUM(I70:I79) -> 22461 | J80: =SUM(J70:J79) -> 16123 | ... L80: =SUM(L70:L79) -> 35399
B82: Investing Activities
B83: Fixed assets purchased | C83: =IFERROR('Cash Flow Data'!E12,0) -> -2723 | D83: =IFERROR('Cash Flow Data'!F12,0) -> -2760 | E83: =IFERROR('Cash Flow Data'!G12,0) -> -1998 | F83: =IFERROR('Cash Flow Data'!H12,0) -> -2445 | G83: =IFERROR('Cash Flow Data'!I12,0) -> -3307 | H83: =IFERROR('Cash Flow Data'!J12,0) -> -2107 | I83: =IFERROR('Cash Flow Data'!K12,0) -> -2161 | J83: =IFERROR('Cash Flow Data'!L12,0) -> -2579 | ... L83: =IFERROR('Cash Flow Data'!N12,0) -> -2237
B84: Fixed assets sold | C84: =IFERROR('Cash Flow Data'!E13,0) -> 0 | D84: =IFERROR('Cash Flow Data'!F13,0) -> 0 | E84: =IFERROR('Cash Flow Data'!G13,0) -> 0 | F84: =IFERROR('Cash Flow Data'!H13,0) -> 0 | G84: =IFERROR('Cash Flow Data'!I13,0) -> 0 | H84: =IFERROR('Cash Flow Data'!J13,0) -> 0 | I84: =IFERROR('Cash Flow Data'!K13,0) -> 0 | J84: =IFERROR('Cash Flow Data'!L13,0) -> 0 | ... L84: =IFERROR('Cash Flow Data'!N13,0) -> 0
B85: Investments purchased | C85: =IFERROR('Cash Flow Data'!E14,0) -> -24577 | D85: =IFERROR('Cash Flow Data'!F14,0) -> -66410 | E85: =IFERROR('Cash Flow Data'!G14,0) -> -69159 | F85: =IFERROR('Cash Flow Data'!H14,0) -> -79410 | G85: =IFERROR('Cash Flow Data'!I14,0) -> -37482 | H85: =IFERROR('Cash Flow Data'!J14,0) -> -46738 | I85: =IFERROR('Cash Flow Data'!K14,0) -> -59951 | J85: =IFERROR('Cash Flow Data'!L14,0) -> -75800 | ... L85: =IFERROR('Cash Flow Data'!N14,0) -> -82753
B86: Investments sold | C86: =IFERROR('Cash Flow Data'!E15,0) -> 24980 | D86: =IFERROR('Cash Flow Data'!F15,0) -> 52048 | E86: =IFERROR('Cash Flow Data'!G15,0) -> 74003 | F86: =IFERROR('Cash Flow Data'!H15,0) -> 78098 | G86: =IFERROR('Cash Flow Data'!I15,0) -> 38861 | H86: =IFERROR('Cash Flow Data'!J15,0) -> 40381 | I86: =IFERROR('Cash Flow Data'!K15,0) -> 57356 | J86: =IFERROR('Cash Flow Data'!L15,0) -> 76722 | ... L86: =IFERROR('Cash Flow Data'!N15,0) -> 84888
B87: Interest received | C87: =IFERROR('Cash Flow Data'!E16,0) -> 2383 | D87: =IFERROR('Cash Flow Data'!F16,0) -> 0 | E87: =IFERROR('Cash Flow Data'!G16,0) -> 0 | F87: =IFERROR('Cash Flow Data'!H16,0) -> 0 | G87: =IFERROR('Cash Flow Data'!I16,0) -> 0 | H87: =IFERROR('Cash Flow Data'!J16,0) -> 0 | I87: =IFERROR('Cash Flow Data'!K16,0) -> 0 | J87: =IFERROR('Cash Flow Data'!L16,0) -> 0 | ... L87: =IFERROR('Cash Flow Data'!N16,0) -> 0
B88: Dividends received | C88: =IFERROR('Cash Flow Data'!E17,0) -> 0 | D88: =IFERROR('Cash Flow Data'!F17,0) -> 2753 | E88: =IFERROR('Cash Flow Data'!G17,0) -> 1768 | F88: =IFERROR('Cash Flow Data'!H17,0) -> 1557 | G88: =IFERROR('Cash Flow Data'!I17,0) -> 1929 | H88: =IFERROR('Cash Flow Data'!J17,0) -> 1418 | I88: =IFERROR('Cash Flow Data'!K17,0) -> 1898 | J88: =IFERROR('Cash Flow Data'!L17,0) -> 1525 | ... L88: =IFERROR('Cash Flow Data'!N17,0) -> 2040
B89: Acquisition of companies | C89: =IFERROR('Cash Flow Data'!E18,0) -> -747 | D89: =IFERROR('Cash Flow Data'!F18,0) -> 0 | E89: =IFERROR('Cash Flow Data'!G18,0) -> 0 | F89: =IFERROR('Cash Flow Data'!H18,0) -> 0 | G89: =IFERROR('Cash Flow Data'!I18,0) -> 0 | H89: =IFERROR('Cash Flow Data'!J18,0) -> 0 | I89: =IFERROR('Cash Flow Data'!K18,0) -> 0 | J89: =IFERROR('Cash Flow Data'!L18,0) -> 0 | ... L89: =IFERROR('Cash Flow Data'!N18,0) -> 0
B90: Investment in group cos | C90: 0 | D90: 0 | E90: 0 | F90: 0 | G90: 0 | H90: 0 | I90: 0 | J90: 0 | K90: 0 | L90: 0
B91: Redemp n Canc of Shares | C91: 0 | D91: 0 | E91: 0 | F91: 0 | G91: 0 | H91: 0 | I91: 0 | J91: 0 | K91: 0 | L91: 0
B92: Inter corporate deposits | C92: =IFERROR('Cash Flow Data'!E19,0) -> -142 | D92: =IFERROR('Cash Flow Data'!F19,0) -> -164 | E92: =IFERROR('Cash Flow Data'!G19,0) -> -130 | F92: =IFERROR('Cash Flow Data'!H19,0) -> -24 | G92: =IFERROR('Cash Flow Data'!I19,0) -> -108 | H92: =IFERROR('Cash Flow Data'!J19,0) -> 0 | I92: =IFERROR('Cash Flow Data'!K19,0) -> 0 | J92: =IFERROR('Cash Flow Data'!L19,0) -> 0 | ... L92: =IFERROR('Cash Flow Data'!N19,0) -> 0
B93: Other investing items | C93: =IFERROR('Cash Flow Data'!E20,0) -> -59 | D93: =IFERROR('Cash Flow Data'!F20,0) -> -131 | E93: =IFERROR('Cash Flow Data'!G20,0) -> 49 | F93: =IFERROR('Cash Flow Data'!H20,0) -> 1592 | G93: =IFERROR('Cash Flow Data'!I20,0) -> -224 | H93: =IFERROR('Cash Flow Data'!J20,0) -> -327 | I93: =IFERROR('Cash Flow Data'!K20,0) -> -3627 | J93: =IFERROR('Cash Flow Data'!L20,0) -> -939 | ... L93: =IFERROR('Cash Flow Data'!N20,0) -> -3802
B94: Cash from Investing Activities | C94: =SUM(C83:C93) -> -885 | D94: =SUM(D83:D93) -> -14664 | E94: =SUM(E83:E93) -> 4533 | F94: =SUM(F83:F93) -> -632 | G94: =SUM(G83:G93) -> -331 | H94: =SUM(H83:H93) -> -7373 | I94: =SUM(I83:I93) -> -6485 | J94: =SUM(J83:J93) -> -1071 | ... L94: =SUM(L83:L93) -> -1864
B96: Financing Activities
B97: Proceeds from shares | C97: =IFERROR('Cash Flow Data'!E22,0) -> 0 | D97: =IFERROR('Cash Flow Data'!F22,0) -> 0 | E97: =IFERROR('Cash Flow Data'!G22,0) -> 5 | F97: =IFERROR('Cash Flow Data'!H22,0) -> 6 | G97: =IFERROR('Cash Flow Data'!I22,0) -> 6 | H97: =IFERROR('Cash Flow Data'!J22,0) -> 15 | I97: =IFERROR('Cash Flow Data'!K22,0) -> 21 | J97: =IFERROR('Cash Flow Data'!L22,0) -> 35 | ... L97: =IFERROR('Cash Flow Data'!N22,0) -> 6
B98: Proceeds from borrowings | C98: 0 | D98: 0 | E98: 0 | F98: 0 | G98: 0 | H98: 0 | I98: 0 | J98: 0 | K98: 0 | L98: 0
B99: Repayment of borrowings | C99: =IFERROR('Cash Flow Data'!E23,0) -> 0 | D99: =IFERROR('Cash Flow Data'!F23,0) -> 0 | E99: =IFERROR('Cash Flow Data'!G23,0) -> 0 | F99: =IFERROR('Cash Flow Data'!H23,0) -> 0 | G99: =IFERROR('Cash Flow Data'!I23,0) -> 0 | H99: =IFERROR('Cash Flow Data'!J23,0) -> 0 | I99: =IFERROR('Cash Flow Data'!K23,0) -> 0 | J99: =IFERROR('Cash Flow Data'!L23,0) -> 0 | ... L99: =IFERROR('Cash Flow Data'!N23,0) -> -985
B100: Interest paid fin | C100: 0 | D100: 0 | E100: 0 | F100: 0 | G100: 0 | H100: 0 | I100: 0 | J100: 0 | K100: 0 | L100: 0
B101: Dividends paid | C101: =IFERROR('Cash Flow Data'!E24,0) -> -6813 | D101: =IFERROR('Cash Flow Data'!F24,0) -> -6939 | E101: =IFERROR('Cash Flow Data'!G24,0) -> -7464 | F101: =IFERROR('Cash Flow Data'!H24,0) -> -13705 | G101: =IFERROR('Cash Flow Data'!I24,0) -> -9548 | H101: =IFERROR('Cash Flow Data'!J24,0) -> -9137 | I101: =IFERROR('Cash Flow Data'!K24,0) -> -12731 | J101: =IFERROR('Cash Flow Data'!L24,0) -> -13653 | ... L101: =IFERROR('Cash Flow Data'!N24,0) -> -20289
B102: Financial liabilities | C102: =IFERROR('Cash Flow Data'!E25,0) -> 0 | D102: =IFERROR('Cash Flow Data'!F25,0) -> 0 | E102: =IFERROR('Cash Flow Data'!G25,0) -> 0 | F102: =IFERROR('Cash Flow Data'!H25,0) -> 0 | G102: =IFERROR('Cash Flow Data'!I25,0) -> -571 | H102: =IFERROR('Cash Flow Data'!J25,0) -> -698 | I102: =IFERROR('Cash Flow Data'!K25,0) -> -915 | J102: =IFERROR('Cash Flow Data'!L25,0) -> -1231 | ... L102: =IFERROR('Cash Flow Data'!N25,0) -> -2355
B103: Other financing items | C103: =IFERROR('Cash Flow Data'!E26,0) -> 0 | D103: =IFERROR('Cash Flow Data'!F26,0) -> 0 | E103: =IFERROR('Cash Flow Data'!G26,0) -> -13046 | F103: =IFERROR('Cash Flow Data'!H26,0) -> -813 | G103: =IFERROR('Cash Flow Data'!I26,0) -> -7478 | H103: =IFERROR('Cash Flow Data'!J26,0) -> 34 | I103: =IFERROR('Cash Flow Data'!K26,0) -> -11017 | J103: =IFERROR('Cash Flow Data'!L26,0) -> -11846 | ... L103: =IFERROR('Cash Flow Data'!N26,0) -> -538
B104: Cash from Financing Activities | C104: =SUM(C97:C103) -> -6813 | D104: =SUM(D97:D103) -> -6939 | E104: =SUM(E97:E103) -> -20505 | F104: =SUM(F97:F103) -> -14512 | G104: =SUM(G97:G103) -> -17591 | H104: =SUM(H97:H103) -> -9786 | I104: =SUM(I97:I103) -> -24642 | J104: =SUM(J97:J103) -> -26695 | ... L104: =SUM(L97:L103) -> -24161
B106: Net Cash Flow | C106: =IFERROR(C80+C94+C104,0) -> 384 | D106: =IFERROR(D80+D94+D104,0) -> -12228 | E106: =IFERROR(E80+E94+E104,0) -> -2670 | F106: =IFERROR(F80+F94+F104,0) -> -756 | G106: =IFERROR(G80+G94+G104,0) -> -3286 | H106: =IFERROR(H80+H94+H104,0) -> 6833 | I106: =IFERROR(I80+I94+I104,0) -> -8666 | J106: =IFERROR(J80+J94+J104,0) -> -11643 | ... L106: =IFERROR(L80+L94+L104,0) -> 9374

Sheet Doupond Analysis
B2: ='Data Sheet'!B1 -> INFOSYS LTD
B3: =CONCATENATE(" ", "(",VLOOKUP(B2,'List of Stock'!B3:D5442,3,1)," |","BSE Code: ",VLOOKUP(B2,'List of Stock'!B2:C5442,2,1)) -> (INFY |BSE Code: 500209
B4: =CONCATENATE(" ","INR "&'Data Sheet'!B8) -> INR 1476.8
B5: 52 Week (High - 1,982.80& Low - 1,307.00)
B8: About the Company
B9: Infosys Limited is an Indian multinational technology company that offers information technology, business consulting, and outsourcing services. Founded in 1981 by seven engineers, the company is headquartered in Bengaluru and considered one of the Big Six Indian IT companies. Infosys has also attracted controversies due to allegations of visa and tax fraud in the United States and for creating malfunctioning government websites.
B14: Financial Summary
B67: Return on Equity (ROE)
C68: ='Historical FS'!F3 -> 43555 | D68: ='Historical FS'!G3 -> 43921 | E68: ='Historical FS'!H3 -> 44286 | F68: ='Historical FS'!I3 -> 44651 | G68: ='Historical FS'!J3 -> 45016 | H68: ='Historical FS'!K3 -> 45382 | I68: ='Historical FS'!L3 -> 45747
B69: Net Profit | C69: ='Data Sheet'!E30 -> 15404 | D69: ='Data Sheet'!F30 -> 16594 | E69: ='Data Sheet'!G30 -> 19351 | F69: ='Data Sheet'!H30 -> 22110 | G69: ='Data Sheet'!I30 -> 24095 | H69: ='Data Sheet'!J30 -> 26233 | I69: ='Data Sheet'!K30 -> 26713
B70: Average ShareHolder Equity | C70: =('Data Sheet'!E57+'Data Sheet'!E58)+('Data Sheet'!D57+'Data Sheet'!D58)/2 -> 97409.5 | D70: =('Data Sheet'!F57+'Data Sheet'!F58)+('Data Sheet'!E57+'Data Sheet'!E58)/2 -> 97924 | E70: =('Data Sheet'!G57+'Data Sheet'!G58)+('Data Sheet'!F57+'Data Sheet'!F58)/2 -> 109076 | F70: =('Data Sheet'!H57+'Data Sheet'!H58)+('Data Sheet'!G57+'Data Sheet'!G58)/2 -> 113525.5 | G70: =('Data Sheet'!I57+'Data Sheet'!I58)+('Data Sheet'!H57+'Data Sheet'!H58)/2 -> 113082 | H70: =('Data Sheet'!J57+'Data Sheet'!J58)+('Data Sheet'!I57+'Data Sheet'!I58)/2 -> 125819.5 | I70: =('Data Sheet'!K57+'Data Sheet'!K58)+('Data Sheet'!J57+'Data Sheet'!J58)/2 -> 139876
B71: Return on Equity | C71: =C69/C70 -> 0.15813653 | D71: =D69/D70 -> 0.16945795 | E71: =E69/E70 -> 0.17740841 | F71: =F69/F70 -> 0.19475801 | G71: =G69/G70 -> 0.21307547 | H71: =H69/H70 -> 0.20849709 | I71: =I69/I70 -> 0.19097629
B73: ROE - Doupond Equation
C74: =C68 -> 43555 | D74: =D68 -> 43921 | E74: =E68 -> 44286 | F74: =F68 -> 44651 | G74: =G68 -> 45016 | H74: =H68 -> 45382 | I74: =I68 -> 45747
B75: =B69 -> Net Profit | C75: =C69 -> 15404 | D75: =D69 -> 16594 | E75: =E69 -> 19351 | F75: =F69 -> 22110 | G75: =G69 -> 24095 | H75: =H69 -> 26233 | I75: =I69 -> 26713
B76: Revenue | C76: ='Data Sheet'!E42 -> 37923 | D76: ='Data Sheet'!F42 -> 39315 | E76: ='Data Sheet'!G42 -> 40986 | F76: ='Data Sheet'!H42 -> 41764 | G76: ='Data Sheet'!I42 -> 40925 | H76: ='Data Sheet'!J42 -> 42279 | I76: ='Data Sheet'!K42 -> 44490
B77: Net Profit Margin (A) | C77: =C75/C76 -> 0.40619149 | D77: =D75/D76 -> 0.42207809 | E77: =E75/E76 -> 0.47213683 | F77: =F75/F76 -> 0.52940331 | G77: =G75/G76 -> 0.58875993 | H77: =H75/H76 -> 0.62047352 | I77: =I75/I76 -> 0.60042706
B79: Revenue | C79: =C76 -> 37923 | D79: =D76 -> 39315 | E79: =E76 -> 40986 | F79: =F76 -> 41764 | G79: =G76 -> 40925 | H79: =H76 -> 42279 | I79: =I76 -> 44490
B80: Average Total Asset | C80: =('Data Sheet'!E66+'Data Sheet'!D66)/2 -> 81707.5 | D80: =('Data Sheet'!F66+'Data Sheet'!E66)/2 -> 87933 | E80: =('Data Sheet'!G66+'Data Sheet'!F66)/2 -> 99655.5 | F80: =('Data Sheet'!H66+'Data Sheet'!G66)/2 -> 112120 | G80: =('Data Sheet'!I66+'Data Sheet'!H66)/2 -> 120662.5 | H80: =('Data Sheet'!J66+'Data Sheet'!I66)/2 -> 130978 | I80: =('Data Sheet'!K66+'Data Sheet'!J66)/2 -> 142577.5
B81: Assets Turnover Ratio (B) | C81: =C79/C80 -> 0.4641312 | D81: =D79/D80 -> 0.44710177 | E81: =E79/E80 -> 0.41127685 | F81: =F79/F80 -> 0.37249376 | G81: =G79/G80 -> 0.33916917 | H81: =H79/H80 -> 0.32279467 | I81: =I79/I80 -> 0.31204082
B83: =B80 -> Average Total Asset | C83: =C80 -> 81707.5 | D83: =D80 -> 87933 | E83: =E80 -> 99655.5 | F83: =F80 -> 112120 | G83: =G80 -> 120662.5 | H83: =H80 -> 130978 | I83: =I80 -> 142577.5
B84: =B70 -> Average ShareHolder Equity | C84: =C70 -> 97409.5 | D84: =D70 -> 97924 | E84: =E70 -> 109076 | F84: =F70 -> 113525.5 | G84: =G70 -> 113082 | H84: =H70 -> 125819.5 | I84: =I70 -> 139876
B85: Equity Multipler (C) | C85: =C83/C84 -> 0.83880422 | D85: =D83/D84 -> 0.8979719 | E85: =E83/E84 -> 0.91363361 | F85: =F83/F84 -> 0.98761952 | G85: =G83/G84 -> 1.0670354 | H85: =H83/H84 -> 1.0409992 | I85: =I83/I84 -> 1.0193135
B87: Return on Equity (A*B*C) | C87: =C77*C81*C85 -> 0.15813653 | D87: =D77*D81*D85 -> 0.16945795 | E87: =E77*E81*E85 -> 0.17740841 | F87: =F77*F81*F85 -> 0.19475801 | G87: =G77*G81*G85 -> 0.21307547 | H87: =H77*H81*H85 -> 0.20849709 | I87: =I77*I81*I85 -> 0.19097629
B89: Return on Assets
C90: =C68 -> 43555 | D90: =D68 -> 43921 | E90: =E68 -> 44286 | F90: =F68 -> 44651 | G90: =G68 -> 45016 | H90: =H68 -> 45382 | I90: =I68 -> 45747
B91: =B69 -> Net Profit | C91: =C69 -> 15404 | D91: =D69 -> 16594 | E91: =E69 -> 19351 | F91: =F69 -> 22110 | G91: =G69 -> 24095 | H91: =H69 -> 26233 | I91: =I69 -> 26713
B92: =B80 -> Average Total Asset | C92: =C80 -> 81707.5 | D92: =D80 -> 87933 | E92: =E80 -> 99655.5 | F92: =F80 -> 112120 | G92: =G80 -> 120662.5 | H92: =H80 -> 130978 | I92: =I80 -> 142577.5
B93: Return on Assets | C93: =C91/C92 -> 0.18852615 | D93: =D91/D92 -> 0.18871186 | E93: =E91/E92 -> 0.19417895 | F93: =F91/F92 -> 0.19719943 | G93: =G91/G92 -> 0.19968922 | H93: =H91/H92 -> 0.20028554 | I93: =I91/I92 -> 0.18735775
B95: ROA - Duopond Equation
C96: =C90 -> 43555 | D96: =D90 -> 43921 | E96: =E90 -> 44286 | F96: =F90 -> 44651 | G96: =G90 -> 45016 | H96: =H90 -> 45382 | I96: =I90 -> 45747
B97: =B91 -> Net Profit | C97: =C91 -> 15404 | D97: =D91 -> 16594 | E97: =E91 -> 19351 | F97: =F91 -> 22110 | G97: =G91 -> 24095 | H97: =H91 -> 26233 | I97: =I91 -> 26713
B98: Revenue | C98: =C79 -> 37923 | D98: =D79 -> 39315 | E98: =E79 -> 40986 | F98: =F79 -> 41764 | G98: =G79 -> 40925 | H98: =H79 -> 42279 | I98: =I79 -> 44490
B99: Net Profit Margin (A) | C99: =C97/C98 -> 0.40619149 | D99: =D97/D98 -> 0.42207809 | E99: =E97/E98 -> 0.47213683 | F99: =F97/F98 -> 0.52940331 | G99: =G97/G98 -> 0.58875993 | H99: =H97/H98 -> 0.62047352 | I99: =I97/I98 -> 0.60042706
B101: Revenue | C101: =C98 -> 37923 | D101: =D98 -> 39315 | E101: =E98 -> 40986 | F101: =F98 -> 41764 | G101: =G98 -> 40925 | H101: =H98 -> 42279 | I101: =I98 -> 44490
B102: Average Total Asset | C102: =C92 -> 81707.5 | D102: =D92 -> 87933 | E102: =E92 -> 99655.5 | F102: =F92 -> 112120 | G102: =G92 -> 120662.5 | H102: =H92 -> 130978 | I102: =I92 -> 142577.5
B103: Assets Turnover Ratio (B) | C103: =C101/C102 -> 0.4641312 | D103: =D101/D102 -> 0.44710177 | E103: =E101/E102 -> 0.41127685 | F103: =F101/F102 -> 0.37249376 | G103: =G101/G102 -> 0.33916917 | H103: =H101/H102 -> 0.32279467 | I103: =I101/I102 -> 0.31204082
B105: Return on Assets (A*B) | C105: =C103*C99 -> 0.18852615 | D105: =D103*D99 -> 0.18871186 | E105: =E103*E99 -> 0.19417895 | F105: =F103*F99 -> 0.19719943 | G105: =G103*G99 -> 0.19968922 | H105: =H103*H99 -> 0.20028554 | I105: =I103*I99 -> 0.18735775

Sheet Altman Z Score
B2: ='Data Sheet'!B1 -> INFOSYS LTD
B3: =CONCATENATE(" ", "(",VLOOKUP(B2,'List of Stock'!B3:D5442,3,1)," |","BSE Code: ",VLOOKUP(B2,'List of Stock'!B2:C5442,2,1)) -> (INFY |BSE Code: 500209
B4: =CONCATENATE(" ","INR "&'Data Sheet'!B8) -> INR 1476.8
B5: 52 Week (High - 1,982.80& Low - 1,307.00)
B8: Altman Z Score Analysis
B9: Infosys Limited is an Indian multinational technology company that offers information technology, business consulting, and outsourcing services. Founded in 1981 by seven engineers, the company is headquartered in Bengaluru and considered one of the Big Six Indian IT companies. Infosys has also attracted controversies due to allegations of visa and tax fraud in the United States and for creating malfunctioning government websites.
B13: Financial Summary
B66: Working Capital/ Total Assets
C67: ='Historical FS'!F3 -> 43555 | D67: ='Historical FS'!G3 -> 43921 | E67: ='Historical FS'!H3 -> 44286 | F67: ='Historical FS'!I3 -> 44651 | G67: ='Historical FS'!J3 -> 45016 | H67: ='Historical FS'!K3 -> 45382 | I67: ='Historical FS'!L3 -> 45747
B68: Working Capital | C68: ='Data Sheet'!E65-'Data Sheet'!E60 -> 36589 | D68: ='Data Sheet'!F65-'Data Sheet'!F60 -> 36548 | E68: ='Data Sheet'!G65-'Data Sheet'!G60 -> 41044 | F68: ='Data Sheet'!H65-'Data Sheet'!H60 -> 34284 | G68: ='Data Sheet'!I65-'Data Sheet'!I60 -> 34715 | H68: ='Data Sheet'!J65-'Data Sheet'!J60 -> 43937 | I68: ='Data Sheet'!K65-'Data Sheet'!K60 -> 48729
B69: Total Assets | C69: ='Data Sheet'!E75 -> 84066 | D69: ='Data Sheet'!F75 -> 91800 | E69: ='Data Sheet'!G75 -> 107511 | F69: ='Data Sheet'!H75 -> 116729 | G69: ='Data Sheet'!I75 -> 124596 | H69: ='Data Sheet'!J75 -> 137360 | I69: ='Data Sheet'!K75 -> 147795
B70: Working Capital/ Total Assets (A) | C70: =C68/C69 -> 0.43524136 | D70: =D68/D69 -> 0.39812636 | E70: =E68/E69 -> 0.38176559 | F70: =F68/F69 -> 0.29370593 | G70: =G68/G69 -> 0.2786205 | H70: =H68/H69 -> 0.3198675 | I70: =I68/I69 -> 0.32970669
B72: Retained Earnings/ Total Assets
C73: =C67 -> 43555 | D73: =D67 -> 43921 | E73: =E67 -> 44286 | F73: =F67 -> 44651 | G73: =G67 -> 45016 | H73: =H67 -> 45382 | I73: =I67 -> 45747
B74: Retained Earnings | C74: ='Historical FS'!F36*'Historical FS'!F38*'Historical FS'!F44 -> 0 | D74: ='Historical FS'!G36*'Historical FS'!G38*'Historical FS'!G44 -> 0 | E74: ='Historical FS'!H36*'Historical FS'!H38*'Historical FS'!H44 -> 0 | F74: ='Historical FS'!I36*'Historical FS'!I38*'Historical FS'!I44 -> 0 | G74: ='Historical FS'!J36*'Historical FS'!J38*'Historical FS'!J44 -> 0 | H74: ='Historical FS'!K36*'Historical FS'!K38*'Historical FS'!K44 -> 0 | I74: ='Historical FS'!L36*'Historical FS'!L38*'Historical FS'!L44 -> 0
B75: Total Assets | C75: =C$69 -> 84066 | D75: =D$69 -> 91800 | E75: =E$69 -> 107511 | F75: =F$69 -> 116729 | G75: =G$69 -> 124596 | H75: =H$69 -> 137360 | I75: =I$69 -> 147795
B76: Retained Earnings/ Total Assets (B) | C76: =C74/C75 -> 0 | D76: =D74/D75 -> 0 | E76: =E74/E75 -> 0 | F76: =F74/F75 -> 0 | G76: =G74/G75 -> 0 | H76: =H74/H75 -> 0 | I76: =I74/I75 -> 0
B78: EBIT/ Total Assets
C79: =C73 -> 43555 | D79: =D73 -> 43921 | E79: =E73 -> 44286 | F79: =F73 -> 44651 | G79: =G73 -> 45016 | H79: =H73 -> 45382 | I79: =I73 -> 45747
B80: EBIT | C80: ='Historical FS'!F18-'Historical FS'!F24 -> 18159 | D80: ='Historical FS'!G18-'Historical FS'!G24 -> 19374 | E80: ='Historical FS'!H18-'Historical FS'!H24 -> 24622 | F80: ='Historical FS'!I18-'Historical FS'!I24 -> 28015 | G80: ='Historical FS'!J18-'Historical FS'!J24 -> 30905 | H80: ='Historical FS'!K18-'Historical FS'!K24 -> 31747 | I80: ='Historical FS'!L18-'Historical FS'!L24 -> 34424
B81: Total Asset | C81: =C$69 -> 84066 | D81: =D$69 -> 91800 | E81: =E$69 -> 107511 | F81: =F$69 -> 116729 | G81: =G$69 -> 124596 | H81: =H$69 -> 137360 | I81: =I$69 -> 147795
B82: EBIT/ Total Assets (C) | C82: =C80/C81 -> 0.21600885 | D82: =D80/D81 -> 0.21104575 | E82: =E80/E81 -> 0.22901843 | F82: =F80/F81 -> 0.24000034 | G82: =G80/G81 -> 0.24804167 | H82: =H80/H81 -> 0.2311226 | I82: =I80/I81 -> 0.23291722
B84: Market Cap/ Long Term Liabilities
C85: =C79 -> 43555 | D85: =D79 -> 43921 | E85: =E79 -> 44286 | F85: =F79 -> 44651 | G85: =G79 -> 45016 | H85: =H79 -> 45382 | I85: =I79 -> 45747
B86: Market Cap | C86: ='Data Sheet'!E70*'Data Sheet'!E90/10000000 -> 322529.97 | D86: ='Data Sheet'!F70*'Data Sheet'!F90/10000000 -> 272044.32 | E86: ='Data Sheet'!G70*'Data Sheet'!G90/10000000 -> 580757.21 | F86: ='Data Sheet'!H70*'Data Sheet'!H90/10000000 -> 799544.67 | G86: ='Data Sheet'!I70*'Data Sheet'!I90/10000000 -> 590655.51 | H86: ='Data Sheet'!J70*'Data Sheet'!J90/10000000 -> 620185.3 | I86: ='Data Sheet'!K70*'Data Sheet'!K90/10000000 -> 650815.72
B87: Long Term Liabilities | C87: 0 | D87: ='Data Sheet'!F59 -> 4633 | E87: ='Data Sheet'!G59 -> 5325 | F87: ='Data Sheet'!H59 -> 5474 | G87: ='Data Sheet'!I59 -> 8299 | H87: ='Data Sheet'!J59 -> 8359 | I87: ='Data Sheet'!K59 -> 8227
B88: EBIT/ Total Assets (D) | D88: =D86/D87 -> 58.718825 | E88: =E86/E87 -> 109.06239 | F88: =F86/F87 -> 146.06223 | G88: =G86/G87 -> 71.17189 | H88: =H86/H87 -> 74.19372 | I88: =I86/I87 -> 79.107295
B90: Sales/ Total Assets
C91: =C67 -> 43555 | D91: =D67 -> 43921 | E91: =E67 -> 44286 | F91: =F67 -> 44651 | G91: =G67 -> 45016 | H91: =H67 -> 45382 | I91: =I67 -> 45747
B92: Total Sales | C92: ='Data Sheet'!E17 -> 82675 | D92: ='Data Sheet'!F17 -> 90791 | E92: ='Data Sheet'!G17 -> 100472 | F92: ='Data Sheet'!H17 -> 121641 | G92: ='Data Sheet'!I17 -> 146767 | H92: ='Data Sheet'!J17 -> 153670 | I92: ='Data Sheet'!K17 -> 162990
B93: =B81 -> Total Asset | C93: =C$69 -> 84066 | D93: =D$69 -> 91800 | E93: =E$69 -> 107511 | F93: =F$69 -> 116729 | G93: =G$69 -> 124596 | H93: =H$69 -> 137360 | I93: =I$69 -> 147795
B94: Sales/ Total Assets (E) | C94: =C92/C93 -> 0.98345348 | D94: =D92/D93 -> 0.98900871 | E94: =E92/E93 -> 0.93452763 | F94: =F92/F93 -> 1.0420804 | G94: =G92/G93 -> 1.1779431 | H94: =H92/H93 -> 1.1187391 | I94: =I92/I93 -> 1.1028113
B96: Altman's Z Score
C97: =C91 -> 43555 | D97: =D91 -> 43921 | E97: =E91 -> 44286 | F97: =F91 -> 44651 | G97: =G91 -> 45016 | H97: =H91 -> 45382 | I97: =I91 -> 45747
B98: Final Score | C98: =(C70*1.2)+(C76*1.4)+(C82*3.3)+(C88*0.6)+(C94*1) -> 2.2185723 | D98: =(D70*1.2)+(D76*1.4)+(D82*3.3)+(D88*0.6)+(D94*1) -> 37.394507 | E98: =(E70*1.2)+(E76*1.4)+(E82*3.3)+(E88*0.6)+(E94*1) -> 67.58584 | F98: =(F70*1.2)+(F76*1.4)+(F82*3.3)+(F88*0.6)+(F94*1) -> 89.823869 | G98: =(G70*1.2)+(G76*1.4)+(G82*3.3)+(G88*0.6)+(G94*1) -> 45.033959 | H98: =(H70*1.2)+(H76*1.4)+(H82*3.3)+(H88*0.6)+(H94*1) -> 46.781517 | I98: =(I70*1.2)+(I76*1.4)+(I82*3.3)+(I88*0.6)+(I94*1) -> 49.731463
B99: Financial Stability | C99: =IF(C98<1.81,"Distressed",IF(C98>3,"Strong","Grey Zone")) -> Grey Zone | D99: =IF(D98<1.81,"Distressed",IF(D98>3,"Strong","Grey Zone")) -> Strong | E99: =IF(E98<1.81,"Distressed",IF(E98>3,"Strong","Grey Zone")) -> Strong | F99: =IF(F98<1.81,"Distressed",IF(F98>3,"Strong","Grey Zone")) -> Strong | G99: =IF(G98<1.81,"Distressed",IF(G98>3,"Strong","Grey Zone")) -> Strong | H99: =IF(H98<1.81,"Distressed",IF(H98>3,"Strong","Grey Zone")) -> Strong | I99: =IF(I98<1.81,"Distressed",IF(I98>3,"Strong","Grey Zone")) -> Strong

Sheet Data>

Sheet List of Stock
B2: COMPANY_NAME | C2: BSE | D2: NSE | E2: Industry
B3: 20 MICRONS LTD | C3: 533022 | D3: 20MICRONS | E3: Mining
B4: 21ST CENTURY MANAGEMENT SERVICES LTD | C4: 526921 | D4: 21STCENMGM | E4: Other Financial Services
B5: 3I INFOTECH LTD | C5: 532628 | D5: 3IINFOTECH | E5: IT Consulting & Software
B6: 3M (INDIA) LTD | C6: 523395 | D6: 3M(INDIA) | E6: Diversified
B7: 3M INDIA LTD | C7: 523395 | D7: 3MINDIA | E7: Diversified
B8: 3P LAND HOLDINGS LTD | C8: 516092 | D8: 3PLAND | E8: Paper & Paper Products
B9: 5PAISA CAPITAL LTD | C9: 540776 | D9: 5PAISA | E9: Other Financial Services
B10: 63 MOONS TECHNOLOGIES LTD | C10: 526881 | D10: 63MOONS | E10: IT Consulting & Software
B11: 7NR RETAIL LTD | C11: 540615 | D11: Not Listed | E11: Specialty Retail
B12: 7SEAS ENTERTAINMENT LTD | C12: 540874 | D12: Not Listed | E12: Movies & Entertainment
B13: 8K MILES SOFTWARE SERVICES LTD | C13: 512161 | D13: 8KMILES | E13: Internet Software & Services
B14: A & M FEBCON LTD | C14: 540697 | D14: Not Listed | E14: Industrial Machinery
B15: A AND M JUMBO BAGS LTD | C15: Not Listed | D15: AMJUMBO | E15: SME
B16: A INFRASTRUCTURE LTD | C16: 539620 | D16: Not Listed | E16: Cement & Cement Products
B17: A K SPINTEX LTD | C17: 539300 | D17: Not Listed | E17: Textiles
B18: A K CAPITAL SERVICES LTD | C18: 530499 | D18: Not Listed | E18: Finance (including NBFCs)
B19: A.F. Enterprises Ltd | C19: 538351 | D19: AFEL | E19: Investment Companies
B20: A-1 ACID LTD | C20: 542012 | D20: Not Listed | E20: Comm.Trading & Distribution
B21: A2Z INFRA ENGINEERING LTD | C21: 533292 | D21: A2ZINFRA | E21: Utilities:Non-Elec.
B22: AADHAAR VENTURES (INDIA) LTD | C22: 531611 | D22: Not Listed | E22: Finance (including NBFCs)
B23: AADHAAR VENTURES INDIA LTD | C23: 531611 | D23: Not Listed | E23: Finance (including NBFCs)
B24: AAKASH EXPLORATION SERVICES LTD | C24: Not Listed | D24: AAKASH | E24: SME
B25: AANANDA LAKSHMI SPINNING MILLS LTD | C25: 539096 | D25: Not Listed | E25: Textiles
B26: AANCHAL ISPAT LTD | C26: 538812 | D26: Not Listed | E26: Iron & Steel/Interm.Products
B27: AAR COMMERCIAL COMPANY LTD | C27: 539632 | D27: Not Listed | E27: Distributors
B28: Aar Shyam India Investment Company Ltd | C28: 542377 | D28: AARSHYAM | E28: Finance (including NBFCs)
B29: AAREY DRUGS & PHARMACEUTICALS LTD | C29: 524412 | D29: Not Listed | E29: Pharmaceuticals
B30: AARON INDUSTRIES LTD | C30: Not Listed | D30: AARON | E30: SME
B31: Aartech Solonics Ltd | C31: 542580 | D31: AARTECH | E31: Heavy Electrical Equipment
B32: AARTI DRUGS LTD | C32: 524348 | D32: AARTIDRUGS | E32: Pharmaceuticals
B33: AARTI INDUSTRIES LTD | C33: 524208 | D33: AARTIIND | E33: Commodity Chemicals
B34: AARV INFRATEL LTD | C34: 526488 | D34: Not Listed | E34: Textiles
B35: AARVEE DENIMS & EXPORTS LTD | C35: 514274 | D35: AARVEEDEN | E35: Textiles
B36: AARVI ENCON LTD | C36: Not Listed | D36: AARVI | E36: SME
B37: AASHEE INFOTECH LTD | C37: 519319 | D37: Not Listed | E37: Internet Software & Services
B38: AASWA TRADING & EXPORTS LTD | C38: 512038 | D38: Not Listed | E38: Comm.Trading & Distribution
B39: AAVAS FINANCIERS LTD | C39: 541988 | D39: AAVAS | E39: Housing Finance
B40: AAYUSH FOOD AND HERBS LTD | C40: 539528 | D40: Not Listed | E40: Packaged Foods
B41: ABAN OFFSHORE LTD | C41: 523204 | D41: ABAN | E41: Exploration & Production
B42: ABANS ENTERPRISES LTD | C42: 512165 | D42: Not Listed | E42: Comm.Trading & Distribution
B43: ABB INDIA LTD | C43: 500002 | D43: ABB | E43: Heavy Electrical Equipment
B44: ABBOTT (INDIA) LTD | C44: 500488 | D44: ABBOT(INDIA) | E44: Pharmaceuticals
B45: ABBOTT INDIA LTD | C45: 500488 | D45: ABBOTINDIA | E45: Pharmaceuticals
B46: ABC (INDIA) LTD | C46: 520123 | D46: Not Listed | E46: Surface Transportation
B47: ABC GAS INTERNATIONAL LTD | C47: 513119 | D47: Not Listed | E47: Copper
B48: ABC INDIA LTD | C48: 520123 | D48: Not Listed | E48: Surface Transportation
... B56: ABIRAMI FINANCIAL SERVICES INDIA LTD | C56: 511756 | D56: Not Listed | E56: Finance (including NBFCs)
B57: ABM INTERNATIONAL LTD | C57: Not Listed | D57: ABMINTLTD | E57: Others
B58: ABM KNOWLEDGEWARE LTD | C58: 531161 | D58: Not Listed | E58: IT Software Products
B59: ACC LTD | C59: 500410 | D59: ACC | E59: Cement & Cement Products
B60: ACCEL LTD | C60: 517494 | D60: Not Listed | E60: Storage Media & Peripherals
B61: ACCELYA KALE SOLUTIONS LTD | C61: 532268 | D61: ACCELYA | E61: IT Consulting & Software
B62: ACCORD SYNERGY LTD | C62: Not Listed | D62: ACCORD | E62: SME
B63: ACCURACY SHIPPING LTD | C63: Not Listed | D63: ACCURACY | E63: SME
B64: ACE EDUTREND LTD | C64: 530093 | D64: Not Listed | E64: Education
B65: ACE INTEGRATED SOLUTIONS LTD | C65: Not Listed | D65: ACEINTEG | E65: SME
B66: ACE MEN ENGG WORKS LTD | C66: 539661 | D66: Not Listed | E66: Distributors
B67: ACE SOFTWARE EXPORTS LTD | C67: 531525 | D67: Not Listed | E67: IT Software Products
B68: Achal Investments Ltd | C68: 538570 | D68: ACHAL | E68: Other Financial Services
B69: ACI INFOCOM LTD | C69: 517356 | D69: Not Listed | E69: Storage Media & Peripherals
B70: ACKNIT INDUSTRIES LTD | C70: 530043 | D70: Not Listed | E70: Other Apparels & Accessories
B71: ACME RESOURCES LTD | C71: 539391 | D71: Not Listed | E71: Finance (including NBFCs)
B72: ACROW INDIA LTD. | C72: 513149 | D72: ACROW | E72: Iron &amp; Steel Products
B73: ACRYSIL LTD | C73: 524091 | D73: Not Listed | E73: Plastic Products
B74: ACTION CONSTRUCTION EQUIPMENT LTD | C74: 532762 | D74: ACE | E74: Transport Related Services
B75: ACTION FINANCIAL SERVICES (INDIA) LTD | C75: 511706 | D75: Not Listed | E75: Other Financial Services
B76: ACTION FINANCIAL SERVICES INDIA LTD | C76: 511706 | D76: Not Listed | E76: Other Financial Services
B77: ACTIVE CLOTHING CO LTD | C77: 541144 | D77: Not Listed | E77: Other Apparels & Accessories
... B135: AGRI-TECH INDIA LTD | C135: 537292 | D135: AGRITECH | E135: Other Agricultural Products
B136: AGRO PHOS (INDIA) LTD | C136: Not Listed | D136: AGROPHOS | E136: SME
B137: AGRO PHOS INDIA LTD | C137: Not Listed | D137: AGROPHOS | E137: SME
B138: AGRO TECH FOODS LTD | C138: 500215 | D138: ATFL | E138: Other Agricultural Products
B139: AHIMSA INDUSTRIES LTD | C139: Not Listed | D139: AHIMSA | E139: SME
B140: AHLADA ENGINEERS LTD | C140: Not Listed | D140: AHLADA | E140: SME
B141: AHLUWALIA CONTRACTS (INDIA) LTD | C141: 532811 | D141: AHLUCONT | E141: Realty
B142: AHLUWALIA CONTRACTS INDIA LTD | C142: 532811 | D142: AHLUCONT | E142: Realty
B143: AHMEDABAD STEELCRAFT LTD | C143: 522273 | D143: Not Listed | E143: Iron & Steel/Interm.Products
B144: AI CHAMPDANY INDUSTRIES LTD | C144: 532806 | D144: Not Listed | E144: Jute & Jute Products
B145: AIA ENGINEERING LTD | C145: 532683 | D145: AIAENG | E145: Other Industrial Goods
B146: AIMCO PESTICIDES LTD | C146: 524288 | D146: Not Listed | E146: Agrochemicals
B147: AIRAN LTD | C147: Not Listed | D147: AIRAN | E147: SME
B148: AIRO LAM LTD | C148: Not Listed | D148: AIROLAM | E148: SME
B149: AISHWARYA TELECOM LTD | C149: 532975 | D149: Not Listed | E149: Telecom Equipment
B150: AJANTA PHARMA LTD | C150: 532331 | D150: AJANTPHARM | E150: Pharmaceuticals
B151: AJANTA SOYA LTD | C151: 519216 | D151: Not Listed | E151: Edible Oils
B152: AJCON GLOBAL SERVICES LTD | C152: 511692 | D152: Not Listed | E152: Other Financial Services
B153: AJEL LTD | C153: 530713 | D153: Not Listed | E153: IT Consulting & Software
B154: AJMERA REALTY & INFRA (INDIA) LTD | C154: 513349 | D154: AJMERA | E154: Realty
B155: AJMERA REALTY & INFRA INDIA LTD | C155: 513349 | D155: AJMERA | E155: Realty
B156: AJOONI BIOTECH LTD | C156: Not Listed | D156: AJOONI | E156: SME
B157: AJWA FUN WORLD & RESORT LTD | C157: 526628 | D157: Not Listed | E157: Other Leisure Facilities
B158: AKAR AUTO INDUSTRIES LTD | C158: 530621 | D158: Not Listed | E158: Industrial Machinery
B159: AKASH INFRA PROJECTS LTD | C159: Not Listed | D159: AKASH | E159: SME
B160: AKASHDEEP METAL INDUSTRIES LTD | C160: 538778 | D160: Not Listed | E160: Finance (including NBFCs)
B161: AKG EXIM LTD | C161: Not Listed | D161: AKG | E161: SME
B162: AKI (INDIA) LTD | C162: 542020 | D162: Not Listed | E162: Other Apparels & Accessories
B163: AKI INDIA LTD | C163: 542020 | D163: Not Listed | E163: Other Apparels & Accessories
B164: AKM LACE AND EMBROTEX LTD | C164: 540718 | D164: Not Listed | E164: Textiles
B165: AKME STAR HOUSING FINANCE LTD | C165: 539017 | D165: Not Listed | E165: Housing Finance
...

Sheet Data Sheet
A1: COMPANY NAME | B1: INFOSYS LTD
A2: LATEST VERSION | B2: 2.1 | E2: PLEASE DO NOT MAKE ANY CHANGES TO THIS SHEET
A3: CURRENT VERSION | B3: 2.1
A5: META
A6: Number of shares | B6: =IF(B9>0, B9/B8, 0) -> 415.44013
A7: Face Value | B7: 5
A8: Current Price | B8: 1476.8
A9: Market Capitalization | B9: 613521.99
A15: PROFIT & LOSS
A16: Report Date | B16: 42460 | C16: 42825 | D16: 43190 | E16: 43555 | F16: 43921 | G16: 44286 | H16: 44651 | I16: 45016 | J16: 45382 | K16: 45747
A17: Sales | B17: 62441 | C17: 68484 | D17: 70522 | E17: 82675 | F17: 90791 | G17: 100472 | H17: 121641 | I17: 146767 | J17: 153670 | K17: 162990
A18: Raw Material Cost
A19: Change in Inventory
A20: Power and Fuel | B20: 217 | C20: 228 | D20: 207 | E20: 221 | F20: 229 | G20: 143 | H20: 132 | I20: 176 | J20: 199 | K20: 222
A21: Other Mfr. Exp | B21: 5860 | C21: 6712 | D21: 7286 | E21: 9902 | F21: 11086 | G21: 12800 | H21: 20690 | I21: 26330 | J21: 27195 | K21: 30395
A22: Employee Cost | B22: 34415 | C22: 37669 | D22: 38902 | E22: 45323 | F22: 50895 | G22: 55547 | H22: 63997 | I22: 78374 | J22: 82636 | K22: 85968
A23: Selling and admin | B23: 4441 | C23: 4584 | D23: 4585 | E23: 5553 | F23: 5375 | G23: 3194 | H23: 4305 | I23: 5300 | J23: 5705 | K23: 6039
A24: Other Expenses | B24: 429 | C24: 687 | D24: 720 | E24: 1506 | F24: 939 | G24: 899 | H24: 1026 | I24: 1457 | J24: 1510 | K24: 1130
A25: Other Income | B25: 3120 | C25: 3050 | D25: 3311 | E25: 2882 | F25: 2803 | G25: 2201 | H25: 2295 | I25: 2701 | J25: 4711 | K25: 3600
A26: Depreciation | B26: 1459 | C26: 1703 | D26: 1863 | E26: 2011 | F26: 2893 | G26: 3267 | H26: 3476 | I26: 4225 | J26: 4678 | K26: 4812
A27: Interest | F27: 170 | G27: 195 | H27: 200 | I27: 284 | J27: 470 | K27: 416
A28: Profit before tax | B28: 18740 | C28: 19951 | D28: 20270 | E28: 21041 | F28: 22007 | G28: 26628 | H28: 30110 | I28: 33322 | J28: 35988 | K28: 37608
A29: Tax | B29: 5251 | C29: 5598 | D29: 4241 | E29: 5631 | F29: 5368 | G29: 7205 | H29: 7964 | I29: 9214 | J29: 9740 | K29: 10858
A30: Net profit | B30: 13489 | C30: 14353 | D30: 16029 | E30: 15404 | F30: 16594 | G30: 19351 | H30: 22110 | I30: 24095 | J30: 26233 | K30: 26713
A31: Dividend Amount | B31: 5548.4 | C31: 5891.6 | D31: 9465.6 | E31: 9222.5 | F31: 7427 | G31: 11469.6 | H31: 13007.6 | I31: 14069.2 | J31: 19053.2 | K31: 17827.8
A33: EBITDA | B33: =+B26+B27+B29+B30 -> 20199 | C33: =+C26+C27+C29+C30 -> 21654 | D33: =+D26+D27+D29+D30 -> 22133 | E33: =+E26+E27+E29+E30 -> 23046 | F33: =+F26+F27+F29+F30 -> 25025 | G33: =+G26+G27+G29+G30 -> 30018 | H33: =+H26+H27+H29+H30 -> 33750 | I33: =+I26+I27+I29+I30 -> 37818 | ... K33: =+K26+K27+K29+K30 -> 42799
A40: Quarters
A41: Report Date | B41: 45107 | C41: 45199 | D41: 45291 | E41: 45382 | F41: 45473 | G41: 45565 | H41: 45657 | I41: 45747 | J41: 45838 | K41: 45930
A42: Sales | B42: 37933 | C42: 38994 | D42: 38821 | E42: 37923 | F42: 39315 | G42: 40986 | H42: 41764 | I42: 40925 | J42: 42279 | K42: 44490
A43: Expenses | B43: 28869 | C43: 29554 | D43: 29684 | E43: 29139 | F43: 29878 | G43: 31177 | H43: 31649 | I43: 31051 | J43: 32336 | K43: 33955
A44: Other Income | B44: 561 | C44: 632 | D44: 789 | E44: 2729 | F44: 838 | G44: 712 | H44: 859 | I44: 1190 | J44: 1042 | K44: 982
A45: Depreciation | B45: 1173 | C45: 1166 | D45: 1176 | E45: 1163 | F45: 1149 | G45: 1160 | H45: 1203 | I45: 1299 | J45: 1140 | K45: 1182
A46: Interest | B46: 90 | C46: 138 | D46: 131 | E46: 110 | F46: 105 | G46: 108 | H46: 101 | I46: 102 | J46: 105 | K46: 106
A47: Profit before tax | B47: 8362 | C47: 8768 | D47: 8619 | E47: 10240 | F47: 9021 | G47: 9253 | H47: 9670 | I47: 9663 | J47: 9740 | K47: 10229
A48: Tax | B48: 2417 | C48: 2553 | D48: 2506 | E48: 2265 | F48: 2647 | G48: 2737 | H48: 2848 | I48: 2625 | J48: 2816 | K48: 2854
A49: Net profit | B49: 5945 | C49: 6212 | D49: 6106 | E49: 7969 | F49: 6368 | G49: 6506 | H49: 6806 | I49: 7033 | J49: 6921 | K49: 7364
A50: Operating Profit | B50: 9064 | C50: 9440 | D50: 9137 | E50: 8784 | F50: 9437 | G50: 9809 | H50: 10115 | I50: 9874 | J50: 9943 | K50: 10535
A52: EBITDA | B52: =+B45+B46+B48+B49 -> 9625 | C52: =+C45+C46+C48+C49 -> 10069 | D52: =+D45+D46+D48+D49 -> 9919 | E52: =+E45+E46+E48+E49 -> 11507 | F52: =+F45+F46+F48+F49 -> 10269 | G52: =+G45+G46+G48+G49 -> 10511 | H52: =+H45+H46+H48+H49 -> 10958 | I52: =+I45+I46+I48+I49 -> 11059 | ... K52: =+K45+K46+K48+K49 -> 11506
A55: BALANCE SHEET
A56: Report Date | B56: 42460 | C56: 42825 | D56: 43190 | E56: 43555 | F56: 43921 | G56: 44286 | H56: 44651 | I56: 45016 | J56: 45382 | K56: 45747
A57: Equity Share Capital | B57: 1144 | C57: 1144 | D57: 1088 | E57: 2170 | F57: 2122 | G57: 2124 | H57: 2098 | I57: 2069 | J57: 2071 | K57: 2073
A58: Reserves | B58: 60600 | C58: 67838 | D58: 63835 | E58: 62778 | F58: 63328 | G58: 74227 | H58: 73252 | I58: 73338 | J58: 86045 | K58: 93745
A59: Borrowings | F59: 4633 | G59: 5325 | H59: 5474 | I59: 8299 | J59: 8359 | K59: 8227
A60: Other Liabilities | B60: 13354 | C60: 14166 | D60: 14426 | E60: 19118 | F60: 21717 | G60: 25835 | H60: 35905 | I60: 40890 | J60: 40885 | K60: 43750
A61: Total | B61: 75098 | C61: 83148 | D61: 79349 | E61: 84066 | F61: 91800 | G61: 107511 | H61: 116729 | I61: 124596 | J61: 137360 | K61: 147795
A62: Net Block | B62: 13386 | C62: 14179 | D62: 12574 | E62: 15710 | F62: 23789 | G62: 25505 | H62: 25800 | I62: 29225 | J62: 27622 | K62: 30961
A63: Capital Work in Progress | B63: 960 | C63: 1365 | D63: 1606 | E63: 1388 | F63: 954 | G63: 922 | H63: 416 | I63: 288 | J63: 293 | K63: 814
A64: Investments | B64: 1892 | C64: 16423 | D64: 12163 | E64: 11261 | F64: 8792 | G64: 14205 | H64: 20324 | I64: 19478 | J64: 24623 | K64: 23541
A65: Other Assets | B65: 58860 | C65: 51181 | D65: 53006 | E65: 55707 | F65: 58265 | G65: 66879 | H65: 70189 | I65: 75605 | J65: 84822 | K65: 92479
A66: Total | B66: 75098 | C66: 83148 | D66: 79349 | E66: 84066 | F66: 91800 | G66: 107511 | H66: 116729 | I66: 124596 | J66: 137360 | K66: 147795
A67: Receivables | B67: 11330 | C67: 12322 | D67: 13142 | E67: 14827 | F67: 18487 | G67: 19294 | H67: 22698 | I67: 25424 | J67: 30193 | K67: 31158
A68: Inventory
A69: Cash & Bank | B69: 32697 | C69: 22625 | D69: 19818 | E69: 19568 | F69: 18649 | G69: 24714 | H69: 17472 | I69: 12173 | J69: 14786 | K69: 24455
A70: No. of Equity Shares | B70: 2285621088 | C70: 2285655150 | D70: 2173312301 | E70: 4335954462 | F70: 4240753210 | G70: 4245146114 | H70: 4193012929 | I70: 4136387925 | J70: 4139950635 | K70: 4143607528
A71: New Bonus Shares | B71: 1148472332 | E71: 2184191490
A72: Face value | B72: 5 | C72: 5 | D72: 5 | E72: 5 | F72: 5 | G72: 5 | H72: 5 | I72: 5 | J72: 5 | K72: 5
A74: Other Assets | B74: =B65-SUM(B67:B69) -> 14833 | C74: =C65-SUM(C67:C69) -> 16234 | D74: =D65-SUM(D67:D69) -> 20046 | E74: =E65-SUM(E67:E69) -> 21312 | F74: =F65-SUM(F67:F69) -> 21129 | G74: =G65-SUM(G67:G69) -> 22871 | H74: =H65-SUM(H67:H69) -> 30019 | I74: =I65-SUM(I67:I69) -> 38008 | ... K74: =K65-SUM(K67:K69) -> 36866
A75: Total Asset | B75: =B66 -> 75098 | C75: =C66 -> 83148 | D75: =D66 -> 79349 | E75: =E66 -> 84066 | F75: =F66 -> 91800 | G75: =G66 -> 107511 | H75: =H66 -> 116729 | I75: =I66 -> 124596 | ... K75: =K66 -> 147795
A80: CASH FLOW:
A81: Report Date | B81: 42460 | C81: 42825 | D81: 43190 | E81: 43555 | F81: 43921 | G81: 44286 | H81: 44651 | I81: 45016 | J81: 45382 | K81: 45747
A82: Cash from Operating Activity | B82: 10028 | C82: 11531 | D82: 13218 | E82: 14841 | F82: 17003 | G82: 23224 | H82: 23885 | I82: 22467 | J82: 25210 | K82: 35694
A83: Cash from Investing Activity | B83: -885 | C83: -14664 | D83: 4533 | E83: -632 | F83: -331 | G83: -7373 | H83: -6485 | I83: -1071 | J83: -5093 | K83: -1864
A84: Cash from Financing Activity | B84: -6813 | C84: -6939 | D84: -20505 | E84: -14512 | F84: -17591 | G84: -9786 | H84: -24642 | I84: -26695 | J84: -17504 | K84: -24161
A85: Net Cash Flow | B85: 2330 | C85: -10072 | D85: -2754 | E85: -303 | F85: -919 | G85: 6065 | H85: -7242 | I85: -5299 | J85: 2613 | K85: 9669
A90: PRICE: | B90: 609.15 | C90: 511.13 | D90: 565.9 | E90: 743.85 | F90: 641.5 | G90: 1368.05 | H90: 1906.85 | I90: 1427.95 | J90: 1498.05 | K90: 1570.65
A92: DERIVED:
A93: Adjusted Equity Shares in Cr | B93: 459.39 | C93: 459.39 | D93: 436.82 | E93: 436.89 | F93: 425.9 | G93: 426.07 | H93: 420.67 | I93: 414.86 | J93: 415.09 | K93: 415.33

Sheet Raw FS
B2: Particulars | C2: 41699 | D2: 42064 | E2: 42430 | F2: 42795 | G2: 43160 | H2: 43525 | I2: 43891 | J2: 44256 | K2: 44621 | L2: 44986 | M2: 45352 | N2: 45717
B4: Equity Capital | C4: 286 | D4: 572 | E4: 1144 | F4: 1144 | G4: 1088 | H4: 2170 | I4: 2122 | J4: 2124 | K4: 2098 | L4: 2069 | M4: 2071 | N4: 2073
B5: Reserves | C5: 44244 | D5: 50164 | E5: 60600 | F5: 67838 | G5: 63835 | H5: 62778 | I5: 63328 | J5: 74227 | K5: 73252 | L5: 73338 | M5: 86045 | N5: 93745
B6: Borrowings -
B7: Lease Liabilities | C7: 0 | D7: 0 | E7: 0 | F7: 0 | G7: 0 | H7: 0 | I7: 4633 | J7: 5325 | K7: 5474 | L7: 8299 | M7: 8359 | N7: 8227
B8: Other Liabilities -
B9: Non controlling int | C9: 0 | D9: 0 | E9: 0 | F9: 0 | G9: 1 | H9: 58 | I9: 394 | J9: 431 | K9: 386 | L9: 388 | M9: 345 | N9: 385
B10: Trade Payables | C10: 173 | D10: 140 | E10: 386 | F10: 367 | G10: 694 | H10: 1655 | I10: 2852 | J10: 2645 | K10: 4134 | L10: 3865 | M10: 3956 | N10: 4164
B11: Advance from Customers | C11: 40 | D11: 27 | E11: 28 | F11: 0 | G11: 0 | H11: 0 | I11: 0 | J11: 0 | K11: 0 | L11: 0 | M11: 0 | N11: 0
B12: Other liability items | C12: 12223 | D12: 15386 | E12: 12940 | F12: 13799 | G12: 13731 | H12: 17405 | I12: 18471 | J12: 22759 | K12: 31385 | L12: 36637 | M12: 36584 | N12: 39201
B13: Total Liabilities | C13: 56966 | D13: 66289 | E13: 75098 | F13: 83148 | G13: 79349 | H13: 84066 | I13: 91800 | J13: 107511 | K13: 116729 | L13: 124596 | M13: 137360 | N13: 147795
B15: Fixed Assets -
B16: Land | C16: 1142 | D16: 1564 | E16: 1622 | F16: 1095 | G16: 1229 | H16: 1307 | I16: 1950 | J16: 2036 | K16: 2065 | L16: 2054 | M16: 2037 | N16: 2079
B17: Building | C17: 5238 | D17: 6102 | E17: 6325 | F17: 8419 | G17: 9334 | H17: 10270 | I17: 15104 | J17: 16328 | K17: 16761 | L17: 16903 | M17: 16515 | N17: 16376
B18: Plant Machinery | C18: 1150 | D18: 1427 | E18: 1759 | F18: 2048 | G18: 2306 | H18: 2709 | I18: 3185 | J18: 3296 | K18: 3210 | L18: 3302 | M18: 3428 | N18: 3461
B19: Equipments | C19: 551 | D19: 676 | E19: 839 | F19: 922 | G19: 1002 | H19: 1101 | I19: 1265 | J19: 1371 | K19: 1427 | L19: 1482 | M19: 1528 | N19: 1628
B20: Computers | C20: 2659 | D20: 3347 | E20: 4486 | F20: 4945 | G20: 4903 | H20: 6287 | I20: 7423 | J20: 8650 | K20: 9936 | L20: 11898 | M20: 12353 | N20: 12925
B21: Furniture n fittings | C21: 805 | D21: 958 | E21: 1444 | F21: 1277 | G21: 1393 | H21: 1620 | I21: 2073 | J21: 2149 | K21: 2279 | L21: 2303 | M21: 2326 | N21: 2340
B22: Vehicles | C22: 35 | D22: 34 | E22: 29 | F22: 31 | G22: 31 | H22: 38 | I22: 69 | J22: 74 | K22: 71 | L22: 60 | M22: 62 | N22: 72
B23: Intangible Assets | C23: 2244 | D23: 3637 | E23: 3858 | F23: 3743 | G23: 2237 | H23: 3640 | I23: 5527 | J23: 6372 | K23: 6495 | L23: 7594 | M23: 7653 | N23: 10626
B24: Other fixed assets | C24: 126 | D24: 71 | E24: 931 | F24: 899 | G24: 545 | H24: 1093 | I24: 2289 | J24: 2730 | K24: 2766 | L24: 3281 | M24: 3294 | N24: 5184
B25: Gross Block | C25: 13950 | D25: 17816 | E25: 21293 | F25: 23379 | G25: 22980 | H25: 28065 | I25: 38885 | J25: 43006 | K25: 45010 | L25: 48877 | M25: 49196 | N25: 54691
B26: Accumulated Depreciation | C26: 5572 | D26: 6470 | E26: 7907 | F26: 9200 | G26: 10406 | H26: 12355 | I26: 15096 | J26: 17501 | K26: 19210 | L26: 19652 | M26: 21574 | N26: 23730
B27: Net Block | C27: =C25-C26 -> 8378 | D27: =D25-D26 -> 11346 | E27: =E25-E26 -> 13386 | F27: =F25-F26 -> 14179 | G27: =G25-G26 -> 12574 | H27: =H25-H26 -> 15710 | I27: =I25-I26 -> 23789 | J27: =J25-J26 -> 25505 | ... N27: =N25-N26 -> 30961
B29: CWIP | C29: 961 | D29: 776 | E29: 960 | F29: 1365 | G29: 1606 | H29: 1388 | I29: 954 | J29: 922 | K29: 416 | L29: 288 | M29: 293 | N29: 814
B30: Investments | C30: 4331 | D30: 2270 | E30: 1892 | F30: 16423 | G30: 12163 | H30: 11261 | I30: 8792 | J30: 14205 | K30: 20324 | L30: 19478 | M30: 24623 | N30: 23541
B33: Other Assets -
B34: Trade receivables | C34: 8351 | D34: 9713 | E34: 11330 | F34: 12322 | G34: 13142 | H34: 14827 | I34: 18487 | J34: 19294 | K34: 22698 | L34: 25424 | M34: 30193 | N34: 31158
B35: Cash Equivalents | C35: 25950 | D35: 30367 | E35: 32697 | F35: 22625 | G35: 19818 | H35: 19568 | I35: 18649 | J35: 24714 | K35: 17472 | L35: 12173 | M35: 14786 | N35: 24455
B36: Loans n Advances | C36: 1484 | D36: 399 | E36: 614 | F36: 844 | G36: 830 | H36: 1524 | I36: 1359 | J36: 1460 | K36: 2491 | L36: 3242 | M36: 10330 | N36: 6717
B37: Other asset items | C37: 7511 | D37: 11418 | E37: 14219 | F37: 15390 | G37: 19216 | H37: 19788 | I37: 19770 | J37: 21411 | K37: 27528 | L37: 34766 | M37: 29513 | N37: 30149
B38: Total Assets | C38: 56966 | D38: 66289 | E38: 75098 | F38: 83148 | G38: 79349 | H38: 84066 | I38: 91800 | J38: 107511 | K38: 116729 | L38: 124596 | M38: 137360 | N38: 147795
B42: Cash from Operating Activity - | C42: 9825 | D42: 8353 | E42: 10028 | F42: 11531 | G42: 13218 | H42: 14841 | I42: 17003 | J42: 23224 | K42: 23885 | L42: 22467 | M42: 25210 | N42: 35694
B43: Profit from operations | C43: 14172 | D43: 15946 | E43: 17839 | F43: 19340 | G43: 19963 | H43: 22126 | I43: 23920 | J43: 28845 | K43: 32921 | L43: 37605 | M43: 39523 | N43: 41591
B44: Receivables | C44: -1406 | D44: -1475 | E44: -1654 | F44: -1743 | G44: -1523 | H44: -2881 | I44: -3861 | J44: -1835 | K44: -7937 | L44: -7076 | M44: -2667 | N44: -1769
B45: Payables | C45: 0 | D45: 0 | E45: 242 | F45: -19 | G45: 328 | H45: 916 | I45: -373 | J45: -245 | K45: 1489 | L45: -279 | M45: 91 | N45: 176
B46: Loans Advances | C46: -1060 | D46: -221 | E46: -1134 | F46: 0 | G46: 0 | H46: 0 | I46: 0 | J46: -534 | K46: -1914 | L46: -3108 | M46: -1172 | N46: -1024
B47: Other WC items | C47: 1993 | D47: 854 | E47: 600 | F47: -394 | G47: 1279 | H47: 1512 | I47: 1867 | J47: 3382 | K47: 6938 | L47: 4119 | M47: -1334 | N47: 2322
B48: Working capital changes | C48: -473 | D48: -842 | E48: -1946 | F48: -2156 | G48: 84 | H48: -453 | I48: -2367 | J48: 768 | K48: -1424 | L48: -6344 | M48: -5082 | N48: -295
... B66: Net Cash Flow | C66: 4118 | D66: 4417 | E66: 2330 | F66: -10072 | G66: -2754 | H66: -303 | I66: -919 | J66: 6065 | K66: -7242 | L66: -5299 | M66: 2613 | N66: 9669

Sheet Cash Flow Data
C2: 41699 | D2: 42064 | E2: 42430 | F2: 42795 | G2: 43160 | H2: 43525 | I2: 43891 | J2: 44256 | K2: 44621 | L2: 44986 | M2: 45352 | N2: 45717
B3: Cash from Operating Activity - | C3: 9825 | D3: 8353 | E3: 10028 | F3: 11531 | G3: 13218 | H3: 14841 | I3: 17003 | J3: 23224 | K3: 23885 | L3: 22467 | M3: 25210 | N3: 35694
B4: Profit from operations | C4: 14172 | D4: 15946 | E4: 17839 | F4: 19340 | G4: 19963 | H4: 22126 | I4: 23920 | J4: 28845 | K4: 32921 | L4: 37605 | M4: 39523 | N4: 41591
B5: Receivables | C5: -1406 | D5: -1475 | E5: -1654 | F5: -1743 | G5: -1523 | H5: -2881 | I5: -3861 | J5: -1835 | K5: -7937 | L5: -7076 | M5: -2667 | N5: -1769
B6: Payables | C6: 0 | D6: 0 | E6: 242 | F6: -19 | G6: 328 | H6: 916 | I6: -373 | J6: -245 | K6: 1489 | L6: -279 | M6: 91 | N6: 176
B7: Loans Advances | C7: -1060 | D7: -221 | E7: -1134 | F7: 0 | G7: 0 | H7: 0 | I7: 0 | J7: -534 | K7: -1914 | L7: -3108 | M7: -1172 | N7: -1024
B8: Other WC items | C8: 1993 | D8: 854 | E8: 600 | F8: -394 | G8: 1279 | H8: 1512 | I8: 1867 | J8: 3382 | K8: 6938 | L8: 4119 | M8: -1334 | N8: 2322
B9: Working capital changes | C9: -473 | D9: -842 | E9: -1946 | F9: -2156 | G9: 84 | H9: -453 | I9: -2367 | J9: 768 | K9: -1424 | L9: -6344 | M9: -5082 | N9: -295
B10: Direct taxes | C10: -3874 | D10: -6751 | E10: -5865 | F10: -5653 | G10: -6829 | H10: -6832 | I10: -4550 | J10: -6389 | K10: -7612 | L10: -8794 | M10: -9231 | N10: -5602
B11: Cash from Investing Activity - | C11: -2563 | D11: 999 | E11: -885 | F11: -14664 | G11: 4533 | H11: -632 | I11: -331 | J11: -7373 | K11: -6485 | L11: -1071 | M11: -5093 | N11: -1864
B12: Fixed assets purchased | C12: -2748 | D12: -2247 | E12: -2723 | F12: -2760 | G12: -1998 | H12: -2445 | I12: -3307 | J12: -2107 | K12: -2161 | L12: -2579 | M12: -2201 | N12: -2237
B13: Fixed assets sold | C13: 3 | D13: 0 | E13: 0 | F13: 0 | G13: 0 | H13: 0 | I13: 0 | J13: 0 | K13: 0 | L13: 0 | M13: 0 | N13: 0
B14: Investments purchased | C14: -25046 | D14: -23923 | E14: -24577 | F14: -66410 | G14: -69159 | H14: -79410 | I14: -37482 | J14: -46738 | K14: -59951 | L14: -75800 | M14: -78118 | N14: -82753
... B27: Net Cash Flow | C27: 4118 | D27: 4417 | E27: 2330 | F27: -10072 | G27: -2754 | H27: -303 | I27: -919 | J27: 6065 | K27: -7242 | L27: -5299 | M27: 2613 | N27: 9669

Sheet Common Size Statement
B2: ="Common Size Statement"&" "&"- "&'Data Sheet'!$B$1 -> Common Size Statement - INFOSYS LTD
B4: Particulars | C4: ='Data Sheet'!B16 -> 42460 | D4: ='Data Sheet'!C16 -> 42825 | E4: ='Data Sheet'!D16 -> 43190 | F4: ='Data Sheet'!E16 -> 43555 | G4: ='Data Sheet'!F16 -> 43921 | H4: ='Data Sheet'!G16 -> 44286 | I4: ='Data Sheet'!H16 -> 44651 | J4: ='Data Sheet'!I16 -> 45016 | ... L4: ='Data Sheet'!K16 -> 45747
B6: ='Data Sheet'!A17 -> Sales | C6: ='Data Sheet'!B17/'Data Sheet'!B$17 -> 1 | D6: ='Data Sheet'!C17/'Data Sheet'!C$17 -> 1 | E6: ='Data Sheet'!D17/'Data Sheet'!D$17 -> 1 | F6: ='Data Sheet'!E17/'Data Sheet'!E$17 -> 1 | G6: ='Data Sheet'!F17/'Data Sheet'!F$17 -> 1 | H6: ='Data Sheet'!G17/'Data Sheet'!G$17 -> 1 | I6: ='Data Sheet'!H17/'Data Sheet'!H$17 -> 1 | J6: ='Data Sheet'!I17/'Data Sheet'!I$17 -> 1 | ... L6: ='Data Sheet'!K17/'Data Sheet'!K$17 -> 1
B7: ='Data Sheet'!A18 -> Raw Material Cost | C7: ='Data Sheet'!B18/'Data Sheet'!B$17 -> 0 | D7: ='Data Sheet'!C18/'Data Sheet'!C$17 -> 0 | E7: ='Data Sheet'!D18/'Data Sheet'!D$17 -> 0 | F7: ='Data Sheet'!E18/'Data Sheet'!E$17 -> 0 | G7: ='Data Sheet'!F18/'Data Sheet'!F$17 -> 0 | H7: ='Data Sheet'!G18/'Data Sheet'!G$17 -> 0 | I7: ='Data Sheet'!H18/'Data Sheet'!H$17 -> 0 | J7: ='Data Sheet'!I18/'Data Sheet'!I$17 -> 0 | ... L7: ='Data Sheet'!K18/'Data Sheet'!K$17 -> 0
B8: ='Data Sheet'!A19 -> Change in Inventory | C8: ='Data Sheet'!B19/'Data Sheet'!B$17 -> 0 | D8: ='Data Sheet'!C19/'Data Sheet'!C$17 -> 0 | E8: ='Data Sheet'!D19/'Data Sheet'!D$17 -> 0 | F8: ='Data Sheet'!E19/'Data Sheet'!E$17 -> 0 | G8: ='Data Sheet'!F19/'Data Sheet'!F$17 -> 0 | H8: ='Data Sheet'!G19/'Data Sheet'!G$17 -> 0 | I8: ='Data Sheet'!H19/'Data Sheet'!H$17 -> 0 | J8: ='Data Sheet'!I19/'Data Sheet'!I$17 -> 0 | ... L8: ='Data Sheet'!K19/'Data Sheet'!K$17 -> 0
B9: ='Data Sheet'!A20 -> Power and Fuel | C9: ='Data Sheet'!B20/'Data Sheet'!B$17 -> 0.0034752807 | D9: ='Data Sheet'!C20/'Data Sheet'!C$17 -> 0.0033292448 | E9: ='Data Sheet'!D20/'Data Sheet'!D$17 -> 0.0029352542 | F9: ='Data Sheet'!E20/'Data Sheet'!E$17 -> 0.0026731176 | G9: ='Data Sheet'!F20/'Data Sheet'!F$17 -> 0.0025222764 | H9: ='Data Sheet'!G20/'Data Sheet'!G$17 -> 0.0014232821 | I9: ='Data Sheet'!H20/'Data Sheet'!H$17 -> 0.0010851604 | J9: ='Data Sheet'!I20/'Data Sheet'!I$17 -> 0.0011991797 | ... L9: ='Data Sheet'!K20/'Data Sheet'!K$17 -> 0.0013620468
B10: ='Data Sheet'!A21 -> Other Mfr. Exp | C10: ='Data Sheet'!B21/'Data Sheet'!B$17 -> 0.093848593 | D10: ='Data Sheet'!C21/'Data Sheet'!C$17 -> 0.098008294 | E10: ='Data Sheet'!D21/'Data Sheet'!D$17 -> 0.10331528 | F10: ='Data Sheet'!E21/'Data Sheet'!E$17 -> 0.11977018 | G10: ='Data Sheet'!F21/'Data Sheet'!F$17 -> 0.12210461 | H10: ='Data Sheet'!G21/'Data Sheet'!G$17 -> 0.12739868 | I10: ='Data Sheet'!H21/'Data Sheet'!H$17 -> 0.17009068 | J10: ='Data Sheet'!I21/'Data Sheet'!I$17 -> 0.1794 | ... L10: ='Data Sheet'!K21/'Data Sheet'!K$17 -> 0.18648383
B11: ='Data Sheet'!A22 -> Employee Cost | C11: ='Data Sheet'!B22/'Data Sheet'!B$17 -> 0.5511603 | D11: ='Data Sheet'!C22/'Data Sheet'!C$17 -> 0.55004089 | E11: ='Data Sheet'!D22/'Data Sheet'!D$17 -> 0.55162928 | F11: ='Data Sheet'!E22/'Data Sheet'!E$17 -> 0.54820683 | G11: ='Data Sheet'!F22/'Data Sheet'!F$17 -> 0.56057318 | H11: ='Data Sheet'!G22/'Data Sheet'!G$17 -> 0.5528605 | I11: ='Data Sheet'!H22/'Data Sheet'!H$17 -> 0.52611373 | J11: ='Data Sheet'!I22/'Data Sheet'!I$17 -> 0.53400288 | ... L11: ='Data Sheet'!K22/'Data Sheet'!K$17 -> 0.5274434
B12: ='Data Sheet'!A23 -> Selling and admin | C12: ='Data Sheet'!B23/'Data Sheet'!B$17 -> 0.07112314 | D12: ='Data Sheet'!C23/'Data Sheet'!C$17 -> 0.066935343 | E12: ='Data Sheet'!D23/'Data Sheet'!D$17 -> 0.065015173 | F12: ='Data Sheet'!E23/'Data Sheet'!E$17 -> 0.067166616 | G12: ='Data Sheet'!F23/'Data Sheet'!F$17 -> 0.059201903 | H12: ='Data Sheet'!G23/'Data Sheet'!G$17 -> 0.031789951 | I12: ='Data Sheet'!H23/'Data Sheet'!H$17 -> 0.035391028 | J12: ='Data Sheet'!I23/'Data Sheet'!I$17 -> 0.03611166 | ... L12: ='Data Sheet'!K23/'Data Sheet'!K$17 -> 0.037051353
B13: ='Data Sheet'!A24 -> Other Expenses | C13: ='Data Sheet'!B24/'Data Sheet'!B$17 -> 0.0068704857 | D13: ='Data Sheet'!C24/'Data Sheet'!C$17 -> 0.01003154 | E13: ='Data Sheet'!D24/'Data Sheet'!D$17 -> 0.01020958 | F13: ='Data Sheet'!E24/'Data Sheet'!E$17 -> 0.018215906 | G13: ='Data Sheet'!F24/'Data Sheet'!F$17 -> 0.010342435 | H13: ='Data Sheet'!G24/'Data Sheet'!G$17 -> 0.0089477665 | I13: ='Data Sheet'!H24/'Data Sheet'!H$17 -> 0.0084346561 | J13: ='Data Sheet'!I24/'Data Sheet'!I$17 -> 0.0099272997 | ... L13: ='Data Sheet'!K24/'Data Sheet'!K$17 -> 0.0069329407
B14: ='Data Sheet'!A25 -> Other Income | C14: ='Data Sheet'!B25/'Data Sheet'!B$17 -> 0.049967169 | D14: ='Data Sheet'!C25/'Data Sheet'!C$17 -> 0.04453595 | E14: ='Data Sheet'!D25/'Data Sheet'!D$17 -> 0.046949888 | F14: ='Data Sheet'!E25/'Data Sheet'!E$17 -> 0.034859389 | G14: ='Data Sheet'!F25/'Data Sheet'!F$17 -> 0.030873104 | H14: ='Data Sheet'!G25/'Data Sheet'!G$17 -> 0.021906601 | I14: ='Data Sheet'!H25/'Data Sheet'!H$17 -> 0.018866994 | J14: ='Data Sheet'!I25/'Data Sheet'!I$17 -> 0.01840332 | ... L14: ='Data Sheet'!K25/'Data Sheet'!K$17 -> 0.022087245
B15: ='Data Sheet'!A26 -> Depreciation | C15: ='Data Sheet'!B26/'Data Sheet'!B$17 -> 0.023366058 | D15: ='Data Sheet'!C26/'Data Sheet'!C$17 -> 0.024867122 | E15: ='Data Sheet'!D26/'Data Sheet'!D$17 -> 0.026417288 | F15: ='Data Sheet'!E26/'Data Sheet'!E$17 -> 0.024324161 | G15: ='Data Sheet'!F26/'Data Sheet'!F$17 -> 0.031864392 | H15: ='Data Sheet'!G26/'Data Sheet'!G$17 -> 0.032516522 | I15: ='Data Sheet'!H26/'Data Sheet'!H$17 -> 0.028575891 | J15: ='Data Sheet'!I26/'Data Sheet'!I$17 -> 0.028787125 | ... L15: ='Data Sheet'!K26/'Data Sheet'!K$17 -> 0.029523284
B16: ='Data Sheet'!A27 -> Interest | C16: ='Data Sheet'!B27/'Data Sheet'!B$17 -> 0 | D16: ='Data Sheet'!C27/'Data Sheet'!C$17 -> 0 | E16: ='Data Sheet'!D27/'Data Sheet'!D$17 -> 0 | F16: ='Data Sheet'!E27/'Data Sheet'!E$17 -> 0 | G16: ='Data Sheet'!F27/'Data Sheet'!F$17 -> 0.0018724323 | H16: ='Data Sheet'!G27/'Data Sheet'!G$17 -> 0.0019408392 | I16: ='Data Sheet'!H27/'Data Sheet'!H$17 -> 0.0016441825 | J16: ='Data Sheet'!I27/'Data Sheet'!I$17 -> 0.0019350399 | ... L16: ='Data Sheet'!K27/'Data Sheet'!K$17 -> 0.0025523038
B17: ='Data Sheet'!A28 -> Profit before tax | C17: ='Data Sheet'!B28/'Data Sheet'!B$17 -> 0.30012332 | D17: ='Data Sheet'!C28/'Data Sheet'!C$17 -> 0.29132352 | E17: ='Data Sheet'!D28/'Data Sheet'!D$17 -> 0.28742804 | F17: ='Data Sheet'!E28/'Data Sheet'!E$17 -> 0.25450257 | G17: ='Data Sheet'!F28/'Data Sheet'!F$17 -> 0.24239187 | H17: ='Data Sheet'!G28/'Data Sheet'!G$17 -> 0.26502906 | I17: ='Data Sheet'!H28/'Data Sheet'!H$17 -> 0.24753167 | J17: ='Data Sheet'!I28/'Data Sheet'!I$17 -> 0.22704014 | ... L17: ='Data Sheet'!K28/'Data Sheet'!K$17 -> 0.23073808
... B20: ='Data Sheet'!A31 -> Dividend Amount | C20: ='Data Sheet'!B31/'Data Sheet'!B$17 -> 0.088858282 | D20: ='Data Sheet'!C31/'Data Sheet'!C$17 -> 0.086028853 | E20: ='Data Sheet'!D31/'Data Sheet'!D$17 -> 0.13422194 | F20: ='Data Sheet'!E31/'Data Sheet'!E$17 -> 0.11155125 | G20: ='Data Sheet'!F31/'Data Sheet'!F$17 -> 0.081803262 | H20: ='Data Sheet'!G31/'Data Sheet'!G$17 -> 0.11415718 | I20: ='Data Sheet'!H31/'Data Sheet'!H$17 -> 0.10693434 | J20: ='Data Sheet'!I31/'Data Sheet'!I$17 -> 0.095860786 | ... L20: ='Data Sheet'!K31/'Data Sheet'!K$17 -> 0.10937972
B21: ='Data Sheet'!A33 -> EBITDA | C21: ='Data Sheet'!B33/'Data Sheet'!B$17 -> 0.32348937 | D21: ='Data Sheet'!C33/'Data Sheet'!C$17 -> 0.31619064 | E21: ='Data Sheet'!D33/'Data Sheet'!D$17 -> 0.31384532 | F21: ='Data Sheet'!E33/'Data Sheet'!E$17 -> 0.27875416 | G21: ='Data Sheet'!F33/'Data Sheet'!F$17 -> 0.27563305 | H21: ='Data Sheet'!G33/'Data Sheet'!G$17 -> 0.29876981 | I21: ='Data Sheet'!H33/'Data Sheet'!H$17 -> 0.27745579 | J21: ='Data Sheet'!I33/'Data Sheet'!I$17 -> 0.25767373 | ... L21: ='Data Sheet'!K33/'Data Sheet'!K$17 -> 0.26258666
B23: ="Common Size Balance Sheet"&" "&"- "&'Data Sheet'!$B$1 -> Common Size Balance Sheet - INFOSYS LTD
B25: Particulars | C25: ='Data Sheet'!B16 -> 42460 | D25: ='Data Sheet'!C16 -> 42825 | E25: ='Data Sheet'!D16 -> 43190 | F25: ='Data Sheet'!E16 -> 43555 | G25: ='Data Sheet'!F16 -> 43921 | H25: ='Data Sheet'!G16 -> 44286 | I25: ='Data Sheet'!H16 -> 44651 | J25: ='Data Sheet'!I16 -> 45016 | ... L25: ='Data Sheet'!K16 -> 45747
B27: Total Liabilities | C27: ='Data Sheet'!B61/'Data Sheet'!B$61 -> 1 | D27: ='Data Sheet'!C61/'Data Sheet'!C$61 -> 1 | E27: ='Data Sheet'!D61/'Data Sheet'!D$61 -> 1 | F27: ='Data Sheet'!E61/'Data Sheet'!E$61 -> 1 | G27: ='Data Sheet'!F61/'Data Sheet'!F$61 -> 1 | H27: ='Data Sheet'!G61/'Data Sheet'!G$61 -> 1 | I27: ='Data Sheet'!H61/'Data Sheet'!H$61 -> 1 | J27: ='Data Sheet'!I61/'Data Sheet'!I$61 -> 1 | ... L27: ='Data Sheet'!K61/'Data Sheet'!K$61 -> 1
B28: ='Data Sheet'!A57 -> Equity Share Capital | C28: ='Data Sheet'!B57/'Data Sheet'!B$61 -> 0.015233428 | D28: ='Data Sheet'!C57/'Data Sheet'!C$61 -> 0.013758599 | E28: ='Data Sheet'!D57/'Data Sheet'!D$61 -> 0.013711578 | F28: ='Data Sheet'!E57/'Data Sheet'!E$61 -> 0.025813052 | G28: ='Data Sheet'!F57/'Data Sheet'!F$61 -> 0.023115468 | H28: ='Data Sheet'!G57/'Data Sheet'!G$61 -> 0.019756118 | I28: ='Data Sheet'!H57/'Data Sheet'!H$61 -> 0.017973254 | J28: ='Data Sheet'!I57/'Data Sheet'!I$61 -> 0.01660567 | ... L28: ='Data Sheet'!K57/'Data Sheet'!K$61 -> 0.014026185
B29: ='Data Sheet'!A58 -> Reserves | C29: ='Data Sheet'!B58/'Data Sheet'!B$61 -> 0.80694559 | D29: ='Data Sheet'!C58/'Data Sheet'!C$61 -> 0.8158705 | E29: ='Data Sheet'!D58/'Data Sheet'!D$61 -> 0.80448399 | F29: ='Data Sheet'!E58/'Data Sheet'!E$61 -> 0.74677039 | G29: ='Data Sheet'!F58/'Data Sheet'!F$61 -> 0.68984749 | H29: ='Data Sheet'!G58/'Data Sheet'!G$61 -> 0.69041307 | I29: ='Data Sheet'!H58/'Data Sheet'!H$61 -> 0.627539 | J29: ='Data Sheet'!I58/'Data Sheet'!I$61 -> 0.58860638 | ... L29: ='Data Sheet'!K58/'Data Sheet'!K$61 -> 0.63429074
B30: ='Data Sheet'!A59 -> Borrowings | C30: ='Data Sheet'!B59/'Data Sheet'!B$61 -> 0 | D30: ='Data Sheet'!C59/'Data Sheet'!C$61 -> 0 | E30: ='Data Sheet'!D59/'Data Sheet'!D$61 -> 0 | F30: ='Data Sheet'!E59/'Data Sheet'!E$61 -> 0 | G30: ='Data Sheet'!F59/'Data Sheet'!F$61 -> 0.05046841 | H30: ='Data Sheet'!G59/'Data Sheet'!G$61 -> 0.049529816 | I30: ='Data Sheet'!H59/'Data Sheet'!H$61 -> 0.046894945 | J30: ='Data Sheet'!I59/'Data Sheet'!I$61 -> 0.066607275 | ... L30: ='Data Sheet'!K59/'Data Sheet'!K$61 -> 0.055664941
B31: ='Data Sheet'!A60 -> Other Liabilities | C31: ='Data Sheet'!B60/'Data Sheet'!B$61 -> 0.17782098 | D31: ='Data Sheet'!C60/'Data Sheet'!C$61 -> 0.1703709 | E31: ='Data Sheet'!D60/'Data Sheet'!D$61 -> 0.18180443 | F31: ='Data Sheet'!E60/'Data Sheet'!E$61 -> 0.22741655 | G31: ='Data Sheet'!F60/'Data Sheet'!F$61 -> 0.23656863 | H31: ='Data Sheet'!G60/'Data Sheet'!G$61 -> 0.24030099 | I31: ='Data Sheet'!H60/'Data Sheet'!H$61 -> 0.3075928 | J31: ='Data Sheet'!I60/'Data Sheet'!I$61 -> 0.32818068 | ... L31: ='Data Sheet'!K60/'Data Sheet'!K$61 -> 0.29601813
B33: ='Data Sheet'!A75 -> Total Asset | C33: ='Data Sheet'!B75/'Data Sheet'!B$75 -> 1 | D33: ='Data Sheet'!C75/'Data Sheet'!C$75 -> 1 | E33: ='Data Sheet'!D75/'Data Sheet'!D$75 -> 1 | F33: ='Data Sheet'!E75/'Data Sheet'!E$75 -> 1 | G33: ='Data Sheet'!F75/'Data Sheet'!F$75 -> 1 | H33: ='Data Sheet'!G75/'Data Sheet'!G$75 -> 1 | I33: ='Data Sheet'!H75/'Data Sheet'!H$75 -> 1 | J33: ='Data Sheet'!I75/'Data Sheet'!I$75 -> 1 | ... L33: ='Data Sheet'!K75/'Data Sheet'!K$75 -> 1
B34: ='Data Sheet'!A62 -> Net Block | C34: ='Data Sheet'!B62/'Data Sheet'!B$75 -> 0.17824709 | D34: ='Data Sheet'!C62/'Data Sheet'!C$75 -> 0.17052725 | E34: ='Data Sheet'!D62/'Data Sheet'!D$75 -> 0.1584645 | F34: ='Data Sheet'!E62/'Data Sheet'!E$75 -> 0.18687698 | G34: ='Data Sheet'!F62/'Data Sheet'!F$75 -> 0.25913943 | H34: ='Data Sheet'!G62/'Data Sheet'!G$75 -> 0.23723154 | I34: ='Data Sheet'!H62/'Data Sheet'!H$75 -> 0.22102477 | J34: ='Data Sheet'!I62/'Data Sheet'!I$75 -> 0.23455809 | ... L34: ='Data Sheet'!K62/'Data Sheet'!K$75 -> 0.20948611
B35: ='Data Sheet'!A63 -> Capital Work in Progress | C35: ='Data Sheet'!B63/'Data Sheet'!B$75 -> 0.012783296 | D35: ='Data Sheet'!C63/'Data Sheet'!C$75 -> 0.01641651 | E35: ='Data Sheet'!D63/'Data Sheet'!D$75 -> 0.020239701 | F35: ='Data Sheet'!E63/'Data Sheet'!E$75 -> 0.016510837 | G35: ='Data Sheet'!F63/'Data Sheet'!F$75 -> 0.010392157 | H35: ='Data Sheet'!G63/'Data Sheet'!G$75 -> 0.0085758667 | I35: ='Data Sheet'!H63/'Data Sheet'!H$75 -> 0.0035638102 | J35: ='Data Sheet'!I63/'Data Sheet'!I$75 -> 0.0023114707 | ... L35: ='Data Sheet'!K63/'Data Sheet'!K$75 -> 0.0055076288
B36: ='Data Sheet'!A64 -> Investments | C36: ='Data Sheet'!B64/'Data Sheet'!B$75 -> 0.025193747 | D36: ='Data Sheet'!C64/'Data Sheet'!C$75 -> 0.19751527 | E36: ='Data Sheet'!D64/'Data Sheet'!D$75 -> 0.15328486 | F36: ='Data Sheet'!E64/'Data Sheet'!E$75 -> 0.13395427 | G36: ='Data Sheet'!F64/'Data Sheet'!F$75 -> 0.09577342 | H36: ='Data Sheet'!G64/'Data Sheet'!G$75 -> 0.13212602 | I36: ='Data Sheet'!H64/'Data Sheet'!H$75 -> 0.17411269 | J36: ='Data Sheet'!I64/'Data Sheet'!I$75 -> 0.15632926 | ... L36: ='Data Sheet'!K64/'Data Sheet'!K$75 -> 0.15928144
B37: ='Data Sheet'!A65 -> Other Assets | C37: ='Data Sheet'!B74/'Data Sheet'!B$75 -> 0.19751525 | D37: ='Data Sheet'!C74/'Data Sheet'!C$75 -> 0.19524222 | E37: ='Data Sheet'!D74/'Data Sheet'!D$75 -> 0.25263078 | F37: ='Data Sheet'!E74/'Data Sheet'!E$75 -> 0.2535151 | G37: ='Data Sheet'!F74/'Data Sheet'!F$75 -> 0.2301634 | H37: ='Data Sheet'!G74/'Data Sheet'!G$75 -> 0.21273172 | I37: ='Data Sheet'!H74/'Data Sheet'!H$75 -> 0.25716831 | J37: ='Data Sheet'!I74/'Data Sheet'!I$75 -> 0.30504992 | ... L37: ='Data Sheet'!K74/'Data Sheet'!K$75 -> 0.2494401
B38: ='Data Sheet'!A67 -> Receivables | C38: ='Data Sheet'!B67/'Data Sheet'!B$75 -> 0.15086953 | D38: ='Data Sheet'!C67/'Data Sheet'!C$75 -> 0.14819358 | E38: ='Data Sheet'!D67/'Data Sheet'!D$75 -> 0.16562276 | F38: ='Data Sheet'!E67/'Data Sheet'!E$75 -> 0.17637333 | G38: ='Data Sheet'!F67/'Data Sheet'!F$75 -> 0.20138344 | H38: ='Data Sheet'!G67/'Data Sheet'!G$75 -> 0.17946071 | I38: ='Data Sheet'!H67/'Data Sheet'!H$75 -> 0.19445039 | J38: ='Data Sheet'!I67/'Data Sheet'!I$75 -> 0.20405149 | ... L38: ='Data Sheet'!K67/'Data Sheet'!K$75 -> 0.21081904
B39: ='Data Sheet'!A68 -> Inventory | C39: ='Data Sheet'!B68/'Data Sheet'!B$75 -> 0 | D39: ='Data Sheet'!C68/'Data Sheet'!C$75 -> 0 | E39: ='Data Sheet'!D68/'Data Sheet'!D$75 -> 0 | F39: ='Data Sheet'!E68/'Data Sheet'!E$75 -> 0 | G39: ='Data Sheet'!F68/'Data Sheet'!F$75 -> 0 | H39: ='Data Sheet'!G68/'Data Sheet'!G$75 -> 0 | I39: ='Data Sheet'!H68/'Data Sheet'!H$75 -> 0 | J39: ='Data Sheet'!I68/'Data Sheet'!I$75 -> 0 | ... L39: ='Data Sheet'!K68/'Data Sheet'!K$75 -> 0
B40: ='Data Sheet'!A69 -> Cash & Bank | C40: ='Data Sheet'!B69/'Data Sheet'!B$75 -> 0.43539109 | D40: ='Data Sheet'!C69/'Data Sheet'!C$75 -> 0.27210516 | E40: ='Data Sheet'!D69/'Data Sheet'!D$75 -> 0.2497574 | F40: ='Data Sheet'!E69/'Data Sheet'!E$75 -> 0.23276949 | G40: ='Data Sheet'!F69/'Data Sheet'!F$75 -> 0.20314815 | H40: ='Data Sheet'!G69/'Data Sheet'!G$75 -> 0.22987415 | I40: ='Data Sheet'!H69/'Data Sheet'!H$75 -> 0.14968003 | J40: ='Data Sheet'!I69/'Data Sheet'!I$75 -> 0.097699766 | ... L40: ='Data Sheet'!K69/'Data Sheet'!K$75 -> 0.16546568

Sheet Beta Comps
B2: Comparable Beta
B3: SL.No | C3: Name | D3: CMP Rs. | E3: Mar Cap Rs.Cr. | F3: Debt Rs.Cr. | G3: Debt / Eq
B4: 1 | C4: TCS | D4: 3311.65 | E4: 1198184 | F4: 10932 | G4: 0.1
B5: 2 | C5: Infosys | D5: 1643.3 | E5: 682729.42 | F5: 8755 | G5: 0.08
B6: 3 | C6: HCL Technologies | D6: 1659.1 | E6: 450224.18 | F6: 6780 | G6: 0.1
B7: 4 | C7: Wipro | D7: 265.3 | E7: 278212.65 | F7: 16163.7 | G7: 0.19
B8: 5 | C8: LTIMindtree | D8: 6045 | E8: 179227.75 | F8: 2382.6 | G8: 0.1

Sheet Beta
B2: Regression Beta -1 Years
L3: Beta | M3: =D274 -> 0.64748944 | Y3: Beta | Z3: =Q274 -> 0.13038434 | AL3: Beta | AM3: =AD274 -> 0.67607431 | AY3: Beta | AZ3: =AQ274 -> 1.060634 | BL3: Beta | BM3: =BD274 -> 0.78416087
B4: Tata Consultancy Services Ltd | G4: Nifty Returns | L4: Beta Drifting | O4: Infosys Ltd | T4: Nifty Returns | Y4: Beta Drifting | AB4: HCL Technologies Ltd | AG4: Nifty Returns | AL4: Beta Drifting | AO4: Wipro Ltd | AT4: Nifty Returns | AY4: Beta Drifting | BB4: LTIMindtree Limited | BG4: Nifty Returns | BL4: Beta Drifting
B6: Date | C6: Closing Price | D6: Return | G6: Date | H6: Closing Price | I6: Return | L6: Levered Raw Beta | M6: =M3 -> 0.64748944 | O6: Date | P6: Closing Price | Q6: Return | T6: Date | U6: Closing Price | V6: Return | Y6: Levered Raw Beta | Z6: =Z3 -> 0.13038434 | AB6: Date | AC6: Closing Price | AD6: Return | AG6: Date | AH6: Closing Price | AI6: Return | AL6: Levered Raw Beta | AM6: =AM3 -> 0.67607431 | AO6: Date | AP6: Closing Price | AQ6: Return | AT6: Date | AU6: Closing Price | AV6: Return | AY6: Levered Raw Beta | AZ6: =AZ3 -> 1.060634 | BB6: Date | BC6: Closing Price | BD6: Return | BG6: Date | BH6: Closing Price | BI6: Return | BL6: Levered Raw Beta | BM6: =BM3 -> 0.78416087
L7: Raw Beta Weight | M7: 0.75 | Y7: Raw Beta Weight | Z7: 0.75 | AL7: Raw Beta Weight | AM7: 0.75 | AY7: Raw Beta Weight | AZ7: 0.75 | BL7: Raw Beta Weight | BM7: 0.75
B8: 45383 | C8: 3739.9441 | G8: 45383 | H8: 22462 | O8: 45383 | P8: 16.549641 | T8: 45383 | U8: 22462 | AB8: 45383 | AC8: 1458.9897 | AG8: 45383 | AH8: 22462 | AO8: 45383 | AP8: 233.16446 | AT8: 45383 | AU8: 22462 | BB8: 45383 | BC8: 4761.2881 | BG8: 45383 | BH8: 22462
B9: 45384 | C9: 3708.4819 | D9: =C9/C8-1 -> -0.0084124675 | G9: 45384 | H9: 22453.301 | I9: =H9/H8-1 -> -0.00038728603 | L9: Market Beta | M9: 1 | O9: 45384 | P9: 16.549641 | Q9: =P9/P8-1 -> -1.110223e-15 | T9: 45384 | U9: 22453.301 | V9: =U9/U8-1 -> -0.00038728603 | Y9: Market Beta | Z9: 1 | AB9: 45384 | AC9: 1432.3726 | AD9: =AC9/AC8-1 -> -0.018243574 | AG9: 45384 | AH9: 22453.301 | AI9: =AH9/AH8-1 -> -0.00038728603 | AL9: Market Beta | AM9: 1 | AO9: 45384 | AP9: 231.36145 | AQ9: =AP9/AP8-1 -> -0.0077327781 | AT9: 45384 | AU9: 22453.301 | AV9: =AU9/AU8-1 -> -0.00038728603 | AY9: Market Beta | AZ9: 1 | BB9: 45384 | BC9: 4778.9868 | BD9: =BC9/BC8-1 -> 0.0037172148 | BG9: 45384 | BH9: 22453.301 | BI9: =BH9/BH8-1 -> -0.00038728603 | BL9: Market Beta | BM9: 1
B10: 45385 | C10: 3769.115 | D10: =C10/C9-1 -> 0.016349832 | G10: 45385 | H10: 22434.65 | I10: =H10/H9-1 -> -0.00083063024 | L10: Market Beta Weight | M10: 0.25 | O10: 45385 | P10: 16.681437 | Q10: =P10/P9-1 -> 0.0079636704 | T10: 45385 | U10: 22434.65 | V10: =U10/U9-1 -> -0.00083063024 | Y10: Market Beta Weight | Z10: 0.25 | AB10: 45385 | AC10: 1439.4485 | AD10: =AC10/AC9-1 -> 0.0049400051 | AG10: 45385 | AH10: 22434.65 | AI10: =AH10/AH9-1 -> -0.00083063024 | AL10: Market Beta Weight | AM10: 0.25 | AO10: 45385 | AP10: 232.32304 | AQ10: =AP10/AP9-1 -> 0.0041562396 | AT10: 45385 | AU10: 22434.65 | AV10: =AU10/AU9-1 -> -0.00083063024 | AY10: Market Beta Weight | AZ10: 0.25 | BB10: 45385 | BC10: 4748.3184 | BD10: =BC10/BC9-1 -> -0.0064173554 | BG10: 45385 | BH10: 22434.65 | BI10: =BH10/BH9-1 -> -0.00083063024 | BL10: Market Beta Weight | BM10: 0.25
B11: 45386 | C11: 3822.5874 | D11: =C11/C10-1 -> 0.014186994 | G11: 45386 | H11: 22514.65 | I11: =H11/H10-1 -> 0.0035659125 | O11: 45386 | P11: 16.709679 | Q11: =P11/P10-1 -> 0.0016930263 | T11: 45386 | U11: 22514.65 | V11: =U11/U10-1 -> 0.0035659125 | AB11: 45386 | AC11: 1443.0099 | AD11: =AC11/AC10-1 -> 0.002474143 | AG11: 45386 | AH11: 22514.65 | AI11: =AH11/AH10-1 -> 0.0035659125 | AO11: 45386 | AP11: 234.34241 | AQ11: =AP11/AP10-1 -> 0.0086920495 | AT11: 45386 | AU11: 22514.65 | AV11: =AU11/AU10-1 -> 0.0035659125 | BB11: 45386 | BC11: 4812.5815 | BD11: =BC11/BC10-1 -> 0.013533883 | BG11: 45386 | BH11: 22514.65 | BI11: =BH11/BH10-1 -> 0.0035659125
B12: 45387 | C12: 3799.623 | D12: =C12/C11-1 -> -0.0060075423 | G12: 45387 | H12: 22513.699 | I12: =H12/H11-1 -> -4.2246797e-05 | L12: Adjusted Beta | M12: =(M6*M7)+(M9*M10) -> 0.73561708 | O12: 45387 | P12: 16.784988 | Q12: =P12/P11-1 -> 0.004506954 | T12: 45387 | U12: 22513.699 | V12: =U12/U11-1 -> -4.2246797e-05 | Y12: Adjusted Beta | Z12: =(Z6*Z7)+(Z9*Z10) -> 0.34778826 | AB12: 45387 | AC12: 1448.2584 | AD12: =AC12/AC11-1 -> 0.0036372136 | AG12: 45387 | AH12: 22513.699 | AI12: =AH12/AH11-1 -> -4.2246797e-05 | AL12: Adjusted Beta | AM12: =(AM6*AM7)+(AM9*AM10) -> 0.75705573 | AO12: 45387 | AP12: 233.21252 | AQ12: =AP12/AP11-1 -> -0.0048215038 | AT12: 45387 | AU12: 22513.699 | AV12: =AU12/AU11-1 -> -4.2246797e-05 | AY12: Adjusted Beta | AZ12: =(AZ6*AZ7)+(AZ9*AZ10) -> 1.0454755 | BB12: 45387 | BC12: 4805.0728 | BD12: =BC12/BC11-1 -> -0.0015602414 | BG12: 45387 | BH12: 22513.699 | BI12: =BH12/BH11-1 -> -4.2246797e-05 | BL12: Adjusted Beta | BM12: =(BM6*BM7)+(BM9*BM10) -> 0.83812066
B13: 45390 | C13: 3793.2253 | D13: =C13/C12-1 -> -0.0016837736 | G13: 45390 | H13: 22666.301 | I13: =H13/H12-1 -> 0.0067781648 | O13: 45390 | P13: 16.813232 | Q13: =P13/P12-1 -> 0.0016826951 | T13: 45390 | U13: 22666.301 | V13: =U13/U12-1 -> 0.0067781648 | AB13: 45390 | AC13: 1443.385 | AD13: =AC13/AC12-1 -> -0.0033650162 | AG13: 45390 | AH13: 22666.301 | AI13: =AH13/AH12-1 -> 0.0067781648 | AO13: 45390 | AP13: 230.7364 | AQ13: =AP13/AP12-1 -> -0.01061744 | AT13: 45390 | AU13: 22666.301 | AV13: =AU13/AU12-1 -> 0.0067781648 | BB13: 45390 | BC13: 4775.7207 | BD13: =BC13/BC12-1 -> -0.0061085549 | BG13: 45390 | BH13: 22666.301 | BI13: =BH13/BH12-1 -> 0.0067781648
B14: 45391 | C14: 3768.3992 | D14: =C14/C13-1 -> -0.0065448714 | G14: 45391 | H14: 22642.75 | I14: =H14/H13-1 -> -0.0010390218 | O14: 45391 | P14: 17.123892 | Q14: =P14/P13-1 -> 0.018477078 | T14: 45391 | U14: 22642.75 | V14: =U14/U13-1 -> -0.0010390218 | AB14: 45391 | AC14: 1443.8066 | AD14: =AC14/AC13-1 -> 0.00029211254 | AG14: 45391 | AH14: 22642.75 | AI14: =AH14/AH13-1 -> -0.0010390218 | AO14: 45391 | AP14: 228.76512 | AQ14: =AP14/AP13-1 -> -0.0085434414 | AT14: 45391 | AU14: 22642.75 | AV14: =AU14/AU13-1 -> -0.0010390218 | BB14: 45391 | BC14: 4771.0879 | BD14: =BC14/BC13-1 -> -0.0009700761 | BG14: 45391 | BH14: 22642.75 | BI14: =BH14/BH13-1 -> -0.0010390218
B15: 45392 | C15: 3804.7791 | D15: =C15/C14-1 -> 0.0096539356 | G15: 45392 | H15: 22753.801 | I15: =H15/H14-1 -> 0.0049044741 | O15: 45392 | P15: 16.945023 | Q15: =P15/P14-1 -> -0.010445595 | T15: 45392 | U15: 22753.801 | V15: =U15/U14-1 -> 0.0049044741 | AB15: 45392 | AC15: 1442.5415 | AD15: =AC15/AC14-1 -> -0.0008762508 | AG15: 45392 | AH15: 22753.801 | AI15: =AH15/AH14-1 -> 0.0049044741 | AO15: 45392 | AP15: 229.48631 | AQ15: =AP15/AP14-1 -> 0.0031525409 | AT15: 45392 | AU15: 22753.801 | AV15: =AU15/AU14-1 -> 0.0049044741 | BB15: 45392 | BC15: 4796.1504 | BD15: =BC15/BC14-1 -> 0.0052529948 | BG15: 45392 | BH15: 22753.801 | BI15: =BH15/BH14-1 -> 0.0049044741
B16: 45394 | C16: 3820.7734 | D16: =C16/C15-1 -> 0.0042037618 | G16: 45394 | H16: 22519.4 | I16: =H16/H15-1 -> -0.010301593 | O16: 45393 | P16: 16.888542 | Q16: =P16/P15-1 -> -0.0033331562 | T16: 45394 | U16: 22519.4 | V16: =U16/U15-1 -> -0.010301593 | AB16: 45394 | AC16: 1425.9991 | AD16: =AC16/AC15-1 -> -0.011467509 | AG16: 45394 | AH16: 22519.4 | AI16: =AH16/AH15-1 -> -0.010301593 | AO16: 45394 | AP16: 226.33708 | AQ16: =AP16/AP15-1 -> -0.013722958 | AT16: 45394 | AU16: 22519.4 | AV16: =AU16/AU15-1 -> -0.010301593 | BB16: 45394 | BC16: 4767.4316 | BD16: =BC16/BC15-1 -> -0.0059878752 | BG16: 45394 | BH16: 22519.4 | BI16: =BH16/BH15-1 -> -0.010301593
B17: 45397 | C17: 3763.2905 | D17: =C17/C16-1 -> -0.015044836 | G17: 45397 | H17: 22272.5 | I17: =H17/H16-1 -> -0.010963897 | O17: 45394 | P17: 16.681437 | Q17: =P17/P16-1 -> -0.012263085 | T17: 45397 | U17: 22272.5 | V17: =U17/U16-1 -> -0.010963897 | AB17: 45397 | AC17: 1410.5818 | AD17: =AC17/AC16-1 -> -0.010811618 | AG17: 45397 | AH17: 22272.5 | AI17: =AH17/AH16-1 -> -0.010963897 | AO17: 45397 | AP17: 220.85594 | AQ17: =AP17/AP16-1 -> -0.024216713 | AT17: 45397 | AU17: 22272.5 | AV17: =AU17/AU16-1 -> -0.010963897 | BB17: 45397 | BC17: 4695.5137 | BD17: =BC17/BC16-1 -> -0.015085265 | BG17: 45397 | BH17: 22272.5 | BI17: =BH17/BH16-1 -> -0.010963897
B18: 45398 | C18: 3697.978 | D18: =C18/C17-1 -> -0.017355158 | G18: 45398 | H18: 22147.9 | I18: =H18/H17-1 -> -0.0055943253 | O18: 45397 | P18: 16.257811 | Q18: =P18/P17-1 -> -0.025395052 | T18: 45398 | U18: 22147.9 | V18: =U18/U17-1 -> -0.0055943253 | AB18: 45398 | AC18: 1384.5736 | AD18: =AC18/AC17-1 -> -0.018437909 | AG18: 45398 | AH18: 22147.9 | AI18: =AH18/AH17-1 -> -0.0055943253 | AO18: 45398 | AP18: 215.56714 | AQ18: =AP18/AP17-1 -> -0.023946845 | AT18: 45398 | AU18: 22147.9 | AV18: =AU18/AU17-1 -> -0.0055943253 | BB18: 45398 | BC18: 4546.998 | BD18: =BC18/BC17-1 -> -0.03162926 | BG18: 45398 | BH18: 22147.9 | BI18: =BH18/BH17-1 -> -0.0055943253
B19: 45400 | C19: 3687.6655 | D19: =C19/C18-1 -> -0.0027886861 | G19: 45400 | H19: 21995.85 | I19: =H19/H18-1 -> -0.0068652459 | O19: 45398 | P19: 16.050703 | Q19: =P19/P18-1 -> -0.012738957 | T19: 45400 | U19: 21995.85 | V19: =U19/U18-1 -> -0.0068652459 | AB19: 45400 | AC19: 1374.7792 | AD19: =AC19/AC18-1 -> -0.007073971 | AG19: 45400 | AH19: 21995.85 | AI19: =AH19/AH18-1 -> -0.0068652459 | AO19: 45400 | AP19: 213.64394 | AQ19: =AP19/AP18-1 -> -0.0089215941 | AT19: 45400 | AU19: 21995.85 | AV19: =AU19/AU18-1 -> -0.0068652459 | BB19: 45400 | BC19: 4580.4458 | BD19: =BC19/BC18-1 -> 0.007356008 | BG19: 45400 | BH19: 21995.85 | BI19: =BH19/BH18-1 -> -0.0068652459
B20: 45401 | C20: 3653.4819 | D20: =C20/C19-1 -> -0.009269711 | G20: 45401 | H20: 22147 | I20: =H20/H19-1 -> 0.0068717687 | O20: 45399 | P20: 15.956565 | Q20: =P20/P19-1 -> -0.0058650481 | T20: 45401 | U20: 22147 | V20: =U20/U19-1 -> 0.0068717687 | AB20: 45401 | AC20: 1356.644 | AD20: =AC20/AC19-1 -> -0.013191305 | AG20: 45401 | AH20: 22147 | AI20: =AH20/AH19-1 -> 0.0068717687 | AO20: 45401 | AP20: 217.68266 | AQ20: =AP20/AP19-1 -> 0.018904009 | AT20: 45401 | AU20: 22147 | AV20: =AU20/AU19-1 -> 0.0068717687 | BB20: 45401 | BC20: 4544.7549 | BD20: =BC20/BC19-1 -> -0.0077920184 | BG20: 45401 | BH20: 22147 | BI20: =BH20/BH19-1 -> 0.0068717687
B21: 45404 | C21: 3690.1487 | D21: =C21/C20-1 -> 0.01003611 | G21: 45404 | H21: 22336.4 | I21: =H21/H20-1 -> 0.008551966 | O21: 45400 | P21: 15.542355 | Q21: =P21/P20-1 -> -0.025958615 | T21: 45404 | U21: 22336.4 | V21: =U21/U20-1 -> 0.008551966 | AB21: 45404 | AC21: 1373.889 | AD21: =AC21/AC20-1 -> 0.012711511 | AG21: 45404 | AH21: 22336.4 | AI21: =AH21/AH20-1 -> 0.008551966 | AO21: 45404 | AP21: 222.13007 | AQ21: =AP21/AP20-1 -> 0.020430671 | AT21: 45404 | AU21: 22336.4 | AV21: =AU21/AU20-1 -> 0.008551966 | BB21: 45404 | BC21: 4560.0161 | BD21: =BC21/BC20-1 -> 0.0033579876 | BG21: 45404 | BH21: 22336.4 | BI21: =BH21/BH20-1 -> 0.008551966
B22: 45405 | C22: 3699.7927 | D22: =C22/C21-1 -> 0.0026134565 | G22: 45405 | H22: 22368 | I22: =H22/H21-1 -> 0.0014147136 | O22: 45401 | P22: 15.82477 | Q22: =P22/P21-1 -> 0.018170695 | T22: 45405 | U22: 22368 | V22: =U22/U21-1 -> 0.0014147136 | AB22: 45405 | AC22: 1393.3368 | AD22: =AC22/AC21-1 -> 0.014155258 | AG22: 45405 | AH22: 22368 | AI22: =AH22/AH21-1 -> 0.0014147136 | AO22: 45405 | AP22: 222.17815 | AQ22: =AP22/AP21-1 -> 0.00021645176 | AT22: 45405 | AU22: 22368 | AV22: =AU22/AU21-1 -> 0.0014147136 | BB22: 45405 | BC22: 4606.0439 | BD22: =BC22/BC21-1 -> 0.010093787 | BG22: 45405 | BH22: 22368 | BI22: =BH22/BH21-1 -> 0.0014147136
B23: 45406 | C23: 3658.1128 | D23: =C23/C22-1 -> -0.011265477 | G23: 45406 | H23: 22402.4 | I23: =H23/H22-1 -> 0.0015379288 | O23: 45404 | P23: 16.286053 | Q23: =P23/P22-1 -> 0.029149411 | T23: 45406 | U23: 22402.4 | V23: =U23/U22-1 -> 0.0015379288 | AB23: 45406 | AC23: 1386.4011 | AD23: =AC23/AC22-1 -> -0.0049777405 | AG23: 45406 | AH23: 22402.4 | AI23: =AH23/AH22-1 -> 0.0015379288 | AO23: 45406 | AP23: 221.12038 | AQ23: =AP23/AP22-1 -> -0.0047609083 | AT23: 45406 | AU23: 22402.4 | AV23: =AU23/AU22-1 -> 0.0015379288 | BB23: 45406 | BC23: 4609.3589 | BD23: =BC23/BC22-1 -> 0.00071969383 | BG23: 45406 | BH23: 22402.4 | BI23: =BH23/BH22-1 -> 0.0015379288
B24: 45407 | C24: 3678.3079 | D24: =C24/C23-1 -> 0.0055206248 | G24: 45407 | H24: 22570.35 | I24: =H24/H23-1 -> 0.0074969296 | O24: 45405 | P24: 16.154259 | Q24: =P24/P23-1 -> -0.0080924444 | T24: 45407 | U24: 22570.35 | V24: =U24/U23-1 -> 0.0074969296 | AB24: 45407 | AC24: 1409.7382 | AD24: =AC24/AC23-1 -> 0.016832817 | AG24: 45407 | AH24: 22570.35 | AI24: =AH24/AH23-1 -> 0.0074969296 | AO24: 45407 | AP24: 221.64928 | AQ24: =AP24/AP23-1 -> 0.0023919105 | AT24: 45407 | AU24: 22570.35 | AV24: =AU24/AU23-1 -> 0.0074969296 | BB24: 45407 | BC24: 4519.5474 | BD24: =BC24/BC23-1 -> -0.019484602 | BG24: 45407 | BH24: 22570.35 | BI24: =BH24/BH23-1 -> 0.0074969296
... B255: 45744 | C255: 3549.0535 | D255: =C255/C254-1 -> -0.012338463 | G255: 45744 | H255: 23519.35 | I255: =H255/H254-1 -> -0.0030773044 | O255: 45742 | P255: 18.127581 | Q255: =P255/P254-1 -> -0.0090281596 | T255: 45744 | U255: 23519.35 | V255: =U255/U254-1 -> -0.0030773044 | AB255: 45744 | AC255: 1549.7273 | AD255: =AC255/AC254-1 -> -0.023095977 | AG255: 45744 | AH255: 23519.35 | AI255: =AH255/AH254-1 -> -0.0030773044 | AO255: 45744 | AP255: 257.19116 | AQ255: =AP255/AP254-1 -> -0.036553981 | AT255: 45744 | AU255: 23519.35 | AV255: =AU255/AU254-1 -> -0.0030773044 | BB255: 45744 | BC255: 4433.6807 | BD255: =BC255/BC254-1 -> -0.035342222 | BG255: 45744 | BH255: 23519.35 | BI255: =BH255/BH254-1 -> -0.0030773044
C257: SUMMARY OUTPUT | P257: SUMMARY OUTPUT | AC257: SUMMARY OUTPUT | AP257: SUMMARY OUTPUT | BC257: SUMMARY OUTPUT
C259: Regression Statistics | P259: Regression Statistics | AC259: Regression Statistics | AP259: Regression Statistics | BC259: Regression Statistics
C260: Multiple R | D260: 0.43540973 | P260: Multiple R | Q260: 0.079974013 | AC260: Multiple R | AD260: 0.40310235 | AP260: Multiple R | AQ260: 0.51549873 | BC260: Multiple R | BD260: 0.38253501
C261: R Square | D261: 0.18958163 | P261: R Square | Q261: 0.0063958428 | AC261: R Square | AD261: 0.1624915 | AP261: R Square | AQ261: 0.26573894 | BC261: R Square | BD261: 0.14633304
C262: Adjusted R Square | D262: 0.1862738 | P262: Adjusted R Square | Q262: 0.0023403156 | AC262: Adjusted R Square | AD262: 0.1590731 | AP262: Adjusted R Square | AQ262: 0.26274196 | BC262: Adjusted R Square | BD262: 0.14284868
C263: Standard Error | D263: 0.011910919 | P263: Standard Error | Q263: 0.014459035 | AC263: Standard Error | AD263: 0.013656197 | AP263: Standard Error | AQ263: 0.015686254 | BC263: Standard Error | BD263: 0.016851334
C264: Observations | D264: 247 | P264: Observations | Q264: 247 | AC264: Observations | AD264: 247 | AP264: Observations | AQ264: 247 | BC264: Observations | BD264: 247
C266: ANOVA | P266: ANOVA | AC266: ANOVA | AP266: ANOVA | BC266: ANOVA
D267: df | E267: SS | F267: MS | G267: F | H267: Significance F | Q267: df | R267: SS | S267: MS | T267: F | U267: Significance F | AD267: df | AE267: SS | AF267: MS | AG267: F | AH267: Significance F | AQ267: df | AR267: SS | AS267: MS | AT267: F | AU267: Significance F | BD267: df | BE267: SS | BF267: MS | BG267: F | BH267: Significance F
C268: Regression | D268: 1 | E268: 0.008130993 | F268: 0.008130993 | G268: 57.312989 | H268: 7.5454266e-13 | P268: Regression | Q268: 1 | R268: 0.0003297077 | S268: 0.0003297077 | T268: 1.5770682 | U268: 0.21037979 | AC268: Regression | AD268: 1 | AE268: 0.008864762 | AF268: 0.008864762 | AG268: 47.534346 | AH268: 4.5608142e-11 | AP268: Regression | AQ268: 1 | AR268: 0.021817716 | AS268: 0.021817716 | AT268: 88.668792 | AU268: 3.6028101e-18 | BC268: Regression | BD268: 1 | BE268: 0.011925828 | BF268: 0.011925828 | BG268: 41.997167 | BH268: 4.9815457e-10
C269: Residual | D269: 245 | E269: 0.034758147 | F269: 0.00014186999 | P269: Residual | Q269: 245 | R269: 0.051220607 | S269: 0.0002090637 | AC269: Residual | AD269: 245 | AE269: 0.045690472 | AF269: 0.00018649172 | AP269: Residual | AQ269: 245 | AR269: 0.060284348 | AS269: 0.00024605856 | BC269: Residual | BD269: 245 | BE269: 0.069572024 | BF269: 0.00028396745
C270: Total | D270: 246 | E270: 0.04288914 | P270: Total | Q270: 246 | R270: 0.051550314 | AC270: Total | AD270: 246 | AE270: 0.054555234 | AP270: Total | AQ270: 246 | AR270: 0.082102064 | BC270: Total | BD270: 246 | BE270: 0.081497853
D272: Coefficients | E272: Standard Error | F272: t Stat | G272: P-value | H272: Lower 95% | I272: Upper 95% | J272: Lower 95.0% | K272: Upper 95.0% | Q272: Coefficients | R272: Standard Error | S272: t Stat | T272: P-value | U272: Lower 95% | V272: Upper 95% | W272: Lower 95.0% | X272: Upper 95.0% | AD272: Coefficients | AE272: Standard Error | AF272: t Stat | AG272: P-value | AH272: Lower 95% | AI272: Upper 95% | AJ272: Lower 95.0% | AK272: Upper 95.0% | AQ272: Coefficients | AR272: Standard Error | AS272: t Stat | AT272: P-value | AU272: Lower 95% | AV272: Upper 95% | AW272: Lower 95.0% | AX272: Upper 95.0% | BD272: Coefficients | BE272: Standard Error | BF272: t Stat | BG272: P-value | BH272: Lower 95% | BI272: Upper 95% | BJ272: Lower 95.0% | BK272: Upper 95.0%
C273: Intercept | D273: -0.000272018 | E273: 0.00075811945 | F273: -0.35880626 | G273: 0.72004904 | H273: -0.0017652813 | I273: 0.0012212453 | J273: -0.0017652813 | K273: 0.0012212453 | P273: Intercept | Q273: 0.00044324213 | R273: 0.00092030481 | S273: 0.48162535 | T273: 0.63050203 | U273: -0.0013694767 | V273: 0.0022559609 | W273: -0.0013694767 | X273: 0.0022559609 | AC273: Intercept | AD273: 0.00020330211 | AE273: 0.00086920488 | AF273: 0.23389435 | AG273: 0.81526232 | AH273: -0.0015087655 | AI273: 0.0019153697 | AJ273: -0.0015087655 | AK273: 0.0019153697 | AP273: Intercept | AQ273: 0.00032457672 | AR273: 0.0009984162 | AS273: 0.3250916 | AT273: 0.74538918 | AU273: -0.0016419976 | AV273: 0.002291151 | AW273: -0.0016419976 | AX273: 0.002291151 | BC273: Intercept | BD273: -0.00029995793 | BE273: 0.0010725725 | BF273: -0.27966215 | BG273: 0.77997268 | BH273: -0.0024125975 | BI273: 0.0018126816 | BJ273: -0.0024125975 | BK273: 0.0018126816
C274: X Variable 1 | D274: 0.64748944 | E274: 0.085527575 | F274: 7.5705343 | G274: 7.5454266e-13 | H274: 0.47902629 | I274: 0.81595258 | J274: 0.47902629 | K274: 0.81595258 | P274: X Variable 1 | Q274: 0.13038434 | R274: 0.10382459 | S274: 1.2558137 | T274: 0.21037979 | U274: -0.074118314 | V274: 0.334887 | W274: -0.074118314 | X274: 0.334887 | AC274: X Variable 1 | AD274: 0.67607431 | AE274: 0.098059726 | AF274: 6.8945156 | AG274: 4.5608142e-11 | AH274: 0.48292667 | AI274: 0.86922196 | AJ274: 0.48292667 | AK274: 0.86922196 | AP274: X Variable 1 | AQ274: 1.060634 | AR274: 0.11263676 | AS274: 9.4164108 | AT274: 3.6028101e-18 | AU274: 0.83877404 | AV274: 1.2824939 | AW274: 0.83877404 | AX274: 1.2824939 | BC274: X Variable 1 | BD274: 0.78416087 | BE274: 0.12100273 | BF274: 6.4805221 | BG274: 4.9815457e-10 | BH274: 0.54582253 | BI274: 1.0224992 | BJ274: 0.54582253 | BK274: 1.0224992

Sheet RM
B2: Returns on Markets
B3: Year | C3: Annual
B4: 2000 | C4: -0.1465 | E4: Average Return | F4: =AVERAGE(C4:C28) -> 0.153348
B5: 2001 | C5: -0.1618 | E5: Dividend Yield | F5: 1.35 1
B6: 2002 | C6: 0.0325 | E6: Total Market Return | F6: =SUM(F4:F5) -> 0.153348
B7: 2003 | C7: 0.719
B8: 2004 | C8: 0.1068
B9: 2005 | C9: 0.3634
B10: 2006 | C10: 0.3983
B11: 2007 | C11: 0.5477
B12: 2008 | C12: -0.5179
B13: 2009 | C13: 0.7576
B14: 2010 | C14: 0.1795
B15: 2011 | C15: -0.2462
B16: 2012 | C16: 0.277
B17: 2013 | C17: 0.0676
B18: 2014 | C18: 0.3139
... B28: 2024 | C28: 0.0875

Sheet WACC
B2: Peer Comps
H3: Debt/ | I3: Debt/ | J3: Levered | K3: Unlevered
B4: Name of the Comp | D4: Country | E4: Total Debt | F4: Total Equity | G4: Tax Rate 1 | H4: Equity | I4: Capital | J4: Beta 2 | K4: Beta 3
B6: TCS | D6: India | E6: 10932 | F6: 1191942.7 | G6: 0.25 | H6: =E6/F6 -> 0.0091715817 | I6: =E6/(E6+F6) -> 0.0090882282 | J6: =Beta!M3 -> 0.64748944 | K6: =J6/(1+(1-G6)*H6) -> 0.64306599
B7: Infosys | D7: India | E7: 8755 | F7: 678471 | G7: 0.29 | H7: =E7/F7 -> 0.012904015 | I7: =E7/(E7+F7) -> 0.012739623 | J7: =Beta!Z3 -> 0.13038434 | K7: =J7/(1+(1-G7)*H7) -> 0.12920063
B8: HCL Technologies | D8: India | E8: 6780 | F8: 445013.97 | G8: 0.25 | H8: =E8/F8 -> 0.015235477 | I8: =E8/(E8+F8) -> 0.01500684 | J8: =Beta!AM3 -> 0.67607431 | K8: =J8/(1+(1-G8)*H8) -> 0.66843635
B9: Wipro | D9: India | E9: 16163.7 | F9: 276849.31 | G9: 0.24 | H9: =E9/F9 -> 0.058384469 | I9: =E9/(E9+F9) -> 0.055163762 | J9: =Beta!AZ3 -> 1.060634 | K9: =J9/(1+(1-G9)*H9) -> 1.0155709
B10: LTIMindtree | D10: India | E10: 2382.6 | F10: 182948.71 | G10: 0.26 | H10: =E10/F10 -> 0.013023322 | I10: =E10/(E10+F10) -> 0.012855896 | J10: =Beta!BM3 -> 0.78416087 | K10: =J10/(1+(1-G10)*H10) -> 0.77667585
F12: Average | G12: =AVERAGE(G6:G10) -> 0.258 | H12: =AVERAGE(H6:H10) -> 0.021743773 | I12: =AVERAGE(I6:I10) -> 0.02097087 | J12: =AVERAGE(J6:J10) -> 0.65974859 | K12: =AVERAGE(K6:K10) -> 0.64658994
F13: Median | G13: =MEDIAN(G6:G10) -> 0.25 | H13: =MEDIAN(H6:H10) -> 0.013023322 | I13: =MEDIAN(I6:I10) -> 0.012855896 | J13: =MEDIAN(J6:J10) -> 0.67607431 | K13: =MEDIAN(K6:K10) -> 0.66843635
B15: Cost of Debt | G15: Cost of Equity
B17: Pre -Tax Cost of Debt | E17: =416/E7 -> 0.047515705 | G17: Risk Free Rate | K17: 0.06606
B18: Tax Rate | E18: =G7 -> 0.29 | G18: Equity Risk Premium | K18: =RM!F6-WACC!K17 -> 0.087288
B19: Post Tax Cost of Debt | E19: =E17*(1-E18) -> 0.033736151 | G19: Levered Beta 4 | K19: =K27 -> 0.6786021
G20: Cost of Equity | K20: =K17+(K18-K17)*K19 -> 0.080465365
B22: Capital Structure | G22: Levered Beta
D24: Current | E24: Target | G24: Comps Median Unlevered Beta | K24: =K13 -> 0.66843635
B25: Total Debt | C25: =E7 -> 8755 | D25: =C25/$C$27 -> 0.012739623 | E25: =I12 -> 0.02097087 | G25: Target Debt/Equity | K25: =E29 -> 0.021420067
B26: Market Capitalization (Total Equity) | C26: =F7 -> 678471 | D26: =C26/$C$27 -> 0.98726038 | E26: =E27-E25 -> 0.97902913 | G26: Tax Rate | K26: =E18 -> 0.29
B27: Total Capital | C27: =SUM(C25:C26) -> 687226 | D27: =C27/$C$27 -> 1 | E27: =D27 -> 1 | G27: Levered Beta | K27: =K24*(1+(1-K26)*K25) -> 0.6786021
B29: Debt/Equity | D29: =D25/D26 -> 0.012904015 | E29: =E25/E26 -> 0.021420067 | G29: Weighted Average Cost of Capital
G31: Cost of Equity | K31: =K20 -> 0.080465365
G32: Equity Weight | K32: =E26 -> 0.97902913
G34: Cost of Debt | K34: =E19 -> 0.033736151
G35: Debt Weight | K35: =E25 -> 0.02097087
G37: WACC | K37: =(K31*K32)+(K34*K35) -> 0.079485413

Sheet Historical Approch
A2: # | B2: Date | C2: Close | D2: Return | E2: Shorted Return | G2: Calculating of Value at Risk- Tata Consultancy Services Ltd (Historical)
B3: 46014 | C3: 18.57 | D3: =(C3-C4)/C4 -> -0.030793328 | E3: -0.0053562068
B4: 46013 | C4: 19.16 | D4: =(C4-C5)/C5 -> -0.052423319 | E4: 0.031771683 | G4: Mean | J4: =AVERAGE(E3:E5976) -> -0.00020638196
B5: 46010 | C5: 20.219999 | D5: =(C5-C6)/C6 -> 0.054223097 | E5: 0.055323563 | G5: Standard Diviation | J5: =_xlfn.STDEV.S(E3:E5976) -> 0.022509698
B6: 46009 | C6: 19.18 | D6: =(C6-C7)/C7 -> 0.052689409 | E6: -0.051434176 | G6: Min | J6: =MIN(E3:E5976) -> -0.18976617
B7: 46008 | C7: 18.219999 | D7: =(C7-C8)/C8 -> 0.025323514 | E7: -0.050052189 | G7: Max | J7: =MAX(E3:E5976) -> 0.4740368
B8: 46007 | C8: 17.77 | D8: =(C8-C9)/C9 -> -0.00056244255 | E8: -0.024698072 | G8: CMP | J8: 1617.9
B9: 46006 | C9: 17.780001 | D9: =(C9-C10)/C10 -> 0 | E9: 0.00056275907
B10: 46003 | C10: 17.780001 | D10: =(C10-C11)/C11 -> -0.0011235141 | E10: 0
B11: 46002 | C11: 17.799999 | D11: =(C11-C12)/C12 -> -0.014941918 | E11: 0.0011247778 | G11: Historical Approach
B12: 46001 | C12: 18.07 | D12: =(C12-C13)/C13 -> 0.018028152 | E12: 0.015168566 | G12: Percentile | H12: Confidence | I12: VAR % | J12: Stock Price | K12: VAR (INR)
B13: 46000 | C13: 17.75 | D13: =(C13-C14)/C14 -> 0.0016930411 | E13: -0.017708893 | G13: 0.05 | H13: =100%-G13 -> 0.95 | I13: =_xlfn.PERCENTILE.INC($E$3:$E$5976,G13) -> -0.03144404 | J13: =$J$8*(1-I13) -> 1668.7733 | K13: =$J$8-J13 -> -50.873313
B14: 45999 | C14: 17.719999 | D14: =(C14-C15)/C15 -> -0.019369142 | E14: -0.0016901795 | G14: 0.01 | H14: =100%-G14 -> 0.99 | I14: =_xlfn.PERCENTILE.INC($E$3:$E$5976,G14) -> -0.05606868 | J14: =$J$8*(1-I14) -> 1708.6135 | K14: =$J$8-J14 -> -90.713518
B15: 45996 | C15: 18.07 | D15: =(C15-C16)/C16 -> -0.012028497 | E15: 0.019751715 | G15: 0.005 | H15: =100%-G15 -> 0.995 | I15: =_xlfn.PERCENTILE.INC($E$3:$E$5976,G15) -> -0.073551793 | J15: =$J$8*(1-I15) -> 1736.8994 | K15: =$J$8-J15 -> -118.99945
B16: 45995 | C16: 18.290001 | D16: =(C16-C17)/C17 -> 0.0356739 | E16: 0.012174943 | G16: 0.1 | H16: =100%-G16 -> 0.9 | I16: =_xlfn.PERCENTILE.INC($E$3:$E$5976,G16) -> -0.0230361 | J16: =$J$8*(1-I16) -> 1655.1701 | K16: =$J$8-J16 -> -37.270106
B17: 45994 | C17: 17.66 | D17: =(C17-C18)/C18 -> 0.014359564 | E17: -0.034445109
B18: 45993 | C18: 17.41 | D18: =(C18-C19)/C19 -> -0.002292316 | E18: -0.014156286
B19: 45992 | C19: 17.450001 | D19: =(C19-C20)/C20 -> -0.0017161774 | E19: 0.0022975828
B20: 45989 | C20: 17.48 | D20: =(C20-C21)/C21 -> 0.0034442862 | E20: 0.0017191277
B21: 45987 | C21: 17.42 | D21: =(C21-C22)/C22 -> 0.0081018162 | E21: -0.0034324638
B22: 45986 | C22: 17.280001 | D22: =(C22-C23)/C23 -> 0.00057905203 | E22: -0.0080367043
B23: 45985 | C23: 17.27 | D23: =(C23-C24)/C24 -> -0.024293802 | E23: -0.00057871693
B24: 45982 | C24: 17.700001 | D24: =(C24-C25)/C25 -> 0.033275051 | E24: 0.024898685
B25: 45981 | C25: 17.129999 | D25: =(C25-C26)/C26 -> -0.010398631 | E25: -0.032203479
B26: 45980 | C26: 17.309999 | D26: =(C26-C27)/C27 -> 0.021238861 | E26: 0.010507899
B27: 45979 | C27: 16.950001 | D27: =(C27-C28)/C28 -> 0.01073347 | E27: -0.020797153
B28: 45978 | C28: 16.77 | D28: =(C28-C29)/C29 -> 0.0072072578 | E28: -0.010619487
... B5976: 37347 | C5976: 1.2392659 | D5976: =(C5976-C5977)/C5977 -> #DIV/0! | E5976: 0.0060173013

Sheet Monte Carlo Stimulation
A2: # | B2: Date | C2: Close | D2: Return | E2: Shorted Return | G2: Replication | H2: Stimulation Return | J2: Calculating of Value at Risk- INFOSYS (Monte Carlo Stimulation)
B3: 46014 | C3: 18.57 | D3: =(C3-C4)/C4 -> -0.030793328 | E3: -0.0053562068 | G3: 1 | H3: =_xlfn.NORM.INV(RAND(),N$5,N$6) -> 0.016634079
B4: 46013 | C4: 19.16 | D4: =(C4-C5)/C5 -> -0.052423319 | E4: 0.031771683 | G4: 2 | H4: =_xlfn.NORM.INV(RAND(),N$5,N$6) -> -0.023803872 | J4: Historical Approach
B5: 46010 | C5: 20.219999 | D5: =(C5-C6)/C6 -> 0.054223097 | E5: 0.055323563 | G5: 3 | H5: =_xlfn.NORM.INV(RAND(),N$5,N$6) -> 0.01176887 | J5: Mean | N5: =AVERAGE(E3:E5976) -> -0.00020638196
B6: 46009 | C6: 19.18 | D6: =(C6-C7)/C7 -> 0.052689409 | E6: -0.051434176 | G6: 4 | H6: =_xlfn.NORM.INV(RAND(),N$5,N$6) -> -0.0058572192 | J6: Standard Diviation | N6: =_xlfn.STDEV.S(E3:E5976) -> 0.022509698
B7: 46008 | C7: 18.219999 | D7: =(C7-C8)/C8 -> 0.025323514 | E7: -0.050052189 | G7: 5 | H7: =_xlfn.NORM.INV(RAND(),N$5,N$6) -> -0.0027765385 | J7: Min | N7: =MIN(E3:E5976) -> -0.18976617
B8: 46007 | C8: 17.77 | D8: =(C8-C9)/C9 -> -0.00056244255 | E8: -0.024698072 | G8: 6 | H8: =_xlfn.NORM.INV(RAND(),N$5,N$6) -> 0.023644128 | J8: Max | N8: =MAX(E3:E5976) -> 0.4740368
B9: 46006 | C9: 17.780001 | D9: =(C9-C10)/C10 -> 0 | E9: 0.00056275907 | G9: 7 | H9: =_xlfn.NORM.INV(RAND(),N$5,N$6) -> -0.028326161 | J9: CMP | N9: 1617.9
B10: 46003 | C10: 17.780001 | D10: =(C10-C11)/C11 -> -0.0011235141 | E10: 0 | G10: 8 | H10: =_xlfn.NORM.INV(RAND(),N$5,N$6) -> 0.017235019
B11: 46002 | C11: 17.799999 | D11: =(C11-C12)/C12 -> -0.014941918 | E11: 0.0011247778 | G11: 9 | H11: =_xlfn.NORM.INV(RAND(),N$5,N$6) -> 0.02660014 | J11: Monte Carlo Simulation
B12: 46001 | C12: 18.07 | D12: =(C12-C13)/C13 -> 0.018028152 | E12: 0.015168566 | G12: 10 | H12: =_xlfn.NORM.INV(RAND(),N$5,N$6) -> -0.011431225 | J12: Mean | N12: =AVERAGE(H3:H6002) -> -0.00045561802
B13: 46000 | C13: 17.75 | D13: =(C13-C14)/C14 -> 0.0016930411 | E13: -0.017708893 | G13: 11 | H13: =_xlfn.NORM.INV(RAND(),N$5,N$6) -> 0.028071601 | J13: Standard Diviation | N13: =_xlfn.STDEV.S(H3:H6002) -> 0.02273466
B14: 45999 | C14: 17.719999 | D14: =(C14-C15)/C15 -> -0.019369142 | E14: -0.0016901795 | G14: 12 | H14: =_xlfn.NORM.INV(RAND(),N$5,N$6) -> 0.0044158411 | J14: Min | N14: =MIN(H3:H6002) -> -0.078740552
B15: 45996 | C15: 18.07 | D15: =(C15-C16)/C16 -> -0.012028497 | E15: 0.019751715 | G15: 13 | H15: =_xlfn.NORM.INV(RAND(),N$5,N$6) -> -0.023939966 | J15: Max | N15: =MAX(H3:H6002) -> 0.092569764
B16: 45995 | C16: 18.290001 | D16: =(C16-C17)/C17 -> 0.0356739 | E16: 0.012174943 | G16: 14 | H16: =_xlfn.NORM.INV(RAND(),N$5,N$6) -> 0.0029521892 | J16: CMP | N16: 1617.9
B17: 45994 | C17: 17.66 | D17: =(C17-C18)/C18 -> 0.014359564 | E17: -0.034445109 | G17: 15 | H17: =_xlfn.NORM.INV(RAND(),N$5,N$6) -> 0.00044713248
B18: 45993 | C18: 17.41 | D18: =(C18-C19)/C19 -> -0.002292316 | E18: -0.014156286 | G18: 16 | H18: =_xlfn.NORM.INV(RAND(),N$5,N$6) -> 0.014592993
B19: 45992 | C19: 17.450001 | D19: =(C19-C20)/C20 -> -0.0017161774 | E19: 0.0022975828 | G19: 17 | H19: =_xlfn.NORM.INV(RAND(),N$5,N$6) -> -0.072048234 | J19: Monte Carlo Simulation
B20: 45989 | C20: 17.48 | D20: =(C20-C21)/C21 -> 0.0034442862 | E20: 0.0017191277 | G20: 18 | H20: =_xlfn.NORM.INV(RAND(),N$5,N$6) -> 0.018118495 | J20: Percentile | K20: Confidence | L20: VAR % | M20: Stock Price | N20: VAR (INR)
B21: 45987 | C21: 17.42 | D21: =(C21-C22)/C22 -> 0.0081018162 | E21: -0.0034324638 | G21: 19 | H21: =_xlfn.NORM.INV(RAND(),N$5,N$6) -> -0.028698801 | J21: 0.05 | K21: =100%-J21 -> 0.95 | L21: =_xlfn.PERCENTILE.INC($H$3:$H$6002,J21) -> -0.038043606 | M21: =$N$9*(1-L21) -> 1679.4508 | N21: =$N$9-M21 -> -61.550751
B22: 45986 | C22: 17.280001 | D22: =(C22-C23)/C23 -> 0.00057905203 | E22: -0.0080367043 | G22: 20 | H22: =_xlfn.NORM.INV(RAND(),N$5,N$6) -> 0.020707215 | J22: 0.01 | K22: =100%-J22 -> 0.99 | L22: =_xlfn.PERCENTILE.INC($H$3:$H$6002,J22) -> -0.052909412 | M22: =$N$9*(1-L22) -> 1703.5021 | N22: =$N$9-M22 -> -85.602138
B23: 45985 | C23: 17.27 | D23: =(C23-C24)/C24 -> -0.024293802 | E23: -0.00057871693 | G23: 21 | H23: =_xlfn.NORM.INV(RAND(),N$5,N$6) -> -0.0038044315 | J23: 0.005 | K23: =100%-J23 -> 0.995 | L23: =_xlfn.PERCENTILE.INC($H$3:$H$6002,J23) -> -0.059276074 | M23: =$N$9*(1-L23) -> 1713.8028 | N23: =$N$9-M23 -> -95.90276
B24: 45982 | C24: 17.700001 | D24: =(C24-C25)/C25 -> 0.033275051 | E24: 0.024898685 | G24: 22 | H24: =_xlfn.NORM.INV(RAND(),N$5,N$6) -> -0.018373048 | J24: 0.1 | K24: =100%-J24 -> 0.9 | L24: =_xlfn.PERCENTILE.INC($H$3:$H$6002,J24) -> -0.029778625 | M24: =$N$9*(1-L24) -> 1666.0788 | N24: =$N$9-M24 -> -48.178838
B25: 45981 | C25: 17.129999 | D25: =(C25-C26)/C26 -> -0.010398631 | E25: -0.032203479 | G25: 23 | H25: =_xlfn.NORM.INV(RAND(),N$5,N$6) -> -0.0027203598
B26: 45980 | C26: 17.309999 | D26: =(C26-C27)/C27 -> 0.021238861 | E26: 0.010507899 | G26: 24 | H26: =_xlfn.NORM.INV(RAND(),N$5,N$6) -> 0.0067154935
B27: 45979 | C27: 16.950001 | D27: =(C27-C28)/C28 -> 0.01073347 | E27: -0.020797153 | G27: 25 | H27: =_xlfn.NORM.INV(RAND(),N$5,N$6) -> 0.03487493
B28: 45978 | C28: 16.77 | D28: =(C28-C29)/C29 -> 0.0072072578 | E28: -0.010619487 | G28: 26 | H28: =_xlfn.NORM.INV(RAND(),N$5,N$6) -> 0.0059676149
B29: 45975 | C29: 16.65 | D29: =(C29-C30)/C30 -> -0.018278271 | E29: -0.0071556849 | G29: 27 | H29: =_xlfn.NORM.INV(RAND(),N$5,N$6) -> -0.039627802
B30: 45974 | C30: 16.959999 | D30: =(C30-C31)/C31 -> -0.00760685 | E30: 0.018618587 | G30: 28 | H30: =_xlfn.NORM.INV(RAND(),N$5,N$6) -> 0.021282547
B31: 45973 | C31: 17.09 | D31: =(C31-C32)/C32 -> 0.0047031113 | E31: 0.0076651577 | G31: 29 | H31: =_xlfn.NORM.INV(RAND(),N$5,N$6) -> 0.01768653
B32: 45972 | C32: 17.01 | D32: =(C32-C33)/C33 -> 0.014916468 | E32: -0.0046810956 | G32: 30 | H32: =_xlfn.NORM.INV(RAND(),N$5,N$6) -> -0.015588533
B33: 45971 | C33: 16.76 | D33: =(C33-C34)/C34 -> 0.01575759 | E33: -0.014697237 | G33: 31 | H33: =_xlfn.NORM.INV(RAND(),N$5,N$6) -> 0.016244852
B34: 45968 | C34: 16.5 | D34: =(C34-C35)/C35 -> 0.019777484 | E34: -0.01551314 | G34: 32 | H34: =_xlfn.NORM.INV(RAND(),N$5,N$6) -> 0.015478257
B35: 45967 | C35: 16.18 | D35: =(C35-C36)/C36 -> -0.014616308 | E35: -0.019393921 | G35: 33 | H35: =_xlfn.NORM.INV(RAND(),N$5,N$6) -> -0.003646757
B36: 45966 | C36: 16.42 | D36: =(C36-C37)/C37 -> 0.007362015 | E36: 0.014833113 | G36: 34 | H36: =_xlfn.NORM.INV(RAND(),N$5,N$6) -> 0.011521539
... B5976: 37347 | C5976: 1.2392659 | D5976: =(C5976-C5977)/C5977 -> #DIV/0! | E5976: 0.0060173013 | G5976: 5974 | H5976: =_xlfn.NORM.INV(RAND(),N$5,N$6) -> -0.014583485
G5977: 5975 | H5977: =_xlfn.NORM.INV(RAND(),N$5,N$6) -> -0.028206008
G5978: 5976 | H5978: =_xlfn.NORM.INV(RAND(),N$5,N$6) -> -0.0075797401
G5979: 5977 | H5979: =_xlfn.NORM.INV(RAND(),N$5,N$6) -> -0.003108205
G5980: 5978 | H5980: =_xlfn.NORM.INV(RAND(),N$5,N$6) -> -0.0048776586
G5981: 5979 | H5981: =_xlfn.NORM.INV(RAND(),N$5,N$6) -> 0.0004828289
G5982: 5980 | H5982: =_xlfn.NORM.INV(RAND(),N$5,N$6) -> 0.026867945
G5983: 5981 | H5983: =_xlfn.NORM.INV(RAND(),N$5,N$6) -> 0.0059689252
G5984: 5982 | H5984: =_xlfn.NORM.INV(RAND(),N$5,N$6) -> 0.0067861982
G5985: 5983 | H5985: =_xlfn.NORM.INV(RAND(),N$5,N$6) -> -0.018637838
G5986: 5984 | H5986: =_xlfn.NORM.INV(RAND(),N$5,N$6) -> -0.0036162649
G5987: 5985 | H5987: =_xlfn.NORM.INV(RAND(),N$5,N$6) -> -0.0077209745
G5988: 5986 | H5988: =_xlfn.NORM.INV(RAND(),N$5,N$6) -> -0.015117742
... G6002: 6000 | H6002: =_xlfn.NORM.INV(RAND(),N$5,N$6) -> 0.017820844
